Workbook

Sheet Legenda
A1: Planejamento de Produto e Desenvolvimento — Confecção HMZT
A3: Fonte | B3: Prints das páginas da Lunfe Malhas (29–30/09/2026) + textos "Descrição Geral" colados pelo Angelo. Fichas em docs/shop-confeccao/catalogo, dossiês em /dossies, prompts em /prompts.
A4: Abas | B4: Resumo · Regras Fornecedor · uma aba por produto (P01–P29) · Não Catalogados · Pendências Gerais · Prompts Lookbook (um prompt por foto)
A6: Convenção de cores
A7: Texto azul | B7: Valor digitado (dado do fornecedor ou estimativa). Pode ser editado.
A8: Texto preto | B8: Fórmula — não editar.
A9: Texto verde | B9: Fórmula que puxa de outra aba.
A10: Fundo amarelo | B10: Estimativa HMZT ou campo a preencher — revisar quando chegar o orçamento real.
A11: Fundo vermelho claro | B11: Contradição, risco ou dado faltando.
A13: Marcas nas tabelas
A14: ✅ | B14: Dado técnico declarado pelo fornecedor
A15: 📣 | B15: Alegação de marketing do fornecedor — NÃO usar como fato na comunicação HMZT
A16: ⚠️ | B16: Contradição ou erro encontrado
A17: 🟢 | B17: Recomendação HMZT
A19: Como usar | B19: 1) Atualize descontos/Pix em "Regras Fornecedor" — todas as abas recalculam. 2) Em cada produto, preencha os custos amarelos (personalização, frete, embalagem, impostos) quando chegarem os orçamentos. 3) Ajuste o preço de venda HMZT e veja a margem.

Sheet Resumo
A1: Resumo do catálogo — 29 produtos Lunfe
A3: Produto | B3: Categoria | C3: Código HMZT | D3: Nome | E3: Linha HMZT | F3: Modelagem | G3: Tecido | H3: Gramatura | I3: Composição | J3: Nº cores | K3: Preço base | L3: Lote 20 + Pix | M3: Topo (300+) | N3: Custo HMZT est. | O3: Preço venda HMZT | P3: Margem bruta % | Q3: Risco / atenção
A4: P01 | B4: Camiseta | C4: HMZT-P01-OVS-SUE300 | D4: Camiseta Oversized Suedine Peruano 300g | E4: Heavy (oversized) | F4: Oversized | G4: Suedine | H4: 300 g/m² | I4: 52% CO / 48% PES | J4: 3 | K4: =P01!$B$47 | L4: =P01!E49 | M4: =P01!D53 | N4: =P01!B59 | O4: =P01!B60 | P4: =P01!B63 | Q4: "Peruano" no nome não é algodão peruano
A5: P02 | B5: Camiseta | C5: HMZT-P02-OVS-ALG185 | D5: Camiseta Oversized Drop Shoulder Algodão Penteado 185g | E5: Essencial — oversized (drops com estampa, eventos) | F5: Oversized drop shoulder — ombro caído, corpo amplo, comprimento alongado | G5: Meia malha lisa, sem acabamento especial | H5: 185 g/m² (resumo do topo diz 300 g/m²) | I5: 100% algodão penteado | J5: 2 | K5: =P02!$B$64 | L5: =P02!E66 | M5: =P02!D70 | N5: =P02!B76 | O5: =P02!B77 | P5: =P02!B80 | Q5: Resumo do topo diz '100% Algodão Penteado 300g/m²'; ficha técnica e FAQ dizem 185 g/m².
A6: P03 | B6: Camiseta | C6: HMZT-P03-REG-PIM165 | D6: Camiseta Pima Cotton 165g | E6: Premium (principal) | F6: Regular | G6: Pima | H6: 165 g/m² | I6: 100% Pima | J6: 8 | K6: =P03!$B$61 | L6: =P03!E63 | M6: =P03!D67 | N6: =P03!B73 | O6: =P03!B74 | P6: =P03!B77 | Q6: Comprovar Pima
A7: P04 | B7: Camiseta | C7: HMZT-P04-REG-SUE300 | D7: Camiseta Suedine Peruano 300g Regular Fit | E7: Heavy (principal) | F7: Regular | G7: Suedine | H7: 300 g/m² | I7: 52% CO / 48% PES | J7: 5 | K7: =P04!$B$57 | L7: =P04!E59 | M7: =P04!D63 | N7: =P04!B69 | O7: =P04!B70 | P7: =P04!B73 | Q7: "Peruano" no nome; cartela divergente
A8: P05 | B8: Camiseta | C8: HMZT-P05-REG-XJG300 / -OVS- | D8: Camiseta Chinese Heavyweight 300g | E8: Heavy (alternativa ⚠️ Xinjiang) | F8: Regular + Oversized | G8: Algodão Xinjiang 2 cabos | H8: 300 g/m² | I8: 100% CO | J8: 4 | K8: =P05!$B$65 | L8: =P05!E67 | M8: =P05!D71 | N8: =P05!B77 | O8: =P05!B78 | P8: =P05!B81 | Q8: Origem Xinjiang
A9: P06 | B9: Camiseta | C9: HMZT-P06-REG-XJG160 | D9: Camiseta Chinese Cotton 160g | E9: Essencial (alternativa ⚠️ Xinjiang) | F9: Regular | G9: Algodão Xinjiang | H9: 160 g/m² ⚠️ | I9: 100% CO | J9: 5 | K9: =P06!$B$56 | L9: =P06!E58 | M9: =P06!D62 | N9: =P06!B68 | O9: =P06!B69 | P9: =P06!B72 | Q9: Origem Xinjiang; 160 × 180 g
A10: P07 | B10: Camiseta | C10: HMZT-P07-REG-PER220 | D10: Camiseta Cotton Peruano 220g com Elastano | E10: Premium (alternativa) | F10: Regular | G10: Algodão peruano + elastano | H10: 220 g/m² | I10: 96% CO / 4% EL | J10: 6 | K10: =P07!$B$59 | L10: =P07!E61 | M10: =P07!D65 | N10: =P07!B71 | O10: =P07!B72 | P10: =P07!B75 | Q10: Esgotado na página; variedade do algodão
A11: P08 | B11: Camiseta | C11: HMZT-P08-REG-EGY50 | D11: Camiseta Egyptian Cotton Fio 50/1 com Elastano | E11: Topo / Assinatura (inclui unissex) | F11: Regular | G11: Algodão egípcio 50/1 + elastano | H11: 170 g/m² | I11: 91,5% CO / 8,5% EL | J11: 7 | K11: =P08!$B$58 | L11: =P08!E60 | M11: =P08!D64 | N11: =P08!B70 | O11: =P08!B71 | P11: =P08!B74 | Q11: Comprovar egípcio; nº OEKO-TEX
A12: P09 | B12: Camiseta | C12: HMZT-P09-REG-SUELT | D12: Camiseta Suedine Light | E12: Suedine light | F12: Regular | G12: Suedine light | H12: não informada ⚠️ | I12: algodão + sintético (% ?) | J12: 5 | K12: =P09!$B$50 | L12: =P09!E52 | M12: =P09!D56 | N12: =P09!B62 | O12: =P09!B63 | P12: =P09!B66 | Q12: Faltam gramatura e composição
A13: P10 | B13: Camiseta | C13: HMZT-P10-OVS-SUEALG300 | D13: Camiseta Oversized Básica Suedine 300GSM (100% algodão) | E13: Heavy — oversized (alternativa mais barata à P01) | F13: True oversized boxy, ombros caídos | G13: Malha suedine 'interlock de dupla frontura' | H13: 300 g/m², zero transparência | I13: 100% algodão (P01, também suedine 300g, é 52/48) | J13: 6 | K13: =P10!$B$48 | L13: =P10!E50 | M13: =P10!D54 | N13: =P10!B60 | O13: =P10!B61 | P13: =P10!B64 | Q13: Composição 100% algodão, R$ 42,00 × P01 (Oversized Suedine Peruano 300g) 52% algodão/48% poliéster, R$ 54,00.
A14: P11 | B14: Camiseta | C14: HMZT-P11-REG-PA160 | D14: Camiseta Custo Inteligente Malha Algodão/Poliéster 160g | E14: Uniformes & Eventos (B2B) — fora da vitrine | F14: Regular fit | G14: — | H14: 160 g/m² | I14: Meia malha algodão + poliéster — % não informado | J14: 6 | K14: =P11!$B$60 | L14: =P11!E62 | M14: =P11!D66 | N14: =P11!B72 | O14: =P11!B73 | P14: =P11!B76 | Q14: Seletor da página: R$ 39,90. Descrição: base R$ 28,99 e 'a partir de R$ 20,29' (= 28,99 × 0,70).
A15: P12 | B15: Camiseta | C15: HMZT-P12-REG-BCI280 | D15: Camiseta Malhão Compact Algodão BCI 280g | E15: Heavy — regular 100% algodão | F15: Regular fit unissex (tabela masculina) | G15: — | H15: 280 g/m² | I15: 100% algodão BCI | J15: 8 | K15: =P12!$B$57 | L15: =P12!E59 | M15: =P12!D63 | N15: =P12!B69 | O15: =P12!B70 | P15: =P12!B73 | Q15: FAQ chama o fio 26/1 de 'fino'; 26/1 é mais grosso que 30/1.
A16: P13 | B16: Camiseta | C16: HMZT-P13-REG-EST175 | D16: Camiseta Estonada Regular 175g (Outras Cores) | E16: Lavada/Vintage (nova) — base regular | F16: Regular (tabela padrão Lunfe) | G16: — | H16: 175 g/m² (texto) × 180 GSM (banner da galeria) | I16: 100% algodão penteado | J16: 6 | K16: =P13!$B$57 | L16: =P13!E59 | M16: =P13!D63 | N16: =P13!B69 | O16: =P13!B70 | P16: =P13!B73 | Q16: P13 × P14 são quase duplicados. Mesma composição, gramatura, preço (R$ 37,26), tabela de desconto, tabela de medidas e sessão de fotos. Muda só o EAN (7897564701282 × 7892948548590), o título ("Vintage") e a cartela. O "-oc" do endereço provavelmente é "outras cores" (hipótese).
A17: P14 | B17: Camiseta | C17: HMZT-P14-REG-EST175 | D17: Camiseta Estonada Regular 175g | E17: Lavada/Vintage (nova) — base regular | F17: Regular (tabela padrão Lunfe) | G17: — | H17: 175 g/m² (texto) × 180 GSM (banner da galeria) | I17: 100% algodão penteado | J17: 6 | K17: =P14!$B$60 | L17: =P14!E62 | M17: =P14!D66 | N17: =P14!B72 | O17: =P14!B73 | P17: =P14!B76 | Q17: P14 × P13: o P13 é a mesma peça (mesma ficha, preço, medidas e fotos) com outro EAN e outra cartela — o texto do P13 até copia as cores do P14.
A18: P15 | B18: Camiseta | C18: HMZT-P15-REG-ESN175 | D18: Camiseta Estonada Neon Regular 175g | E18: Lavada/Vintage — cápsula de verão (drop) | F18: Regular (tabela padrão Lunfe) | G18: — | H18: 175 g/m² (texto) × 180 GSM (banner da galeria) | I18: 100% algodão penteado | J18: 6 | K18: =P15!$B$57 | L18: =P15!E59 | M18: =P15!D63 | N18: =P15!B69 | O18: =P15!B70 | P18: =P15!B73 | Q18: Neon + algodão: corante fluorescente em algodão tem solidez à luz baixa — desbota com sol e lavagem mais rápido que cor comum. O próprio FAQ recomenda "lavar do avesso em água fria para prolongar a intensidade", o que contradiz "vibração estável".
A19: P16 | B19: Camiseta | C19: HMZT-P16-OVS-EST175 | D19: Camiseta Estonada Oversized 175g | E19: Lavada/Vintage (nova) — base oversized | F19: Oversized (ombro caído, corpo amplo e alongado) | G19: — | H19: 175 g/m² (texto) × 180 GSM (banner da galeria) | I19: 100% algodão penteado | J19: 15 | K19: =P16!$B$65 | L19: =P16!E67 | M19: =P16!D71 | N19: =P16!B77 | O19: =P16!B78 | P19: =P16!B81 | Q19: Mangas × P17: o texto do P17 diz que a modelagem é idêntica, mas as mangas diferem (P16: 24–28 cm, +1 por tamanho; P17: 22–30 cm, +2 por tamanho).
A20: P17 | B20: Camiseta | C20: HMZT-P17-OVS-ESB175 | D20: Camiseta Estonada Oversized com Bolso 175g | E20: Lavada/Vintage — destaque oversized com bolso (após reposição) | F20: Oversized com bolso no peito | G20: — | H20: 175 g/m² (texto) × 180 GSM (banner da galeria) | I20: 100% algodão penteado | J20: 3 | K20: =P17!$B$55 | L20: =P17!E57 | M20: =P17!D61 | N20: =P17!B67 | O20: =P17!B68 | P20: =P17!B71 | Q20: Conferência com a página do P02: o comparativo do P02 diz "Estonada Oversized Bolso 175g, 100% algodão penteado 30/1, 3 cores, R$ 39,78" — bate com esta página ✅ (175 g, 30/1, Verde Musgo/Azul/Preto, base R$ 39,78, mínimo R$ 27,85). E o "Esse acabou" do P02 também bate: a própria página do P17 está esgotada (sem seletor, sem preço no topo). O P02 ainda diz "peso ao vestir: leve" e "volume de vendas alto" 📣.
A21: P18 | B21: Camiseta | C21: HMZT-P18-REG-RIB240 | D21: Camiseta Rib Wide Texture 240g — canelado largo vertical | E21: Textura (nova) — alternativa vertical; esgotada | F21: Regular fit | G21: Malha (tricô) texturizada — o texto chama de "tecelagem", termo errado para malha | H21: 240 g/m² | I21: 52% algodão + 48% poliéster | J21: 5 | K21: =P18!$B$63 | L21: =P18!E65 | M21: =P18!D69 | N21: =P18!B75 | O21: =P18!B76 | P21: =P18!B79 | Q21: Estoque: página diz "Esse acabou"; FAQ diz 5 cores em estoque com despacho em 24h.
A22: P19 | B22: Camiseta | C22: HMZT-P19-REG-PLS240 | D22: Camiseta Plissé Texture 240g — canelado vertical largo acetinado | E22: Textura (nova) — cápsula noturna / drop | F22: Regular fit | G22: Malha (tricô) texturizada — o texto chama de "tecelagem", termo errado para malha | H22: 240 g/m² | I22: 52% algodão + 48% poliéster | J22: 6 | K22: =P19!$B$64 | L22: =P19!E66 | M22: =P19!D70 | N22: =P19!B76 | O22: =P19!B77 | P22: =P19!B80 | Q22: Cores: o texto lista 5 cores sem cinza; o seletor da página mostra só Cinza e Preto; as fotos são cinza e preto.
A23: P20 | B23: Camiseta | C23: HMZT-P20-REG-RPL240 | D23: Camiseta Ripple Texture 240g — micro-ondulação horizontal | E23: Textura (nova) — base principal (quiet luxury, sob blazer) | F23: Regular fit | G23: Malha (tricô) texturizada — o texto chama de "tecelagem", termo errado para malha | H23: 240 g/m² | I23: 52% algodão + 48% poliéster | J23: 8 | K23: =P20!$B$65 | L23: =P20!E67 | M23: =P20!D71 | N23: =P20!B77 | O23: =P20!B78 | P23: =P20!B81 | Q23: Cores: texto (5) × seletor (6) × fotos (5) não batem; Azul, Verde e Cinza não existem no texto; Bege e Marinho não existem no seletor.
A24: P21 | B24: Camiseta | C24: HMZT-P21-REG-WFK240 | D24: Camiseta Waffle Knit Texture 240g — faixas trançadas horizontais | E24: Textura (nova) — casual de fim de semana e presente | F24: Regular fit | G24: Malha (tricô) texturizada — o texto chama de "tecelagem", termo errado para malha | H24: 240 g/m² | I24: 52% algodão + 48% poliéster | J24: 5 | K24: =P21!$B$62 | L24: =P21!E64 | M24: =P21!D68 | N24: =P21!B74 | O24: =P21!B75 | P24: =P21!B78 | Q24: Cores: seletor mostra Marrom, Preto, Off White; fotos mostram bege, preto, off-white; texto lista 5 cores.
A25: P22 | B25: Camiseta | C25: HMZT-P22-REG-PIQ240 | D25: Camiseta Piqué Texture 240g — micro-mesh | E25: Textura (nova) — piquê "old money" e uniforme B2B bordado | F25: Regular fit (oversized "em estudo") | G25: "Tecelagem piquê (interlock com relevo micro-mesh)" — piquê é malha de ponto carregado, não interlock nem tecelagem | H25: 240 g/m² (± 5%) | I25: 51% poliéster + 49% algodão (poliéster majoritário) | J25: 3 | K25: =P22!$B$62 | L25: =P22!E64 | M25: =P22!D68 | N25: =P22!B74 | O25: =P22!B75 | P25: =P22!B78 | Q25: Composição: 51% poliéster / 49% algodão — confirma o texto do P05; o texto do P04 (52% algodão / 48% poliéster) vale para Rib Wide, Plissé, Ripple e Waffle, não para a Piqué. São duas composições na mesma "linha texturizada".
A26: P23 | B26: Regata | C26: HMZT-P23-SLM-CAN21 | D26: Regata Masculina Canelada 2/1 Slim Fit (American Style) | E26: Regatas / Verão — Essencial (entrada, kit e cross-sell) | F26: Slim fit / American style (ajustada) | G26: Canelada rib knit 2/1, 'alta densidade de fios' | H26: Não informada | I26: 100% algodão (sem elastano — elasticidade é mecânica, da nervura) | J26: 5 | K26: =P23!$B$58 | L26: =P23!E60 | M26: =P23!D64 | N26: =P23!B70 | O26: =P23!B71 | P26: =P23!B74 | Q26: Estoque: página diz 'Esse acabou' (nenhuma variação selecionável); resumo diz 'Envio em até 24h'.
A27: P24 | B27: Regata | C27: HMZT-P24-SLM-CAN21SW | D27: Regata Estonada Canelada 2/1 Slim Fit (Stone Wash) | E27: Regatas / Verão — Vintage (drop streetwear, lavada) | F27: Slim fit atlético | G27: Canelada rib knit 2/1 (mesma base da P23) | H27: Não informada | I27: 100% algodão | J27: 4 | K27: =P24!$B$60 | L27: =P24!E62 | M27: =P24!D66 | N27: =P24!B72 | O27: =P24!B73 | P27: =P24!B76 | Q27: Preço invertido: a estonada (R$ 23,99) custa MENOS que a lisa P23 (R$ 24,99), apesar de ter uma etapa extra de lavanderia.
A28: P25 | B28: Calça | C28: HMZT-P25-CNF-MOL320 | D28: Calça Moletom 3 Cabos 320g Felpada Confort Fit | E28: Inverno Heavy — conjunto com o moletom P26 (calça avulsa como complemento) | F28: Confort fit 'levemente solta' — nas fotos: jogger com perna afunilada | G28: Moletom 3 cabos (triple ply) com felpado interno | H28: 320 g/m² (heavyweight) | I28: 50% algodão + 50% poliéster | J28: 4 | K28: =P25!$B$60 | L28: =P25!E62 | M28: =P25!D66 | N28: =P25!B72 | O28: =P25!B73 | P28: =P25!B76 | Q28: Estoque: 'Disponibilidade: Imediata' + 'Esse acabou' na mesma página.
A29: P26 | B29: Moletom | C29: HMZT-P26-REG-MOL320 | D29: Moletom Gola Careca 3 Cabos 320g Felpado | E29: Inverno Heavy — moletom 320g (topo do inverno; conjunto com a calça P25) | F29: Regular fit, sem capuz e sem bolso | G29: Moletom 3 cabos (triple ply) com felpado interno | H29: 320 g/m² (heavyweight) | I29: 50% algodão + 50% poliéster | J29: 6 | K29: =P26!$B$63 | L29: =P26!E65 | M29: =P26!D69 | N29: =P26!B75 | O29: =P26!B76 | P29: =P26!B79 | Q29: Preço: a página mostra R$ 68,00 no seletor; o texto dá preço base de R$ 59,00 e tabela a partir dele. Provável preço de varejo/unidade × atacado — confirmar qual vale no pedido.
A30: P27 | B30: Manga longa | C30: HMZT-P27-RGL-ML300 | D30: Blusa Raglan Manga Longa 300g (fio importado 2 cabos) | E30: Meia-estação — Manga longa 'Design' (raglan) · condicionada à composição | F30: Regular fit, manga longa raglan | G30: Malha 2 cabos (double ply), sem peluciado; interior liso | H30: 300 g/m² | I30: 'Fio importado chinês de fibra longa' — SEM percentual | J30: 4 | K30: =P27!$B$58 | L30: =P27!E60 | M30: =P27!D64 | N30: =P27!B70 | O30: =P27!B71 | P30: =P27!B74 | Q30: Composição não informada em % — só 'fio importado chinês'. Não dá para etiquetar (rotulagem têxtil exige composição) nem afirmar 'algodão'.
A31: P28 | B31: Moletom | C31: HMZT-P28-REG-PEL260 | D31: Moletom Canguru Peluciado 260g com Capuz e Cordão | E31: Inverno — Hoodie (moletom canguru, peça de desejo) | F31: Regular fit com capuz | G31: Moletinho 2 cabos com peluciado interno (escovado) | H31: 260 g/m² (texto) · ⚠️ arquivos das fotos: '240gsm' | I31: 50% algodão + 50% poliéster | J31: 5 | K31: =P28!$B$62 | L31: =P28!E64 | M31: =P28!D68 | N31: =P28!B74 | O31: =P28!B75 | P31: =P28!B78 | Q31: Gramatura: página e ficha dizem 260 g; TODOS os 15 arquivos de foto se chamam 'moletom_canguru_2_cabos_basico_240gsm'. Ou a foto é de outro produto (240 g, 'básico'), ou a gramatura mudou.
A32: P29 | B32: Manga longa | C32: HMZT-P29-REG-ML300 | D32: Blusa Manga Longa Gola Careca 300g (fio importado 2 cabos) | E32: Meia-estação — Manga longa clássica · condicionada à composição | F32: Regular fit, manga longa set-in | G32: Malha 2 cabos (double ply), sem peluciado; interior liso | H32: 300 g/m² | I32: 'Fio importado chinês de fibra longa' — SEM percentual | J32: 4 | K32: =P29!$B$59 | L32: =P29!E61 | M32: =P29!D65 | N32: =P29!B71 | O32: =P29!B72 | P32: =P29!B75 | Q32: Composição não informada em % — só 'fio importado chinês de fibra longa'. Não dá para etiquetar nem afirmar 'algodão'.
A34: Valores em verde vêm das abas de cada produto. Custo e preço de venda são estimativas até chegarem os orçamentos.

Sheet Regras Fornecedor
A1: Regras gerais — Lunfe Malhas (fabricação própria, Itajaí-SC)
A3: Faixa | B3: De (pç) | C3: Até (pç) | D3: Desconto
A4: Faixa 1 | B4: 20 | C4: 40 | D4: 0.1
A5: Faixa 2 | B5: 40 | C5: 80 | D5: 0.15
A6: Faixa 3 | B6: 80 | C6: 100 | D6: 0.2
A7: Faixa 4 | B7: 100 | C7: 300 | D7: 0.25
A8: Faixa 5 | B8: 300 | C8: 999 | D8: 0.3
A10: Desconto Pix adicional | B10: 0.05 | C10: Sobre o preço já com desconto progressivo
A11: Pedido mínimo (pç, pedido total) | B11: 20
A13: Outras condições
A14: Cartão | B14: Até 6× sem juros no atacado (página do produto diz "com juros" ⚠️ — confirmar)
A15: Boleto | B15: 30/60 dias para cadastro aprovado acima de R$ 2.000
A16: Amostra | B16: Até 2 peças, cobradas e abatidas no pedido aprovado; frete por conta do cliente
A17: Mistura | B17: Mínimo de 20 peças no pedido total — mistura livre de produtos, modelos, cores e tamanhos; soma para o desconto
A18: Cor Pantone exclusiva | B18: A partir de 100 peças/cor; 15–25 dias úteis
A19: Embalagem customizada | B19: A partir de 50 peças
A20: Personalização | B20: Silk, DTF, bordado, private label a partir de 20 peças — preço SEMPRE sob orçamento
A21: Prazo | B21: Lisas em estoque: despacho em 24h úteis · personalizadas: sob consulta
A22: Grade customizada | B22: Acima de 200 peças (sob consulta)
A23: Molde regular | B23: Tabela única em todos os regulares: M = 72 × 54 cm, ombro 46, manga 18; P–EG, +2 cm por tamanho
A24: Modelo das fotos | B24: 1,84 m · 84 kg · veste M
A25: Nota fiscal | B25: NF-e com CFOP de revenda; Simples, Presumido e Real
A26: Fabricação | B26: Própria: tecelagem, tingimento, corte, confecção e tratamentos em Itajaí-SC

Sheet P01
A1: P01 — Camiseta Oversized Suedine Peruano 300g
A3: 1. Identificação
A4: Código HMZT | B4: HMZT-P01-OVS-SUE300
A5: Fornecedor | B5: Lunfe Malhas — fabricação própria, Itajaí-SC
A6: Referência | B6: 7897385478523 (EAN-13)
A7: URL | B7: lunfemalhas.com.br/camiseta-oversized-suedine-peruano-300g-atacado-lunfe
A8: Categoria no site | B8: Camisetas › Masculino › Oversized
A9: Linha HMZT recomendada | B9: Heavy (oversized)
A10: Estoque | B10: Em estoque
A11: Descritor canônico (IA) | B11: Camiseta masculina heavyweight oversized boxy, ombro caído, manga larga até acima do cotovelo, gola careca canelada, malha aveludada e fosca tipo camurça.
A13: 2. Especificação técnica
A14: Item | B14: Valor | C14: Fonte
A15: Modelagem | B15: Oversized boxy, ombro caído (drop shoulder)
A16: Gramatura | B16: 300 g/m² (heavyweight)
A17: Tecido | B17: Suedine — acabamento escovado (peach finish), toque de camurça
A18: Composição | B18: 52% algodão / 48% poliéster
A19: Gola | B19: Careca, ribana canelada média
A20: Manga | B20: Curta, larga, até acima do cotovelo
A21: Barra | B21: Reta, pouco abaixo do quadril
A22: Opacidade | B22: Total (mesma malha do P04)
A23: Irmão | B23: P04 — mesma malha, modelagem regular (texto do P04 confirma)
A24: Cuidados | B24: Lavar do avesso a 30 °C, sem secadora quente, não passar ferro direto na superfície
A26: 3. Tabela de medidas (cm)
A27: ⚠️ Tabela da oversized NÃO informada — pedir ao fornecedor (referência provisória: Chinese Heavyweight oversized, aba P05).
A28: Modelo das fotos: 1,84 m · 84 kg · veste M
A30: 4. Cores disponíveis
A31: Cor | B31: Código HMZT | C31: Ref. fornecedor | D31: Observação
A32: Off-white | B32: OFF | C32: — | D32: Cor das fotos
A33: Areia / bege | B33: ARE | C33: —
A34: Cinza chumbo | B34: CHU | C34: —
A35: ⚠️ Cartela da página. O texto do P04 (mesma malha) lista Preto, Off White, Bege, Marrom, Marinho (refs SDP-). Confirmar a cartela da oversized.
A37: 5. Personalização (preço sempre sob orçamento)
A38: Técnica | B38: Detalhe | C38: Mínimo
A39: Silk base d'água | B39: Testar aderência sobre suedine | C39: 20 pç
A40: DTF | B40: Testar aderência | C40: 20 pç
A41: Bordado | B41: Melhor resultado; costas na oversized | C41: 20 pç
A42: Etiqueta private label | B42: Interna + tag | C42: 20 pç
A43: Embalagem customizada | C43: 50 pç
A44: Cor Pantone | C44: 100 pç/cor
A46: 6. Preços do fornecedor (desconto progressivo)
A47: Preço base (R$) | B47: 54
A48: Faixa | B48: Peças | C48: Desconto | D48: Preço unitário | E48: Preço + Pix
A49: Faixa 1 | B49: 20–40 | C49: ='Regras Fornecedor'!$D$4 | D49: =ROUND($B$47*(1-C49),2) | E49: =ROUND(D49*(1-'Regras Fornecedor'!$B$10),2)
A50: Faixa 2 | B50: 40–80 | C50: ='Regras Fornecedor'!$D$5 | D50: =ROUND($B$47*(1-C50),2) | E50: =ROUND(D50*(1-'Regras Fornecedor'!$B$10),2)
A51: Faixa 3 | B51: 80–100 | C51: ='Regras Fornecedor'!$D$6 | D51: =ROUND($B$47*(1-C51),2) | E51: =ROUND(D51*(1-'Regras Fornecedor'!$B$10),2)
A52: Faixa 4 | B52: 100–300 | C52: ='Regras Fornecedor'!$D$7 | D52: =ROUND($B$47*(1-C52),2) | E52: =ROUND(D52*(1-'Regras Fornecedor'!$B$10),2)
A53: Faixa 5 | B53: 300–999 | C53: ='Regras Fornecedor'!$D$8 | D53: =ROUND($B$47*(1-C53),2) | E53: =ROUND(D53*(1-'Regras Fornecedor'!$B$10),2)
A55: 7. Custo HMZT e margem (lote de 20 peças, Pix)
A56: Peça (20 pç, Pix) | B56: =E49
A57: Personalização + etiqueta + tag (R$/pç) | B57: 16 | C57: Estimativa HMZT — trocar pelo orçamento real
A58: Frete rateado + embalagem (R$/pç) | B58: 6 | C58: Estimativa HMZT — trocar pelo orçamento real
A59: Custo unitário estimado | B59: =SUM(B56:B58)
A60: Preço de venda HMZT (R$) | B60: 169 | C60: Sugestão do dossiê — ajustar
A61: Impostos + gateway (% do preço) | B61: 0 | C61: A preencher (Simples + taxa Asaas)
A62: Margem bruta (R$) | B62: =B60-B59
A63: Margem bruta (%) | B63: =IF(B60=0,0,(B60-B59)/B60)
A64: Margem após impostos/gateway (%) | B64: =IF(B60=0,0,(B60*(1-B61)-B59)/B60) | C64: Ainda sem frete ao cliente e mídia
A66: 8. Contradições e erros ⚠️
A67: ⚠️ "Peruano" no nome, mas é 52/48 com poliéster — não é algodão peruano
A68: ⚠️ Tabela de medidas da oversized não informada
A69: ⚠️ Cartela da página × texto do P04 divergem
A71: 9. Comunicação HMZT
A72: ✅ Pode usar | D72: 📣 / ⛔ Não usar
A73: Toque aveludado tipo camurça; acabamento físico que não sai na lavagem | D73: "Algodão peruano" (NUNCA)
A74: Heavyweight 300 g/m², 100% opaca | D74: "Maior conversão por toque", "exclusiva no atacado"
A75: Composição por extenso: 52% algodão, 48% poliéster | D75: "Percepção de R$ 149–199"
A76: Fabricada em Santa Catarina
A78: 10. Pendências com o fornecedor
A79: Pendência | B79: Status | C79: Responsável | D79: Resposta
A80: Tabela de medidas oversized | B80: Aberta
A81: Cartela real de cores | B81: Aberta
A82: O que significa "Peruano" no nome | B82: Aberta
A83: Peça-teste de silk/DTF | B83: Aberta
A84: Orçamento de personalização | B84: Aberta
A86: 11. Fluxo de prompts de lookbook (docs/shop-confeccao/prompts/P01-prompts.md)
A87: Foto | B87: Origem no print | C87: Formato | D87: Status
A88: F1 — Hero 3/4 com mão no peito | B88: Foto principal (1ª do print e 1ª miniatura) | C88: 4:5 | D88: A gerar
A89: F2 — Detalhe gola, ombro caído e manga | B89: 2ª foto e 2ª miniatura | C89: 4:5 | D89: A gerar
A90: F3 — Frontal com mãos nos bolsos | B90: 3ª foto e 3ª miniatura | C90: 4:5 | D90: A gerar
A91: F4 — Corpo inteiro frontal | B91: 4ª miniatura (baixa resolução — leitura aproximada) | C91: 4:5 | D91: A gerar

Sheet P02
A1: P02 — Camiseta Oversized Drop Shoulder Algodão Penteado 185g
A3: 1. Identificação
A4: Código HMZT | B4: HMZT-P02-OVS-ALG185
A5: Fornecedor | B5: Lunfe Malhas — fabricação própria, Itajaí-SC
A6: Referência | B6: 7899196241006
A7: URL | B7: lunfemalhas.com.br/camiseta-oversized-drop-shoulder-atacado-185g-lunfe
A8: Categoria no site | B8: Camisetas › Masculino › Oversized
A9: Linha HMZT recomendada | B9: Essencial — oversized (drops com estampa, eventos)
A10: Estoque | B10: Disponibilidade imediata; 2 cores; despacho em 24h úteis
A11: Descritor canônico (IA) | B11: Camiseta masculina oversized drop shoulder, manga curta larga até acima do cotovelo, ombro caído cerca de 2 cm além do ombro, gola careca canelada fina, meia malha 100% algodão penteado de 185 g/m² com superfície lisa e fosca, caimento amplo e leve com dobras suaves, barra dupla reta abaixo do quadril. Peça lisa, sem logos. Fundo cinza claro de estúdio.
A13: 2. Especificação técnica
A14: Item | B14: Valor | C14: Fonte
A15: Composição | B15: 100% algodão penteado
A16: Gramatura | B16: 185 g/m² (resumo do topo diz 300 g/m²)
A17: Tecido | B17: Meia malha lisa, sem acabamento especial
A18: Modelagem | B18: Oversized drop shoulder — ombro caído, corpo amplo, comprimento alongado
A19: Gola | B19: Canelada 2/1, fecho em anel, reforço ombro a ombro
A20: Costuras | B20: Ponto cadeia em todas as emendas
A21: Barras | B21: Dupla nas mangas e na barra inferior
A22: Tratamentos | B22: Pré-encolhimento mecânico, tingimento reativo, anti-torção, amaciamento
A23: Tamanhos | B23: P, M, G, GG, EG (grade oversized)
A24: Queda do ombro | B24: Texto: 4–8 cm abaixo do ombro; tabela: só +2 cm por lado
A25: Giro | B25: 'A oversized mais vendida', 'maior giro do catálogo'
A26: Produção | B26: Fabricação própria — Itajaí, SC
A28: 3. Tabela de medidas (cm)
A29: Tabela 1
A30: Tamanho | B30: Comprimento | C30: Largura | D30: Ombros | E30: Mangas
A31: P | B31: 74 | C31: 56 | D31: 48 | E31: 20
A32: M | B32: 76 | C32: 58 | D32: 50 | E32: 22
A33: G | B33: 78 | C33: 60 | D33: 52 | E33: 24
A34: GG | B34: 80 | C34: 62 | D34: 54 | E34: 26
A35: EG | B35: 82 | C35: 64 | D35: 56 | E35: 28
A36: Regular Lunfe (comparação)
A37: Tamanho | B37: Comprimento | C37: Largura | D37: Ombros | E37: Mangas
A38: P | B38: 70 | C38: 52 | D38: 44 | E38: 16
A39: M | B39: 72 | C39: 54 | D39: 46 | E39: 18
A40: G | B40: 74 | C40: 56 | D40: 48 | E40: 20
A41: GG | B41: 76 | C41: 58 | D41: 50 | E41: 22
A42: EG | B42: 78 | C42: 60 | D42: 52 | E42: 24
A43: Grade oversized oficial, em cm, ± 2 cm. M oversized = regular +4 cm em todas as medidas. Modelo 1,84 m / 84 kg veste M. Única tabela oversized publicada — referência provisória para P01 e P10.
A44: Modelo das fotos: 1,84 m · 84 kg · veste M
A46: 4. Cores disponíveis
A47: Cor | B47: Código HMZT | C47: Ref. fornecedor | D47: Observação
A48: Preto | B48: PRT | C48: OVD-PRT | D48: Cor das fotos #1–5
A49: Branco | B49: BCO | C49: OVD-BRA | D49: Fotos #6–10; opaco nas fotos
A50: Só 2 cores. Pantone a partir de 100 pç/cor, 15–25 dias úteis. A peça cinza do print de 29/09 não existe na cartela atual.
A52: 5. Personalização (preço sempre sob orçamento)
A53: Técnica | B53: Detalhe | C53: Mínimo
A54: Silk base d'água | B54: Toque zero — ideal para costas | C54: 20 pç
A55: Silk plastisol | B55: Cobertura em base preta | C55: 20 pç
A56: Gel alto relevo / Puff 3D / Foil / Silicone 3D | B56: Efeitos para drops | C56: 20 pç
A57: DTF | B57: Full color | C57: 20 pç
A58: Bordado industrial | B58: Peito pequeno com entretela (malha leve repuxa) | C58: 20 pç
A59: Etiqueta private label | B59: Interna + tag | C59: 20 pç
A60: Embalagem customizada | B60: Saco, caixa, tag | C60: 50 pç
A61: Cor Pantone | B61: Tingimento exclusivo | C61: 100 pç/cor
A63: 6. Preços do fornecedor (desconto progressivo)
A64: Preço base (R$) | B64: 39.78
A65: Faixa | B65: Peças | C65: Desconto | D65: Preço unitário | E65: Preço + Pix
A66: Faixa 1 | B66: 20–40 | C66: ='Regras Fornecedor'!$D$4 | D66: =ROUND($B$64*(1-C66),2) | E66: =ROUND(D66*(1-'Regras Fornecedor'!$B$10),2)
A67: Faixa 2 | B67: 40–80 | C67: ='Regras Fornecedor'!$D$5 | D67: =ROUND($B$64*(1-C67),2) | E67: =ROUND(D67*(1-'Regras Fornecedor'!$B$10),2)
A68: Faixa 3 | B68: 80–100 | C68: ='Regras Fornecedor'!$D$6 | D68: =ROUND($B$64*(1-C68),2) | E68: =ROUND(D68*(1-'Regras Fornecedor'!$B$10),2)
A69: Faixa 4 | B69: 100–300 | C69: ='Regras Fornecedor'!$D$7 | D69: =ROUND($B$64*(1-C69),2) | E69: =ROUND(D69*(1-'Regras Fornecedor'!$B$10),2)
A70: Faixa 5 | B70: 300–999 | C70: ='Regras Fornecedor'!$D$8 | D70: =ROUND($B$64*(1-C70),2) | E70: =ROUND(D70*(1-'Regras Fornecedor'!$B$10),2)
A72: 7. Custo HMZT e margem (lote de 20 peças, Pix)
A73: Peça (20 pç, Pix) | B73: =E66
A74: Personalização + etiqueta + tag (R$/pç) | B74: 12 | C74: Estimativa HMZT — trocar pelo orçamento real
A75: Frete rateado + embalagem (R$/pç) | B75: 4 | C75: Estimativa HMZT — trocar pelo orçamento real
A76: Custo unitário estimado | B76: =SUM(B73:B75)
A77: Preço de venda HMZT (R$) | B77: 109 | C77: Sugestão do dossiê — ajustar
A78: Impostos + gateway (% do preço) | B78: 0 | C78: A preencher (Simples + taxa Asaas)
A79: Margem bruta (R$) | B79: =B77-B76
A80: Margem bruta (%) | B80: =IF(B77=0,0,(B77-B76)/B77)
A81: Margem após impostos/gateway (%) | B81: =IF(B77=0,0,(B77*(1-B78)-B76)/B77) | C81: Ainda sem frete ao cliente e mídia
A83: 8. Contradições e erros ⚠️
A84: ⚠️ Resumo do topo diz '100% Algodão Penteado 300g/m²'; ficha técnica e FAQ dizem 185 g/m².
A85: ⚠️ Comparativo cita 'Oversized Suedine 300g — 100% CO penteado, R$ 42,00, 6 cores'; a ficha P01 (Oversized Suedine Peruano 300g) é 52% algodão/48% poliéster, R$ 54,00. O comparativo bate com a P10 (Oversized Básica Suedine 300GSM) — a Lunfe tem duas oversized suedine 300g.
A86: ⚠️ Comparativo cita 'Estonada Oversized Bolso 175g — 3 cores em estoque, R$ 39,78'; nas páginas relacionadas as estonadas oversized aparecem 'Esse acabou', uma a R$ 39,78 e outra a R$ 90,00.
A87: ⚠️ Texto: ombro caído 4–8 cm abaixo do ombro; tabela: ombro 50 × 46 cm da regular (M) = só +2 cm por lado.
A88: ⚠️ Texto: 6× sem juros; print de 29/09: 6× R$ 7,28 com juros.
A90: 9. Comunicação HMZT
A91: ✅ Pode usar | D91: 📣 / ⛔ Não usar
A92: Oversized com ombro caído, corpo amplo e comprimento alongado. | D92: A oversized mais vendida / maior giro / campeã.
A93: 100% algodão penteado, 185 g/m² — leve para usar o ano todo. | D93: Silhueta dominante do streetwear global 2024–2026.
A94: Pré-encolhida e anti-torção. | D94: Preto e branco = 60–70% do volume de oversized.
A95: Gola canelada com reforço ombro a ombro, barra dupla. | D95: Veste bem em qualquer biotipo / menos objeção = mais conversão.
A96: Fabricada em Santa Catarina. | D96: A peça que vende sozinha na arara.
A97: Tabela de medidas real no provador (M 76 × 58 cm). | D97: Nomes de marcas de terceiros (Fear of God, Stüssy, Represent, Acne).
D98: Heavyweight / premium / 300 g.
A100: 10. Pendências com o fornecedor
A101: Pendência | B101: Status | C101: Responsável | D101: Resposta
A102: Corrigir 300 g do resumo (é 185 g) | B102: Aberta
A103: Composição e preço da 'Oversized Suedine 300g' do comparativo (P10 × P01) | B103: Aberta
A104: Estoque e preço da Estonada Oversized Bolso 175g | B104: Aberta
A105: Opacidade do branco com amostra | B105: Aberta
A106: Orçamento silk/DTF costas + etiqueta + tag | B106: Aberta
A107: 6× com ou sem juros | B107: Aberta
A109: 11. Fluxo de prompts de lookbook (docs/shop-confeccao/prompts/P02-prompts.md)
A110: Foto | B110: Origem no print | C110: Formato | D110: Status
A111: F1 — Frontal olhar baixo | B111: Origem: fotos #1 e #5 da galeria (preto, frontal, braços soltos, olhar para baixo/para fora à esquerda da câmera) | C111: 4:5 | D111: A gerar
...

Sheet P03
A1: P03 — Camiseta Pima Cotton 165g
A3: 1. Identificação
A4: Código HMZT | B4: HMZT-P03-REG-PIM165
A5: Fornecedor | B5: Lunfe Malhas — fabricação própria, Itajaí-SC
A6: Referência | B6: cms-pimacotton (código interno)
A7: URL | B7: lunfemalhas.com.br/camiseta-pima-cotton-165g-100-algodao-puro-atacado-lunfe
A8: Categoria no site | B8: Camisetas › Masculino › Premium
A9: Linha HMZT recomendada | B9: Premium (principal)
A10: Estoque | B10: 8 cores em estoque (página mostra 5 ⚠️)
A11: Descritor canônico (IA) | B11: Camiseta masculina regular fit, manga ajustada até metade do bíceps, gola careca de ribana fina rente, malha leve de algodão sedosa com brilho natural.
A13: 2. Especificação técnica
A14: Item | B14: Valor | C14: Fonte
A15: Composição | B15: 100% algodão Pima (G. barbadense) — sem elastano, sem poliéster
A16: Fibra | B16: Extra-longa, staple > 35 mm
A17: Construção | B17: "Malha premium" — título do fio não informado
A18: Gramatura | B18: 165 g/m²
A19: Modelagem | B19: Regular fit
A20: Gola | B20: Careca, ribana reforçada
A21: Mangas | B21: Curtas, barra dupla
A22: Barra | B22: Dupla, acabamento invisível
A23: Costuras | B23: Reforçadas; ombro a ombro com fita interna
A24: Tratamentos | B24: Pré-encolhimento industrial; fixação de cor de alta solidez
A25: Encolhimento | B25: 1–2% nas primeiras lavagens, estabiliza após 2–3 ciclos
A26: Cuidados | B26: Lavar a 30 °C, sem secadora quente, pendurar; ferro baixo
A27: Produção | B27: Própria Lunfe — Itajaí-SC
A29: 3. Tabela de medidas (cm)
A30: Tamanho | B30: Comprimento | C30: Largura | D30: Ombros | E30: Mangas
A31: P | B31: 70 | C31: 52 | D31: 44 | E31: 16
A32: M | B32: 72 | C32: 54 | D32: 46 | E32: 18
A33: G | B33: 74 | C33: 56 | D33: 48 | E33: 20
A34: GG | B34: 76 | C34: 58 | D34: 50 | E34: 22
A35: EG | B35: 78 | C35: 60 | D35: 52 | E35: 24
A36: Em cm, em repouso, ± 2 cm. Molde regular padrão.
A37: Modelo das fotos: 1,84 m · 84 kg · veste M
A39: 4. Cores disponíveis
A40: Cor | B40: Código HMZT | C40: Ref. fornecedor | D40: Observação
A41: Preto | B41: PRT | C41: PMA-PRT | D41: Não aparecia no seletor
A42: Off White | B42: OFF | C42: PMA-OFW | D42: Não aparecia no seletor
A43: Bege | B43: BGE | C43: PMA-BGE | D43: Provável "creme"
A44: Capuccino | B44: CAP | C44: PMA-CAP | D44: Exclusiva do Pima; provável "caramelo"
A45: Cinza Claro | B45: CZC | C45: PMA-CZC
A46: Marrom | B46: MRR | C46: PMA-MRR | D46: Cor das fotos ("café")
A47: Marinho | B47: MAR | C47: PMA-MRN
A48: Verde | B48: VRD | C48: PMA-VRD | D48: Não aparecia no seletor
A49: Pantone a partir de 100 pç/cor.
A51: 5. Personalização (preço sempre sob orçamento)
A52: Técnica | B52: Detalhe | C52: Mínimo
A53: Silk base d'água | B53: Toque zero | C53: 20 pç
A54: DTF | B54: Full color | C54: 20 pç
A55: Bordado | B55: Peito, mangas — o mais indicado | C55: 20 pç
A56: Etiqueta private label | B56: Interna + tag | C56: 20 pç
A57: Embalagem customizada | B57: Saco, caixa premium, tag | C57: 50 pç
A58: Cor Pantone | C58: 100 pç/cor
A60: 6. Preços do fornecedor (desconto progressivo)
A61: Preço base (R$) | B61: 63.45
A62: Faixa | B62: Peças | C62: Desconto | D62: Preço unitário | E62: Preço + Pix
A63: Faixa 1 | B63: 20–40 | C63: ='Regras Fornecedor'!$D$4 | D63: =ROUND($B$61*(1-C63),2) | E63: =ROUND(D63*(1-'Regras Fornecedor'!$B$10),2)
A64: Faixa 2 | B64: 40–80 | C64: ='Regras Fornecedor'!$D$5 | D64: =ROUND($B$61*(1-C64),2) | E64: =ROUND(D64*(1-'Regras Fornecedor'!$B$10),2)
A65: Faixa 3 | B65: 80–100 | C65: ='Regras Fornecedor'!$D$6 | D65: =ROUND($B$61*(1-C65),2) | E65: =ROUND(D65*(1-'Regras Fornecedor'!$B$10),2)
A66: Faixa 4 | B66: 100–300 | C66: ='Regras Fornecedor'!$D$7 | D66: =ROUND($B$61*(1-C66),2) | E66: =ROUND(D66*(1-'Regras Fornecedor'!$B$10),2)
A67: Faixa 5 | B67: 300–999 | C67: ='Regras Fornecedor'!$D$8 | D67: =ROUND($B$61*(1-C67),2) | E67: =ROUND(D67*(1-'Regras Fornecedor'!$B$10),2)
A69: 7. Custo HMZT e margem (lote de 20 peças, Pix)
A70: Peça (20 pç, Pix) | B70: =E63
A71: Personalização + etiqueta + tag (R$/pç) | B71: 12.5 | C71: Estimativa HMZT — trocar pelo orçamento real
A72: Frete rateado + embalagem (R$/pç) | B72: 7.5 | C72: Estimativa HMZT — trocar pelo orçamento real
A73: Custo unitário estimado | B73: =SUM(B70:B72)
A74: Preço de venda HMZT (R$) | B74: 189 | C74: Sugestão do dossiê — ajustar
A75: Impostos + gateway (% do preço) | B75: 0 | C75: A preencher (Simples + taxa Asaas)
A76: Margem bruta (R$) | B76: =B74-B73
A77: Margem bruta (%) | B77: =IF(B74=0,0,(B74-B73)/B74)
A78: Margem após impostos/gateway (%) | B78: =IF(B74=0,0,(B74*(1-B75)-B73)/B74) | C78: Ainda sem frete ao cliente e mídia
A80: 8. Contradições e erros ⚠️
A81: ⚠️ "Origem: Pima" — Pima é variedade, não lugar (EUA ou Peru?)
A82: ⚠️ Texto do P08 cita "Pima 200g, 100% peruano, sob consulta" — não bate
A83: ⚠️ Ticket varejo: R$ 149–229 (texto P07) × R$ 179–299 (este texto)
A84: ⚠️ Cores: 5 na página × 8 no texto
A86: 9. Comunicação HMZT
A87: ✅ Pode usar | D87: 📣 / ⛔ Não usar
A88: 100% algodão Pima — SÓ com comprovação do fio | D88: "A fibra mais nobre do planeta"
A89: Fibra extra-longa: toque sedoso | D89: "Percepção de R$ 199–299", "maior margem"
A90: Sem elastano, sem poliéster | D90: "Migração irreversível", LTV 4–6×, recompra
A91: Malha leve 165 g/m²
A92: Fabricada em Santa Catarina
A94: 10. Pendências com o fornecedor
A95: Pendência | B95: Status | C95: Responsável | D95: Resposta
A96: Origem/variedade do Pima + documento do fio (Supima?) | B96: Aberta
A97: Título do fio | B97: Aberta
A98: Estoque de Preto, Off White e Verde | B98: Aberta
A99: Existe uma "Pima 200g"? | B99: Aberta
A100: Orçamento bordado + etiqueta + caixa | B100: Aberta
A102: 11. Fluxo de prompts de lookbook (docs/shop-confeccao/prompts/P03-prompts.md)
A103: Foto | B103: Origem no print | C103: Formato | D103: Status
A104: F1 — Hero mão na gola | B104: Foto principal e 1ª miniatura | C104: 4:5 | D104: A gerar
A105: F2 — Olhar baixo ajustando a manga | B105: 2ª foto e 2ª miniatura | C105: 4:5 | D105: A gerar
A106: F3 — Frontal mãos nos bolsos da frente | B106: 3ª foto e 3ª miniatura | C106: 4:5 | D106: A gerar
A107: F4 — Variação de cor (mesma pose da F1) | B107: 5ª miniatura — peça em tom terracota/capuccino | C107: 4:5 | D107: A gerar

Sheet P04
A1: P04 — Camiseta Suedine Peruano 300g Regular Fit
A3: 1. Identificação
A4: Código HMZT | B4: HMZT-P04-REG-SUE300
A5: Fornecedor | B5: Lunfe Malhas — fabricação própria, Itajaí-SC
A6: Referência | B6: 7891865209942 (EAN-13)
A7: URL | B7: lunfemalhas.com.br/camiseta-suedine-peruano-300g-toque-aveludado-atacado-lunfe
A8: Categoria no site | B8: Algodão Importado (breadcrumb) · também em Masculino › Premium
A9: Linha HMZT recomendada | B9: Heavy (principal)
A10: Estoque | B10: 5 cores em estoque
A11: Descritor canônico (IA) | B11: Camiseta masculina heavyweight regular fit, manga reta, gola careca canelada, malha encorpada aveludada e fosca tipo camurça, caimento estruturado.
A13: 2. Especificação técnica
A14: Item | B14: Valor | C14: Fonte
A15: Composição | B15: 52% algodão / 48% poliéster
A16: Acabamento | B16: Suedine (peach/sanded finish) — escovação com micro-abrasivos; físico, permanente
A17: Gramatura | B17: 300 g/m²
A18: Modelagem | B18: Regular fit, caimento estruturado sem elastano
A19: Gola | B19: Careca, ribana reforçada
A20: Mangas | B20: Curtas, barra dupla
A21: Barra | B21: Dupla, acabamento invisível
A22: Costuras | B22: Reforçadas; ombro a ombro com fita interna
A23: Tratamentos | B23: Pré-encolhimento industrial; fixação de cor
A24: Opacidade | B24: Total, inclusive off white
A25: Cuidados | B25: Lavar do avesso a 30 °C, sem secadora quente, não passar ferro direto
A26: Uso | B26: Meia-estação 15–22 °C; mar–out no Sul/Sudeste
A28: 3. Tabela de medidas (cm)
A29: Tamanho | B29: Comprimento | C29: Largura | D29: Ombros | E29: Mangas
A30: P | B30: 70 | C30: 52 | D30: 44 | E30: 16
A31: M | B31: 72 | C31: 54 | D31: 46 | E31: 18
A32: G | B32: 74 | C32: 56 | D32: 48 | E32: 20
A33: GG | B33: 76 | C33: 58 | D33: 50 | E33: 22
A34: EG | B34: 78 | C34: 60 | D34: 52 | E34: 24
A35: Em cm, em repouso, ± 2 cm.
A36: Modelo das fotos: 1,84 m · 84 kg · veste M
A38: 4. Cores disponíveis
A39: Cor | B39: Código HMZT | C39: Ref. fornecedor | D39: Observação
A40: Preto | B40: PRT | C40: SDP-PRT
A41: Off White | B41: OFF | C41: SDP-OFW | D41: 100% opaco
A42: Bege | B42: BGE | C42: SDP-BGE | D42: Provável nude/rosé das fotos
A43: Marrom | B43: MRR | C43: SDP-MRR | D43: "A que mais parece camurça"
A44: Marinho | B44: MAR | C44: SDP-MRN
A45: ⚠️ Página mostrava Areia, Cinza chumbo, Branco, Preto — sem Marrom/Marinho. Confirmar.
A47: 5. Personalização (preço sempre sob orçamento)
A48: Técnica | B48: Detalhe | C48: Mínimo
A49: Silk base d'água | B49: Frente, costas, mangas — testar aderência | C49: 20 pç
A50: DTF | B50: Testar aderência | C50: 20 pç
A51: Bordado | B51: Peito, mangas, costas — melhor resultado | C51: 20 pç
A52: Etiqueta private label | B52: Interna + tag | C52: 20 pç
A53: Embalagem customizada | B53: Saco, caixa premium, tag | C53: 50 pç
A54: Cor Pantone | C54: 100 pç/cor
A56: 6. Preços do fornecedor (desconto progressivo)
A57: Preço base (R$) | B57: 52
A58: Faixa | B58: Peças | C58: Desconto | D58: Preço unitário | E58: Preço + Pix
A59: Faixa 1 | B59: 20–40 | C59: ='Regras Fornecedor'!$D$4 | D59: =ROUND($B$57*(1-C59),2) | E59: =ROUND(D59*(1-'Regras Fornecedor'!$B$10),2)
A60: Faixa 2 | B60: 40–80 | C60: ='Regras Fornecedor'!$D$5 | D60: =ROUND($B$57*(1-C60),2) | E60: =ROUND(D60*(1-'Regras Fornecedor'!$B$10),2)
A61: Faixa 3 | B61: 80–100 | C61: ='Regras Fornecedor'!$D$6 | D61: =ROUND($B$57*(1-C61),2) | E61: =ROUND(D61*(1-'Regras Fornecedor'!$B$10),2)
A62: Faixa 4 | B62: 100–300 | C62: ='Regras Fornecedor'!$D$7 | D62: =ROUND($B$57*(1-C62),2) | E62: =ROUND(D62*(1-'Regras Fornecedor'!$B$10),2)
A63: Faixa 5 | B63: 300–999 | C63: ='Regras Fornecedor'!$D$8 | D63: =ROUND($B$57*(1-C63),2) | E63: =ROUND(D63*(1-'Regras Fornecedor'!$B$10),2)
A65: 7. Custo HMZT e margem (lote de 20 peças, Pix)
A66: Peça (20 pç, Pix) | B66: =E59
A67: Personalização + etiqueta + tag (R$/pç) | B67: 12.5 | C67: Estimativa HMZT — trocar pelo orçamento real
A68: Frete rateado + embalagem (R$/pç) | B68: 6 | C68: Estimativa HMZT — trocar pelo orçamento real
A69: Custo unitário estimado | B69: =SUM(B66:B68)
A70: Preço de venda HMZT (R$) | B70: 159 | C70: Sugestão do dossiê — ajustar
A71: Impostos + gateway (% do preço) | B71: 0 | C71: A preencher (Simples + taxa Asaas)
A72: Margem bruta (R$) | B72: =B70-B69
A73: Margem bruta (%) | B73: =IF(B70=0,0,(B70-B69)/B70)
A74: Margem após impostos/gateway (%) | B74: =IF(B70=0,0,(B70*(1-B71)-B69)/B70) | C74: Ainda sem frete ao cliente e mídia
A76: 8. Contradições e erros ⚠️
A77: ⚠️ "Peruano" no nome — é 52/48 com poliéster, não é algodão peruano
A78: ⚠️ Cores página × texto
A79: ⚠️ "A partir de" na página × preço fixo no texto
A80: ⚠️ Texturizadas 240g: 52/48 aqui × 51% poliéster/49% algodão no texto do P05
A81: ⚠️ Ticket Chinese HW: R$ 79–129 aqui × drops de R$ 150–250 no texto do P05
A83: 9. Comunicação HMZT
A84: ✅ Pode usar | D84: 📣 / ⛔ Não usar
A85: Toque aveludado tipo camurça, permanente | D85: "Algodão peruano" (NUNCA)
A86: Heavyweight 300 g/m², 100% opaca | D86: "Maior conversão por toque", "ciclo de 5 passos"
A87: Caimento estruturado | D87: "ROI de R$ 6–10 por R$ 1"
A88: Disponível em regular e oversized | D88: "Exclusiva no atacado brasileiro"
A89: Composição por extenso: 52% algodão, 48% poliéster
A91: 10. Pendências com o fornecedor
A92: Pendência | B92: Status | C92: Responsável | D92: Resposta
A93: Cartela real (cinza chumbo existe?) | B93: Aberta
A94: Significado de "Peruano" no nome | B94: Aberta
A95: Peça-teste silk/DTF | B95: Aberta
A96: Orçamento bordado + etiqueta + caixa | B96: Aberta
A98: 11. Fluxo de prompts de lookbook (docs/shop-confeccao/prompts/P04-prompts.md)
A99: Foto | B99: Origem no print | C99: Formato | D99: Status
A100: F1 — Frontal braços soltos | B100: Foto principal e 1ª miniatura | C100: 4:5 | D100: A gerar
A101: F2 — Detalhe gola e punho | B101: 2ª foto e 2ª miniatura | C101: 4:5 | D101: A gerar
A102: F3 — Frontal plano aberto | B102: 3ª miniatura | C102: 4:5 | D102: A gerar
A103: F4 — 3/4 tocando a barra | B103: 3ª foto e 4ª miniatura | C103: 4:5 | D103: A gerar
A104: F5 — Lateral | B104: 5ª miniatura (baixa resolução — leitura aproximada) | C104: 4:5 | D104: A gerar

Sheet P05
A1: P05 — Camiseta Chinese Heavyweight 300g
A3: 1. Identificação
A4: Código HMZT | B4: HMZT-P05-REG-XJG300 / -OVS-
A5: Fornecedor | B5: Lunfe Malhas — fabricação própria, Itajaí-SC
A6: Referência | B6: 790836512100 (12 dígitos ⚠️)
A7: URL | B7: lunfemalhas.com.br/camiseta-chinese-heavyweight-atacado-300g-algodao-importado-lunfe
A8: Categoria no site | B8: Camisetas › Masculino › Premium
A9: Linha HMZT recomendada | B9: Heavy (alternativa ⚠️ Xinjiang)
A10: Estoque | B10: 4 cores em pronta entrega permanente
A11: Descritor canônico (IA) | B11: Camiseta masculina heavyweight regular, gola careca estruturada, malha de algodão grossa e encorpada com leve brilho acetinado, caimento reto.
A13: 2. Especificação técnica
A14: Item | B14: Valor | C14: Fonte
A15: Composição | B15: 100% algodão importado — origem Xinjiang, China ⚠️
A16: Fibra | B16: Longa, staple 28–30 mm
A17: Fio | B17: 28/1 × 2 cabos (retorcido duplo; equivale a ~14/1)
A18: Gramatura | B18: 300 g/m² ± 5% ("ultra-heavyweight")
A19: Rolo / rendimento | B19: 1,80 m tubular aberta · 3,0–3,5 camisetas/m (M)
A20: Modelagens | B20: Regular (P–GG) + Oversized (P–G1) — mesma malha
A21: Gola | B21: Canelada 2/1 estruturada, fecho em anel
A22: Ombros | B22: Reforço ombro a ombro com faixa larga
A23: Costuras | B23: Ponto cadeia
A24: Barras | B24: Dupla nas mangas e barra
A25: Tratamentos | B25: Pré-encolhimento (<3%), tingimento reativo, anti-torção, amaciamento, anti-pilling enzimático
A26: Anti-rugas | B26: Não
A27: Versão feminina | B27: Não existe (em análise)
A29: 3. Tabela de medidas (cm)
A30: Regular
A31: Tamanho | B31: Comprimento | C31: Largura | D31: Ombros | E31: Mangas
A32: P | B32: 70 | C32: 52 | D32: 44 | E32: 16
A33: M | B33: 72 | C33: 54 | D33: 46 | E33: 18
A34: G | B34: 74 | C34: 56 | D34: 48 | E34: 20
A35: GG | B35: 76 | C35: 58 | D35: 50 | E35: 22
A36: Oversized
A37: Tamanho | B37: Comprimento | C37: Largura | D37: Ombros | E37: Mangas
A38: P | B38: 74 | C38: 57 | D38: 54 | E38: 24
A39: M | B39: 76 | C39: 59 | D39: 56 | E39: 25
A40: G | B40: 78 | C40: 61 | D40: 58 | E40: 26
A41: GG | B41: 80 | C41: 64 | D41: 60 | E41: 27
A42: G1 | B42: 82 | C42: 67 | D42: 62 | E42: 28
A43: Regular vai só até GG (sem EG ⚠️). ± 2 cm.
A44: Modelo das fotos: 1,84 m · 84 kg · veste M
A46: 4. Cores disponíveis
A47: Cor | B47: Código HMZT | C47: Ref. fornecedor | D47: Observação
A48: Preto | B48: PRT | C48: CHW-PRT | D48: Maior giro
A49: Cinza | B49: CZA | C49: CHW-CZA
A50: Marinho | B50: MAR | C50: CHW-MRN
A51: Off White | B51: OFF | C51: CHW-OFW
A52: Pantone a partir de 100 pç/cor, 15–25 dias úteis.
A54: 5. Personalização (preço sempre sob orçamento)
A55: Técnica | B55: Detalhe | C55: Mínimo
A56: Silk | B56: Até 4 cores | C56: 20 pç
A57: DTF | B57: Full color | C57: 20 pç
A58: Bordado | B58: Até 15.000 pontos | C58: 20 pç
A59: Sublimação | B59: ⚠️ Não funciona em 100% algodão — não usar | C59: 20 pç
A60: Etiqueta private label | C60: 20 pç
A61: Embalagem customizada | C61: 50 pç
A62: Cor Pantone | C62: 100 pç/cor
A64: 6. Preços do fornecedor (desconto progressivo)
A65: Preço base (R$) | B65: 52.79
A66: Faixa | B66: Peças | C66: Desconto | D66: Preço unitário | E66: Preço + Pix
A67: Faixa 1 | B67: 20–40 | C67: ='Regras Fornecedor'!$D$4 | D67: =ROUND($B$65*(1-C67),2) | E67: =ROUND(D67*(1-'Regras Fornecedor'!$B$10),2)
A68: Faixa 2 | B68: 40–80 | C68: ='Regras Fornecedor'!$D$5 | D68: =ROUND($B$65*(1-C68),2) | E68: =ROUND(D68*(1-'Regras Fornecedor'!$B$10),2)
A69: Faixa 3 | B69: 80–100 | C69: ='Regras Fornecedor'!$D$6 | D69: =ROUND($B$65*(1-C69),2) | E69: =ROUND(D69*(1-'Regras Fornecedor'!$B$10),2)
A70: Faixa 4 | B70: 100–300 | C70: ='Regras Fornecedor'!$D$7 | D70: =ROUND($B$65*(1-C70),2) | E70: =ROUND(D70*(1-'Regras Fornecedor'!$B$10),2)
A71: Faixa 5 | B71: 300–999 | C71: ='Regras Fornecedor'!$D$8 | D71: =ROUND($B$65*(1-C71),2) | E71: =ROUND(D71*(1-'Regras Fornecedor'!$B$10),2)
A73: 7. Custo HMZT e margem (lote de 20 peças, Pix)
A74: Peça (20 pç, Pix) | B74: =E67
A75: Personalização + etiqueta + tag (R$/pç) | B75: 15 | C75: Estimativa HMZT — trocar pelo orçamento real
A76: Frete rateado + embalagem (R$/pç) | B76: 5 | C76: Estimativa HMZT — trocar pelo orçamento real
A77: Custo unitário estimado | B77: =SUM(B74:B76)
A78: Preço de venda HMZT (R$) | B78: 169 | C78: Sugestão do dossiê — ajustar
A79: Impostos + gateway (% do preço) | B79: 0 | C79: A preencher (Simples + taxa Asaas)
A80: Margem bruta (R$) | B80: =B78-B77
A81: Margem bruta (%) | B81: =IF(B78=0,0,(B78-B77)/B78)
A82: Margem após impostos/gateway (%) | B82: =IF(B78=0,0,(B78*(1-B79)-B77)/B78) | C82: Ainda sem frete ao cliente e mídia
A84: 8. Contradições e erros ⚠️
A85: ⚠️ Sublimação oferecida em 100% algodão
A86: ⚠️ Chinese Cotton citada como 180g (página P06 diz 160g)
A87: ⚠️ Grade regular só até GG
A88: ⚠️ Oversized sem página/SKU visível
A89: ⚠️ Referência com 12 dígitos
A91: 9. Comunicação HMZT
A92: ✅ Pode usar | D92: 📣 / ⛔ Não usar
A93: Heavyweight 300 g/m², fio 2 cabos | D93: Origem Xinjiang (NUNCA citar)
A94: 100% algodão de fibra longa | D94: "95% das heavyweight nacionais…"
A95: Gola estruturada, reforço ombro a ombro | D95: "Não forma pilling", "maior recompra"
A96: Regular e oversized
A98: 10. Pendências com o fornecedor
A99: Pendência | B99: Status | C99: Responsável | D99: Resposta
A100: Como pedir a oversized (SKU, fotos) | B100: Aberta
A101: Regular tem EG? | B101: Aberta
A102: Orçamento silk/DTF A3 + bordado | B102: Aberta
A103: Documentação de origem | B103: Aberta
A104: Resto do FAQ | B104: Aberta
A106: 11. Fluxo de prompts de lookbook (docs/shop-confeccao/prompts/P05-prompts.md)
A107: Foto | B107: Origem no print | C107: Formato | D107: Status
A108: F1 — Hero frontal segurando a barra | B108: Foto principal e 1ª miniatura | C108: 4:5 | D108: A gerar
A109: F2 — 3/4 | B109: 2ª foto e 2ª miniatura | C109: 4:5 | D109: A gerar
A110: F3 — Costas | B110: 3ª foto e 3ª miniatura | C110: 4:5 | D110: A gerar
A111: F4 — Mockup de personalização (versão HMZT) | B111: 4ª miniatura — no original é a arte promocional do fornecedor sobre peça off-white; aqui vira base lisa para arte HMZT | C111: 4:5 | D111: A gerar
...

Sheet P06
A1: P06 — Camiseta Chinese Cotton 160g
A3: 1. Identificação
A4: Código HMZT | B4: HMZT-P06-REG-XJG160
A5: Fornecedor | B5: Lunfe Malhas — fabricação própria, Itajaí-SC
A6: Referência | B6: 7908365128857 (EAN-13)
A7: URL | B7: lunfemalhas.com.br/camiseta-chinese-cotton-atacado-lunfe
A8: Categoria no site | B8: Camisetas › Masculino › Premium
A9: Linha HMZT recomendada | B9: Essencial (alternativa ⚠️ Xinjiang)
A10: Estoque | B10: 5 cores em pronta entrega permanente
A11: Descritor canônico (IA) | B11: Camiseta masculina regular fit, gola careca canelada fina, malha leve de algodão penteado com leve brilho acetinado.
A13: 2. Especificação técnica
A14: Item | B14: Valor | C14: Fonte
A15: Composição | B15: 100% algodão importado — Xinjiang, China ⚠️
A16: Fibra | B16: Longa, staple 28–30 mm
A17: Fio | B17: Penteado, 30/1
A18: Gramatura | B18: 160 g/m² ± 5% (⚠️ texto do P05 diz 180g)
A19: Rolo / rendimento | B19: 1,80 m tubular aberta · 4,0–4,5 camisetas/m (M)
A20: Modelagem | B20: Regular fit
A21: Gola | B21: Canelada 2/1, fecho em anel (sem emenda frontal)
A22: Ombros | B22: Reforço ombro a ombro
A23: Costuras | B23: Ponto cadeia
A24: Barras | B24: Dupla nas mangas e barra
A25: Tratamentos | B25: Pré-encolhimento (<3%), tingimento reativo, anti-torção, anti-pilling enzimático, amaciamento
A27: 3. Tabela de medidas (cm)
A28: Tamanho | B28: Comprimento | C28: Largura | D28: Ombros | E28: Mangas
A29: P | B29: 70 | C29: 52 | D29: 44 | E29: 16
A30: M | B30: 72 | C30: 54 | D30: 46 | E30: 18
A31: G | B31: 74 | C31: 56 | D31: 48 | E31: 20
A32: GG | B32: 76 | C32: 58 | D32: 50 | E32: 22
A33: EG | B33: 78 | C33: 60 | D33: 52 | E33: 24
A34: ± 2 cm. Grade customizada acima de 200 pç.
A35: Modelo das fotos: 1,84 m · 84 kg · veste M
A37: 4. Cores disponíveis
A38: Cor | B38: Código HMZT | C38: Ref. fornecedor | D38: Observação
A39: Preto | B39: PRT | C39: CHC-PRT | D39: Maior giro
A40: Marinho | B40: MAR | C40: CHC-MRN | D40: 2º maior giro
A41: Verde Militar | B41: VML | C41: CHC-VML
A42: Azul Celeste | B42: AZC | C42: CHC-AZC
A43: Off White | B43: OFF | C43: CHC-OFW | D43: Cor das fotos
A44: Pantone a partir de 100 pç/cor.
A46: 5. Personalização (preço sempre sob orçamento)
A47: Técnica | B47: Detalhe | C47: Mínimo
A48: Silk base d'água / plastisol / gel / puff 3D / foil / silicone 3D | B48: 6 técnicas | C48: 20 pç
A49: DTF | B49: Full color | C49: 20 pç
A50: Bordado | B50: 📣 "até 15.000 pontos" — preferir ≤ 8.000 em 160g | C50: 20 pç
A51: Etiqueta private label | C51: 20 pç
A52: Embalagem customizada | C52: 50 pç
A53: Cor Pantone | C53: 100 pç/cor
A55: 6. Preços do fornecedor (desconto progressivo)
A56: Preço base (R$) | B56: 44.2
A57: Faixa | B57: Peças | C57: Desconto | D57: Preço unitário | E57: Preço + Pix
A58: Faixa 1 | B58: 20–40 | C58: ='Regras Fornecedor'!$D$4 | D58: =ROUND($B$56*(1-C58),2) | E58: =ROUND(D58*(1-'Regras Fornecedor'!$B$10),2)
A59: Faixa 2 | B59: 40–80 | C59: ='Regras Fornecedor'!$D$5 | D59: =ROUND($B$56*(1-C59),2) | E59: =ROUND(D59*(1-'Regras Fornecedor'!$B$10),2)
A60: Faixa 3 | B60: 80–100 | C60: ='Regras Fornecedor'!$D$6 | D60: =ROUND($B$56*(1-C60),2) | E60: =ROUND(D60*(1-'Regras Fornecedor'!$B$10),2)
A61: Faixa 4 | B61: 100–300 | C61: ='Regras Fornecedor'!$D$7 | D61: =ROUND($B$56*(1-C61),2) | E61: =ROUND(D61*(1-'Regras Fornecedor'!$B$10),2)
A62: Faixa 5 | B62: 300–999 | C62: ='Regras Fornecedor'!$D$8 | D62: =ROUND($B$56*(1-C62),2) | E62: =ROUND(D62*(1-'Regras Fornecedor'!$B$10),2)
A64: 7. Custo HMZT e margem (lote de 20 peças, Pix)
A65: Peça (20 pç, Pix) | B65: =E58
A66: Personalização + etiqueta + tag (R$/pç) | B66: 9 | C66: Estimativa HMZT — trocar pelo orçamento real
A67: Frete rateado + embalagem (R$/pç) | B67: 4 | C67: Estimativa HMZT — trocar pelo orçamento real
A68: Custo unitário estimado | B68: =SUM(B65:B67)
A69: Preço de venda HMZT (R$) | B69: 119 | C69: Sugestão do dossiê — ajustar
A70: Impostos + gateway (% do preço) | B70: 0 | C70: A preencher (Simples + taxa Asaas)
A71: Margem bruta (R$) | B71: =B69-B68
A72: Margem bruta (%) | B72: =IF(B69=0,0,(B69-B68)/B69)
A73: Margem após impostos/gateway (%) | B73: =IF(B69=0,0,(B69*(1-B70)-B68)/B69) | C73: Ainda sem frete ao cliente e mídia
A75: 8. Contradições e erros ⚠️
A76: ⚠️ 160g × 180g entre textos
A77: ⚠️ Fibra 28–30 mm × 28–32 mm (texto P07)
A78: ⚠️ "Rastreabilidade completa" confirma a origem Xinjiang
A79: ⚠️ Bordado 15.000 pontos em 160g é otimista
A81: 9. Comunicação HMZT
A82: ✅ Pode usar | D82: 📣 / ⛔ Não usar
A83: Algodão de fibra longa, fio penteado | D83: Origem Xinjiang (NUNCA citar)
A84: Pré-encolhida, anti-torção, tingimento reativo | D84: "Campeã de vendas", "maior recompra"
A85: Fabricada em Santa Catarina | D85: "Amacia com as lavagens"
A87: 10. Pendências com o fornecedor
A88: Pendência | B88: Status | C88: Responsável | D88: Resposta
A89: Gramatura real (160 × 180) | B89: Aberta
A90: Orçamento de personalização | B90: Aberta
A91: Documentação de origem | B91: Aberta
A92: Comparar com Prime Cotton BCI | B92: Aberta
A94: 11. Fluxo de prompts de lookbook (docs/shop-confeccao/prompts/P06-prompts.md)
A95: Foto | B95: Origem no print | C95: Formato | D95: Status
A96: F1 — Hero puxando a barra | B96: Foto principal e 1ª miniatura | C96: 4:5 | D96: A gerar
A97: F2 — 3/4 mão no bolso, olhar lateral | B97: 2ª foto e 2ª miniatura | C97: 4:5 | D97: A gerar
A98: F3 — Detalhe gola e ombro | B98: 3ª foto e 3ª miniatura | C98: 4:5 | D98: A gerar
A99: F4 — Costas | B99: 4ª miniatura | C99: 4:5 | D99: A gerar

Sheet P07
A1: P07 — Camiseta Cotton Peruano 220g com Elastano
A3: 1. Identificação
A4: Código HMZT | B4: HMZT-P07-REG-PER220
A5: Fornecedor | B5: Lunfe Malhas — fabricação própria, Itajaí-SC
A6: Referência | B6: 7892474270330 (EAN-13)
A7: URL | B7: lunfemalhas.com.br/camiseta-cotton-peruano-220g-elastano-atacado-lunfe
A8: Categoria no site | B8: Camisetas › Masculino › Premium
A9: Linha HMZT recomendada | B9: Premium (alternativa)
A10: Estoque | B10: 🔴 Página: "Esse acabou" × texto: 6 cores em estoque
A11: Descritor canônico (IA) | B11: Camiseta masculina regular fit, gola careca de ribana fina, jersey de algodão com leve brilho acetinado que acompanha o corpo.
A13: 2. Especificação técnica
A14: Item | B14: Valor | C14: Fonte
A15: Composição | B15: 96% algodão peruano (G. barbadense) + 4% elastano
A16: Fibra | B16: Extra-longa, staple > 34 mm (Pima peruano ou Tangüis?)
A17: Construção | B17: Jersey 30/1
A18: Gramatura | B18: 220 g/m²
A19: Modelagem | B19: Regular fit
A20: Gola | B20: Careca, ribana reforçada
A21: Mangas | B21: Curtas, barra dupla
A22: Barra | B22: Dupla, acabamento invisível
A23: Costuras | B23: Reforçadas; ombro a ombro com fita
A24: Tratamentos | B24: Pré-encolhimento; fixação de cor de alta solidez
A25: Elastano | B25: Memória de forma, caimento, menos rugas
A26: Opacidade | B26: Opaca em todas as cores
A28: 3. Tabela de medidas (cm)
A29: Tamanho | B29: Comprimento | C29: Largura | D29: Ombros | E29: Mangas
A30: P | B30: 70 | C30: 52 | D30: 44 | E30: 16
A31: M | B31: 72 | C31: 54 | D31: 46 | E31: 18
A32: G | B32: 74 | C32: 56 | D32: 48 | E32: 20
A33: GG | B33: 76 | C33: 58 | D33: 50 | E33: 22
A34: EG | B34: 78 | C34: 60 | D34: 52 | E34: 24
A35: Em cm, em repouso, ± 2 cm.
A36: Modelo das fotos: 1,84 m · 84 kg · veste M
A38: 4. Cores disponíveis
A39: Cor | B39: Código HMZT | C39: Ref. fornecedor | D39: Observação
A40: Preto | B40: PRT | C40: CPR-PRT | D40: Cor das fotos
A41: Off White | B41: OFF | C41: CPR-OFW
A42: Bege | B42: BGE | C42: CPR-BGE | D42: Provável nude da 5ª foto
A43: Marinho | B43: MAR | C43: CPR-MRN
A44: Bordô | B44: BDO | C44: CPR-BDO
A45: Verde Militar | B45: VML | C45: CPR-VML
A46: Pantone a partir de 100 pç/cor, 15–25 dias úteis.
A48: 5. Personalização (preço sempre sob orçamento)
A49: Técnica | B49: Detalhe | C49: Mínimo
A50: Silk base d'água | B50: Toque zero | C50: 20 pç
A51: DTF | B51: Full color | C51: 20 pç
A52: Bordado | B52: Peito, mangas | C52: 20 pç
A53: Sublimação | B53: ⚠️ Não funciona com 96% algodão — não usar | C53: 20 pç
A54: Etiqueta private label | B54: Interna + tag | C54: 20 pç
A55: Embalagem customizada | C55: 50 pç
A56: Cor Pantone | C56: 100 pç/cor
A58: 6. Preços do fornecedor (desconto progressivo)
A59: Preço base (R$) | B59: 55
A60: Faixa | B60: Peças | C60: Desconto | D60: Preço unitário | E60: Preço + Pix
A61: Faixa 1 | B61: 20–40 | C61: ='Regras Fornecedor'!$D$4 | D61: =ROUND($B$59*(1-C61),2) | E61: =ROUND(D61*(1-'Regras Fornecedor'!$B$10),2)
A62: Faixa 2 | B62: 40–80 | C62: ='Regras Fornecedor'!$D$5 | D62: =ROUND($B$59*(1-C62),2) | E62: =ROUND(D62*(1-'Regras Fornecedor'!$B$10),2)
A63: Faixa 3 | B63: 80–100 | C63: ='Regras Fornecedor'!$D$6 | D63: =ROUND($B$59*(1-C63),2) | E63: =ROUND(D63*(1-'Regras Fornecedor'!$B$10),2)
A64: Faixa 4 | B64: 100–300 | C64: ='Regras Fornecedor'!$D$7 | D64: =ROUND($B$59*(1-C64),2) | E64: =ROUND(D64*(1-'Regras Fornecedor'!$B$10),2)
A65: Faixa 5 | B65: 300–999 | C65: ='Regras Fornecedor'!$D$8 | D65: =ROUND($B$59*(1-C65),2) | E65: =ROUND(D65*(1-'Regras Fornecedor'!$B$10),2)
A67: 7. Custo HMZT e margem (lote de 20 peças, Pix)
A68: Peça (20 pç, Pix) | B68: =E61
A69: Personalização + etiqueta + tag (R$/pç) | B69: 11.5 | C69: Estimativa HMZT — trocar pelo orçamento real
A70: Frete rateado + embalagem (R$/pç) | B70: 6 | C70: Estimativa HMZT — trocar pelo orçamento real
A71: Custo unitário estimado | B71: =SUM(B68:B70)
A72: Preço de venda HMZT (R$) | B72: 149 | C72: Sugestão do dossiê — ajustar
A73: Impostos + gateway (% do preço) | B73: 0 | C73: A preencher (Simples + taxa Asaas)
A74: Margem bruta (R$) | B74: =B72-B71
A75: Margem bruta (%) | B75: =IF(B72=0,0,(B72-B71)/B72)
A76: Margem após impostos/gateway (%) | B76: =IF(B72=0,0,(B72*(1-B73)-B71)/B72) | C76: Ainda sem frete ao cliente e mídia
A78: 8. Contradições e erros ⚠️
A79: ⚠️ Esgotado na página × em estoque no texto
A80: ⚠️ 6× com juros (página) × sem juros (texto)
A81: ⚠️ "30/1s mais grosso que 30/1" — mesmo fio
A82: ⚠️ Sublimação oferecida em algodão
A83: ⚠️ Cores das fotos × lista
A85: 9. Comunicação HMZT
A86: ✅ Pode usar | D86: 📣 / ⛔ Não usar
A87: Algodão peruano de fibra extra-longa — só com a variedade confirmada | D87: "Migração irreversível", recompra, LTV 3–5×
A88: 96% algodão, 4% elastano: volta à forma | D88: "Camiseta de R$ 150"
A89: 220 g/m², opaca, pré-encolhida | D89: "Aristocracia do algodão"
A91: 10. Pendências com o fornecedor
A92: Pendência | B92: Status | C92: Responsável | D92: Resposta
A93: Variedade: Pima peruano ou Tangüis? | B93: Aberta
A94: Reposição | B94: Aberta
A95: Juros no cartão | B95: Aberta
A96: Orçamento bordado + etiqueta | B96: Aberta
A97: Frete Itajaí → SP | B97: Aberta
A99: 11. Fluxo de prompts de lookbook (docs/shop-confeccao/prompts/P07-prompts.md)
A100: Foto | B100: Origem no print | C100: Formato | D100: Status
A101: F1 — Hero 3/4 | B101: Foto principal e 1ª miniatura | C101: 4:5 | D101: A gerar
A102: F2 — Detalhe gola e manga | B102: 2ª foto e 2ª miniatura | C102: 4:5 | D102: A gerar
A103: F3 — Frontal leve 3/4 | B103: 3ª foto e 3ª miniatura | C103: 4:5 | D103: A gerar
A104: F4 — Macro da malha | B104: 3ª foto do 2º print — close de textura ocupando o quadro | C104: 1:1 | D104: A gerar
A105: F5 — Variação de cor | B105: 4ª/5ª miniatura — peça nude/rosé com calça preta | C105: 4:5 | D105: A gerar

Sheet P08
A1: P08 — Camiseta Egyptian Cotton Fio 50/1 com Elastano
A3: 1. Identificação
A4: Código HMZT | B4: HMZT-P08-REG-EGY50
A5: Fornecedor | B5: Lunfe Malhas — fabricação própria, Itajaí-SC
A6: Referência | B6: 7891557272995 (EAN-13)
A7: URL | B7: lunfemalhas.com.br/camiseta-egyptian-cotton-atacado-algodao-egipcio-50-1-lunfe
A8: Categoria no site | B8: Camisetas › Masculino › Premium
A9: Linha HMZT recomendada | B9: Topo / Assinatura (inclui unissex)
A10: Estoque | B10: 7 cores em estoque (off white com traço na página ⚠️)
A11: Descritor canônico (IA) | B11: Camiseta regular fit de caimento fluido, gola careca de ribana lisa fina, malha leve de algodão muito lisa com brilho natural sutil.
A13: 2. Especificação técnica
A14: Item | B14: Valor | C14: Fonte
A15: Composição | B15: 91,5% algodão egípcio (G. barbadense) + 8,5% elastano
A16: Fibra | B16: Extra-longa, staple 32–36 mm
A17: Fio | B17: Penteado e refinado 50/1 (o mais fino do catálogo)
A18: Gramatura | B18: 170 g/m²
A19: Modelagem | B19: Regular fit, caimento fluido
A20: Gola | B20: Ribana 2/1 lisa (sem canelado)
A21: Costura interna | B21: Ponto conjugado (costura plana)
A22: Ombros | B22: Reforço ombro a ombro
A23: Barra | B23: Dupla
A24: Tratamentos | B24: Pré-encolhimento, fixação reativa de cor, amaciamento
A25: Certificação | B25: OEKO-TEX Standard 100 (algodão e elastano)
A27: 3. Tabela de medidas (cm)
A28: Tamanho | B28: Comprimento | C28: Largura | D28: Ombros | E28: Mangas
A29: P | B29: 70 | C29: 52 | D29: 44 | E29: 16
A30: M | B30: 72 | C30: 54 | D30: 46 | E30: 18
A31: G | B31: 74 | C31: 56 | D31: 48 | E31: 20
A32: GG | B32: 76 | C32: 58 | D32: 50 | E32: 22
A33: EG | B33: 78 | C33: 60 | D33: 52 | E33: 24
A34: Em cm, em repouso, ± 2 cm.
A35: Modelo das fotos: 1,84 m · 84 kg · veste M
A37: 4. Cores disponíveis
A38: Cor | B38: Código HMZT | C38: Ref. fornecedor | D38: Observação
A39: Off White | B39: OFF | C39: EGY-OFW | D39: Traço na bolinha — confirmar estoque
A40: Bordô | B40: BDO | C40: EGY-BRD
A41: Bege | B41: BGE | C41: EGY-BGE | D41: 7ª cor que faltava no seletor
A42: Preto | B42: PRT | C42: EGY-PRT
A43: Verde Militar | B43: VML | C43: EGY-VML
A44: Laranja | B44: LAR | C44: EGY-LRJ
A45: Verde | B45: VRD | C45: EGY-VRD
A46: Pantone a partir de 100 pç/cor, 15–25 dias úteis.
A48: 5. Personalização (preço sempre sob orçamento)
A49: Técnica | B49: Detalhe | C49: Mínimo
A50: Silk base d'água | B50: Toque zero (evitar plastisol) | C50: 20 pç
A51: DTF | B51: Full color | C51: 20 pç
A52: Bordado | B52: Exige entretela (elastano) | C52: 20 pç
A53: Etiqueta private label | B53: Interna + tag | C53: 20 pç
A54: Embalagem customizada | C54: 50 pç
A55: Cor Pantone | C55: 100 pç/cor
A57: 6. Preços do fornecedor (desconto progressivo)
A58: Preço base (R$) | B58: 52.65
A59: Faixa | B59: Peças | C59: Desconto | D59: Preço unitário | E59: Preço + Pix
A60: Faixa 1 | B60: 20–40 | C60: ='Regras Fornecedor'!$D$4 | D60: =ROUND($B$58*(1-C60),2) | E60: =ROUND(D60*(1-'Regras Fornecedor'!$B$10),2)
A61: Faixa 2 | B61: 40–80 | C61: ='Regras Fornecedor'!$D$5 | D61: =ROUND($B$58*(1-C61),2) | E61: =ROUND(D61*(1-'Regras Fornecedor'!$B$10),2)
A62: Faixa 3 | B62: 80–100 | C62: ='Regras Fornecedor'!$D$6 | D62: =ROUND($B$58*(1-C62),2) | E62: =ROUND(D62*(1-'Regras Fornecedor'!$B$10),2)
A63: Faixa 4 | B63: 100–300 | C63: ='Regras Fornecedor'!$D$7 | D63: =ROUND($B$58*(1-C63),2) | E63: =ROUND(D63*(1-'Regras Fornecedor'!$B$10),2)
A64: Faixa 5 | B64: 300–999 | C64: ='Regras Fornecedor'!$D$8 | D64: =ROUND($B$58*(1-C64),2) | E64: =ROUND(D64*(1-'Regras Fornecedor'!$B$10),2)
A66: 7. Custo HMZT e margem (lote de 20 peças, Pix)
A67: Peça (20 pç, Pix) | B67: =E60
A68: Personalização + etiqueta + tag (R$/pç) | B68: 15 | C68: Estimativa HMZT — trocar pelo orçamento real
A69: Frete rateado + embalagem (R$/pç) | B69: 6 | C69: Estimativa HMZT — trocar pelo orçamento real
A70: Custo unitário estimado | B70: =SUM(B67:B69)
A71: Preço de venda HMZT (R$) | B71: 189 | C71: Sugestão do dossiê — ajustar
A72: Impostos + gateway (% do preço) | B72: 0 | C72: A preencher (Simples + taxa Asaas)
A73: Margem bruta (R$) | B73: =B71-B70
A74: Margem bruta (%) | B74: =IF(B71=0,0,(B71-B70)/B71)
A75: Margem após impostos/gateway (%) | B75: =IF(B71=0,0,(B71*(1-B72)-B70)/B71) | C75: Ainda sem frete ao cliente e mídia
A77: 8. Contradições e erros ⚠️
A78: ⚠️ "50/1 é quase o dobro da finura do 30/1" — exagero
A79: ⚠️ "Como percal 400 fios" — sem base
A80: ⚠️ Fibra 32–36 × 36+ mm entre textos
A81: ⚠️ Tabela cita "Pima 200g peruano sob consulta"
A82: ⚠️ Off white com traço × em estoque
A84: 9. Comunicação HMZT
A85: ✅ Pode usar | D85: 📣 / ⛔ Não usar
A86: OEKO-TEX Standard 100 — com nº do certificado | D86: "O algodão mais nobre do mundo", "como seda"
A87: Algodão egípcio fibra extra-longa, fio 50/1 — só com comprovação | D87: "Maior conversão por toque"
A88: Caimento fluido, não amassa
A89: Costura plana, gola lisa
A91: 10. Pendências com o fornecedor
A92: Pendência | B92: Status | C92: Responsável | D92: Resposta
A93: Nº do certificado OEKO-TEX | B93: Aberta
A94: Comprovação egípcio (Giza? Cotton Egypt?) | B94: Aberta
A95: Estoque off white | B95: Aberta
A96: Modelagem feminina? | B96: Aberta
A97: Orçamento bordado com entretela | B97: Aberta
A99: 11. Fluxo de prompts de lookbook (docs/shop-confeccao/prompts/P08-prompts.md)
A100: Foto | B100: Origem no print | C100: Formato | D100: Status
A101: F1 — Frontal plano aberto | B101: Foto principal e 1ª miniatura | C101: 4:5 | D101: A gerar
A102: F2 — Detalhe gola e ombro | B102: 2ª foto e 2ª miniatura | C102: 4:5 | D102: A gerar
A103: F3 — Costas | B103: 3ª foto e 3ª miniatura | C103: 4:5 | D103: A gerar
A104: F4 — 3/4 mão no bolso | B104: 4ª miniatura (baixa resolução — leitura aproximada) | C104: 4:5 | D104: A gerar

Sheet P09
A1: P09 — Camiseta Suedine Light
A3: 1. Identificação
A4: Código HMZT | B4: HMZT-P09-REG-SUELT
A5: Fornecedor | B5: Lunfe Malhas — fabricação própria, Itajaí-SC
A6: Referência | B6: 7908365128002 (EAN-13)
A7: URL | B7: lunfemalhas.com.br/camiseta-suedine-light-atacado-toque-aveludado-lunfe
A8: Categoria no site | B8: Camisetas › Masculino › Premium
A9: Linha HMZT recomendada | B9: Suedine light
A10: Estoque | B10: Lisas em estoque, 24h
A11: Descritor canônico (IA) | B11: Camiseta masculina regular fit, gola careca canelada, malha leve aveludada e fosca, caimento reto e fluido.
A13: 2. Especificação técnica
A14: Item | B14: Valor | C14: Fonte
A15: Composição | B15: Blend algodão + fibras sintéticas — % NÃO informado
A16: Gramatura | B16: "Leve" — número NÃO informado
A17: Acabamento | B17: Suedine aveludado
A18: Modelagem | B18: Regular fit, caimento fluido
A19: Gola | B19: Careca
A20: Acabamentos | B20: Costuras reforçadas, pré-encolhida
A21: Uso | B21: Ano inteiro; segunda pele sob jaqueta
A23: 3. Tabela de medidas (cm)
A24: Tamanho | B24: Comprimento | C24: Largura | D24: Ombros | E24: Mangas
A25: P | B25: 70 | C25: 52 | D25: 44 | E25: 16
A26: M | B26: 72 | C26: 54 | D26: 46 | E26: 18
A27: G | B27: 74 | C27: 56 | D27: 48 | E27: 20
A28: GG | B28: 76 | C28: 58 | D28: 50 | E28: 22
A29: EG | B29: 78 | C29: 60 | D29: 52 | E29: 24
A30: Em cm, variação 1–2 cm.
A31: Modelo das fotos: 1,84 m · 84 kg · veste M
A33: 4. Cores disponíveis
A34: Cor | B34: Código HMZT | C34: Ref. fornecedor | D34: Observação
A35: Bege | B35: BGE | C35: — | D35: ⚠️ Fotos em caramelo — é este?
A36: Preto | B36: PRT | C36: —
A37: Azul Bebê | B37: AZB | C37: —
A38: Laranja | B38: LAR | C38: —
A39: Verde | B39: VRD | C39: —
A40: Mockup do fornecedor mostra off white (fora da lista). Sem códigos de referência.
A42: 5. Personalização (preço sempre sob orçamento)
A43: Técnica | B43: Detalhe | C43: Mínimo
A44: Silk | B44: Testar aderência | C44: 20 pç?
A45: DTF | B45: Testar aderência | C45: 20 pç?
A46: Bordado | C46: 20 pç?
A47: Etiqueta private label | C47: 20 pç?
A49: 6. Preços do fornecedor (desconto progressivo)
A50: Preço base (R$) | B50: 44.8
A51: Faixa | B51: Peças | C51: Desconto | D51: Preço unitário | E51: Preço + Pix
A52: Faixa 1 | B52: 20–40 | C52: ='Regras Fornecedor'!$D$4 | D52: =ROUND($B$50*(1-C52),2) | E52: =ROUND(D52*(1-'Regras Fornecedor'!$B$10),2)
A53: Faixa 2 | B53: 40–80 | C53: ='Regras Fornecedor'!$D$5 | D53: =ROUND($B$50*(1-C53),2) | E53: =ROUND(D53*(1-'Regras Fornecedor'!$B$10),2)
A54: Faixa 3 | B54: 80–100 | C54: ='Regras Fornecedor'!$D$6 | D54: =ROUND($B$50*(1-C54),2) | E54: =ROUND(D54*(1-'Regras Fornecedor'!$B$10),2)
A55: Faixa 4 | B55: 100–300 | C55: ='Regras Fornecedor'!$D$7 | D55: =ROUND($B$50*(1-C55),2) | E55: =ROUND(D55*(1-'Regras Fornecedor'!$B$10),2)
A56: Faixa 5 | B56: 300–999 | C56: ='Regras Fornecedor'!$D$8 | D56: =ROUND($B$50*(1-C56),2) | E56: =ROUND(D56*(1-'Regras Fornecedor'!$B$10),2)
A58: 7. Custo HMZT e margem (lote de 20 peças, Pix)
A59: Peça (20 pç, Pix) | B59: =E52
A60: Personalização + etiqueta + tag (R$/pç) | B60: 10 | C60: Estimativa HMZT — trocar pelo orçamento real
A61: Frete rateado + embalagem (R$/pç) | B61: 4 | C61: Estimativa HMZT — trocar pelo orçamento real
A62: Custo unitário estimado | B62: =SUM(B59:B61)
A63: Preço de venda HMZT (R$) | B63: 129 | C63: Sugestão do dossiê — ajustar
A64: Impostos + gateway (% do preço) | B64: 0 | C64: A preencher (Simples + taxa Asaas)
A65: Margem bruta (R$) | B65: =B63-B62
A66: Margem bruta (%) | B66: =IF(B63=0,0,(B63-B62)/B63)
A67: Margem após impostos/gateway (%) | B67: =IF(B63=0,0,(B63*(1-B64)-B62)/B63) | C67: Ainda sem frete ao cliente e mídia
A69: 8. Contradições e erros ⚠️
A70: ⚠️ "Textura que não existe em outra composição" — P01/P04 também são suedine
A71: ⚠️ FAQ diz que a Suedine 300g é oversized (existe a regular)
A72: ⚠️ Caramelo nas fotos × Bege na lista
A73: ⚠️ Sem gramatura, % e condições de pagamento
A75: 9. Comunicação HMZT
A76: ✅ Pode usar | D76: 📣 / ⛔ Não usar
A77: Toque aveludado de suedine em malha leve | D77: "Premium antes de olhar a etiqueta"
A78: Pré-encolhida | D78: "Não bole"
A79: Composição exata só depois de informada
A81: 10. Pendências com o fornecedor
A82: Pendência | B82: Status | C82: Responsável | D82: Resposta
A83: Gramatura em g/m² | B83: Aberta
A84: Composição em % | B84: Aberta
A85: Referências de cor / caramelo | B85: Aberta
A86: Condições de pagamento | B86: Aberta
A87: Mínimos e preço de personalização | B87: Aberta
A89: 11. Fluxo de prompts de lookbook (docs/shop-confeccao/prompts/P09-prompts.md)
A90: Foto | B90: Origem no print | C90: Formato | D90: Status
A91: F1 — Hero 3/4 enrolando a manga | B91: Foto principal e 1ª miniatura | C91: 4:5 | D91: A gerar
A92: F2 — Detalhe gola e ombro | B92: 2ª foto e 2ª miniatura | C92: 4:5 | D92: A gerar
A93: F3 — Mockup de personalização (versão HMZT) | B93: 3ª foto — no original é a arte promocional do fornecedor sobre peça off-white em modelo negro; aqui vira base lisa para arte HMZT | C93: 4:5 | D93: A gerar

Sheet P10
A1: P10 — Camiseta Oversized Básica Suedine 300GSM (100% algodão)
A3: 1. Identificação
A4: Código HMZT | B4: HMZT-P10-OVS-SUEALG300
A5: Fornecedor | B5: Lunfe Malhas — fabricação própria, Itajaí-SC
A6: Referência | B6: 7896630253786
A7: URL | B7: lunfemalhas.com.br/camiseta-oversized-basica-lunfe-399
A8: Categoria no site | B8: Camisetas › Masculino › Oversized
A9: Linha HMZT recomendada | B9: Heavy — oversized (alternativa mais barata à P01)
A10: Estoque | B10: 6 cores no seletor; sem campo de disponibilidade; texto diz 'estoque limitado'
A11: Descritor canônico (IA) | B11: Camiseta masculina oversized boxy heavyweight, ombro bem caído no braço, manga curta larga até o cotovelo, gola careca de ribana canelada larga (2,5 cm), malha encorpada de 300 g/m² com superfície fosca e macia, corpo amplo e quadrado que se sustenta, barra reta abaixo do quadril. Peça lisa, sem logos. Fundo cinza claro de estúdio.
A13: 2. Especificação técnica
A14: Item | B14: Valor | C14: Fonte
A15: Tecido | B15: Malha suedine 'interlock de dupla frontura'
A16: Composição | B16: 100% algodão (P01, também suedine 300g, é 52/48)
A17: Gramatura | B17: 300 g/m², zero transparência
A18: Toque | B18: 'Aveludado / pele de pêssego' e 'acetinado' na mesma página
A19: Gola | B19: Ribana canelada 2,5 cm, alta densidade
A20: Reforço | B20: Ombro a ombro
A21: Modelagem | B21: True oversized boxy, ombros caídos
A22: Tamanhos | B22: Não informados
A23: Autoridade | B23: 'Elimina qualquer objeção de preço', 'vicia o cliente'
A24: Produção | B24: Fabricação própria — Itajaí, SC
A26: 3. Tabela de medidas (cm)
A27: ⚠️ Tabela de medidas não publicada. Modelo 1,84 m / 84 kg veste M. Pelas fotos é mais boxy que a P02 (ombro 6–8 cm no braço, manga no cotovelo). Não publicar medidas sem a tabela oficial.
A28: Modelo das fotos: 1,84 m · 84 kg · veste M
A30: 4. Cores disponíveis
A31: Cor | B31: Código HMZT | C31: Ref. fornecedor | D31: Observação
A32: Preto | B32: PRT | C32: — | D32: Fotos #14–15
A33: Branco | B33: BCO | C33: — | D33: Fotos #5–8
A34: Cinza | B34: CZA | C34: — | D34: Cinza médio/chumbo, fotos #1–4
A35: Bege | B35: BGE | C35: — | D35: Sem foto
A36: Azul Marinho | B36: MAR | C36: — | D36: Sem foto
A37: Rose Gold | B37: RSG | C37: — | D37: Rosé empoeirado, fotos #9–13
A38: 6 cores; fornecedor não publica refs. de cor nesta página. Bege e Azul Marinho sem foto.
A40: 5. Personalização (preço sempre sob orçamento)
A41: Técnica | B41: Detalhe | C41: Mínimo
A42: Bordado | B42: Peito ou costas — melhor contraste sobre superfície escovada | C42: 20 pç
A43: DTF | B43: Full color — peça-teste de aderência | C43: 20 pç
A44: Silk base d'água | B44: Testar sobre o felpado | C44: 20 pç
A45: Etiqueta private label | B45: Interna + tag | C45: 20 pç
A47: 6. Preços do fornecedor (desconto progressivo)
A48: Preço base (R$) | B48: 42
A49: Faixa | B49: Peças | C49: Desconto | D49: Preço unitário | E49: Preço + Pix
A50: Faixa 1 | B50: 20–40 | C50: ='Regras Fornecedor'!$D$4 | D50: =ROUND($B$48*(1-C50),2) | E50: =ROUND(D50*(1-'Regras Fornecedor'!$B$10),2)
A51: Faixa 2 | B51: 40–80 | C51: ='Regras Fornecedor'!$D$5 | D51: =ROUND($B$48*(1-C51),2) | E51: =ROUND(D51*(1-'Regras Fornecedor'!$B$10),2)
A52: Faixa 3 | B52: 80–100 | C52: ='Regras Fornecedor'!$D$6 | D52: =ROUND($B$48*(1-C52),2) | E52: =ROUND(D52*(1-'Regras Fornecedor'!$B$10),2)
A53: Faixa 4 | B53: 100–300 | C53: ='Regras Fornecedor'!$D$7 | D53: =ROUND($B$48*(1-C53),2) | E53: =ROUND(D53*(1-'Regras Fornecedor'!$B$10),2)
A54: Faixa 5 | B54: 300–999 | C54: ='Regras Fornecedor'!$D$8 | D54: =ROUND($B$48*(1-C54),2) | E54: =ROUND(D54*(1-'Regras Fornecedor'!$B$10),2)
A56: 7. Custo HMZT e margem (lote de 20 peças, Pix)
A57: Peça (20 pç, Pix) | B57: =E50
A58: Personalização + etiqueta + tag (R$/pç) | B58: 14 | C58: Estimativa HMZT — trocar pelo orçamento real
A59: Frete rateado + embalagem (R$/pç) | B59: 5 | C59: Estimativa HMZT — trocar pelo orçamento real
A60: Custo unitário estimado | B60: =SUM(B57:B59)
A61: Preço de venda HMZT (R$) | B61: 159 | C61: Sugestão do dossiê — ajustar
A62: Impostos + gateway (% do preço) | B62: 0 | C62: A preencher (Simples + taxa Asaas)
A63: Margem bruta (R$) | B63: =B61-B60
A64: Margem bruta (%) | B64: =IF(B61=0,0,(B61-B60)/B61)
A65: Margem após impostos/gateway (%) | B65: =IF(B61=0,0,(B61*(1-B62)-B60)/B61) | C65: Ainda sem frete ao cliente e mídia
A67: 8. Contradições e erros ⚠️
A68: ⚠️ Composição 100% algodão, R$ 42,00 × P01 (Oversized Suedine Peruano 300g) 52% algodão/48% poliéster, R$ 54,00.
A69: ⚠️ O comparativo da P02 ('Oversized Suedine 300g — 100% CO, R$ 42,00, 6 cores, mín. R$ 29,40') descreve esta P10, não a P01.
A70: ⚠️ Resumo: 'atacado a partir de R$ 28,99'; tabela: R$ 29,40 (= 42,00 × 0,70). R$ 28,99 é o preço base da P11.
A71: ⚠️ Suedine descrita como interlock de dupla frontura; nos dossiês P04/P09 é malha escovada (peach finish).
A72: ⚠️ 'Peletização' não é termo técnico; o processo é escovação/lixamento.
A73: ⚠️ Título diz 'toque acetinado'; texto diz 'aveludado/pele de pêssego' — opostos.
A74: ⚠️ Aba chama de 'Malhão Suedine'; a P12 é 'Malhão Compact', outra malha.
A75: ⚠️ Fotos mostram superfície fosca e lisa, sem felpado visível.
A77: 9. Comunicação HMZT
A78: ✅ Pode usar | D78: 📣 / ⛔ Não usar
A79: Malha heavyweight de 300 g/m², opaca. | D79: Gera autoridade / elimina qualquer objeção de preço / vicia o cliente / fideliza.
A80: Modelagem oversized boxy, ombro caído. | D80: Qualidade indestrutível / caimento de passarela / grife × feira.
A81: Gola canelada larga de 2,5 cm. | D81: Grandes marcas cobram R$ 150–180.
A82: Reforço ombro a ombro. | D82: Estoque limitado, reposição não é imediata (urgência artificial).
A83: Fabricada em Santa Catarina. | D83: Algodão nobre.
A84: Composição por extenso só após confirmação escrita. | D84: 100% algodão antes de confirmar.
D85: Toque acetinado e aveludado juntos.
A87: 10. Pendências com o fornecedor
A88: Pendência | B88: Status | C88: Responsável | D88: Resposta
A89: Composição real (100% algodão × 52/48) | B89: Aberta
A90: Diferença entre P10 e P01 | B90: Aberta
A91: Ficha do tecido (interlock ou meia malha escovada) | B91: Aberta
A92: Tabela de medidas | B92: Aberta
A93: Mínimo R$ 28,99 × R$ 29,40 | B93: Aberta
A94: Pix e parcelamento | B94: Aberta
A95: Estoque por cor e fotos de Bege/Marinho | B95: Aberta
A96: Peça-teste DTF/silk e orçamento de bordado costas | B96: Aberta
A98: 11. Fluxo de prompts de lookbook (docs/shop-confeccao/prompts/P10-prompts.md)
A99: Foto | B99: Origem no print | C99: Formato | D99: Status
A100: F1 — Corpo inteiro | B100: Origem: fotos #1 (cinza), #5 (branco), #9 e #10 (rose gold) e #14 (preto) da galeria — mesma pose de corpo inteiro em 4 cores | C100: 4:5 | D100: A gerar
A101: F2 — 3/4 meia figura | B101: Origem: foto #2 da galeria (cinza, leve 3/4, braços soltos, olhar na câmera) | C101: 4:5 | D101: A gerar
A102: F3 — Detalhe gola e ombro | B102: Origem: fotos #3 (cinza), #8 (branco) e #13 (rose gold) da galeria (close da gola larga e do ombro caído) | C102: 4:5 | D102: A gerar
A103: F4 — Mão na nuca | B103: Origem: fotos #4 (cinza), #7 (branco) e #11 (rose gold) da galeria | C103: 4:5 | D103: A gerar
A104: F5 — Mãos juntas na cintura | B104: Origem: foto #6 da galeria (branco, mãos juntas à frente, olhar para o lado) | C104: 4:5 | D104: A gerar
A105: F6 — Frontal meia figura | B105: Origem: fotos #12 (rose gold) e #15 (preto) da galeria (frontal, braços soltos, olhar direto) | C105: 4:5 | D105: A gerar

Sheet P11
A1: P11 — Camiseta Custo Inteligente Malha Algodão/Poliéster 160g
A3: 1. Identificação
A4: Código HMZT | B4: HMZT-P11-REG-PA160
A5: Fornecedor | B5: Lunfe Malhas — fabricação própria, Itajaí-SC
A6: Referência | B6: 7899516388428
A7: URL | B7: lunfemalhas.com.br/camiseta-custo-inteligente-atacado-malha-pa-lunfe
A8: Categoria no site | B8: Camisetas › Masculino › Regular Fit
A9: Linha HMZT recomendada | B9: Uniformes & Eventos (B2B) — fora da vitrine
A10: Estoque | B10: 6 cores em estoque; despacho em 24h úteis
A11: Descritor canônico (IA) | B11: Camiseta masculina regular fit, manga curta reta até o meio do bíceps, gola careca em ribana fina 1×1 de 2 cm sem pesponto aparente, meia malha leve de algodão com poliéster (160 g/m²), superfície lisa e fosca, cinza claro com aspecto mesclado, caimento leve que acompanha o corpo, barra dupla reta no quadril. Peça lisa, sem logos. Fundo cinza claro de estúdio.
A13: 2. Especificação técnica
A14: Item | B14: Valor | C14: Fonte
A15: Composição | B15: Meia malha algodão + poliéster — % não informado
A16: Gramatura | B16: 160 g/m²
A17: Modelagem | B17: Regular fit
A18: Gola | B18: Ribana 1×1, 2 cm, desagulhada (sem pesponto externo)
A19: Acabamentos | B19: Fita de cadarço ombro a ombro, ponto cadeia, barra dupla
A20: Tratamentos | B20: Pré-encolhimento mecânico, fixação de cor
A21: Tamanhos | B21: P, M, G, GG, EG
A22: Sigla 'PA' | B22: No mercado PA = poliamida; aqui usada para poliéster/algodão
A23: Secagem | B23: 'Seca 2–3× mais rápido que 100% algodão'
A24: Percepção | B24: '90% da percepção por 50% do custo'
A25: Produção | B25: Fabricação própria — Itajaí, SC
A27: 3. Tabela de medidas (cm)
A28: Tamanho | B28: Comprimento | C28: Largura | D28: Ombros | E28: Mangas
A29: P | B29: 70 | C29: 52 | D29: 44 | E29: 16
A30: M | B30: 72 | C30: 54 | D30: 46 | E30: 18
A31: G | B31: 74 | C31: 56 | D31: 48 | E31: 20
A32: GG | B32: 76 | C32: 58 | D32: 50 | E32: 22
A33: EG | B33: 78 | C33: 60 | D33: 52 | E33: 24
A34: Molde regular único Lunfe, em cm, ± 2 cm. Modelo 1,84 m / 84 kg veste M.
A35: Modelo das fotos: 1,84 m · 84 kg · veste M
A37: 4. Cores disponíveis
A38: Cor | B38: Código HMZT | C38: Ref. fornecedor | D38: Observação
A39: Preto | B39: PRT | C39: CIN-PRT
A40: Branco | B40: BCO | C40: CIN-BRA
A41: Marinho | B41: MAR | C41: CIN-MRN | D41: ⚠️ foto mostra azul royal
A42: Cinza Claro | B42: CZC | C42: CIN-CZC | D42: Mescla clara
A43: Bege | B43: BGE | C43: CIN-BGE
A44: Azul Bebê | B44: AZB | C44: CIN-AZB | D44: Sem foto
A45: 6 cores. Pantone a partir de 100 pç/cor, 15–25 dias úteis. O azul das fotos (#8–10) é royal, não marinho.
A47: 5. Personalização (preço sempre sob orçamento)
A48: Técnica | B48: Detalhe | C48: Mínimo
A49: Silk base d'água | B49: Uniformes e brindes | C49: 20 pç
A50: Silk plastisol | B50: Escuras — pedir bloqueador de migração | C50: 20 pç
A51: Gel / Puff 3D / Foil | B51: Efeitos | C51: 20 pç
A52: DTF | B52: Full color | C52: 20 pç
A53: Bordado industrial | B53: Logo pequeno com entretela | C53: 20 pç
A54: Etiqueta private label | B54: Interna + tag | C54: 20 pç
A55: Embalagem customizada | B55: Saco, caixa, tag | C55: 50 pç
A56: Cor Pantone | B56: Tingimento exclusivo | C56: 100 pç/cor
A57: Sublimação | B57: ⚠️ Só com % de poliéster confirmado e peça-teste | C57: consultar
A59: 6. Preços do fornecedor (desconto progressivo)
A60: Preço base (R$) | B60: 28.99
A61: Faixa | B61: Peças | C61: Desconto | D61: Preço unitário | E61: Preço + Pix
A62: Faixa 1 | B62: 20–40 | C62: ='Regras Fornecedor'!$D$4 | D62: =ROUND($B$60*(1-C62),2) | E62: =ROUND(D62*(1-'Regras Fornecedor'!$B$10),2)
A63: Faixa 2 | B63: 40–80 | C63: ='Regras Fornecedor'!$D$5 | D63: =ROUND($B$60*(1-C63),2) | E63: =ROUND(D63*(1-'Regras Fornecedor'!$B$10),2)
A64: Faixa 3 | B64: 80–100 | C64: ='Regras Fornecedor'!$D$6 | D64: =ROUND($B$60*(1-C64),2) | E64: =ROUND(D64*(1-'Regras Fornecedor'!$B$10),2)
A65: Faixa 4 | B65: 100–300 | C65: ='Regras Fornecedor'!$D$7 | D65: =ROUND($B$60*(1-C65),2) | E65: =ROUND(D65*(1-'Regras Fornecedor'!$B$10),2)
A66: Faixa 5 | B66: 300–999 | C66: ='Regras Fornecedor'!$D$8 | D66: =ROUND($B$60*(1-C66),2) | E66: =ROUND(D66*(1-'Regras Fornecedor'!$B$10),2)
A68: 7. Custo HMZT e margem (lote de 20 peças, Pix)
A69: Peça (20 pç, Pix) | B69: =E62
A70: Personalização + etiqueta + tag (R$/pç) | B70: 8 | C70: Estimativa HMZT — trocar pelo orçamento real
A71: Frete rateado + embalagem (R$/pç) | B71: 3 | C71: Estimativa HMZT — trocar pelo orçamento real
A72: Custo unitário estimado | B72: =SUM(B69:B71)
A73: Preço de venda HMZT (R$) | B73: 69 | C73: Sugestão do dossiê — ajustar
A74: Impostos + gateway (% do preço) | B74: 0 | C74: A preencher (Simples + taxa Asaas)
A75: Margem bruta (R$) | B75: =B73-B72
A76: Margem bruta (%) | B76: =IF(B73=0,0,(B73-B72)/B73)
A77: Margem após impostos/gateway (%) | B77: =IF(B73=0,0,(B73*(1-B74)-B72)/B73) | C77: Ainda sem frete ao cliente e mídia
A79: 8. Contradições e erros ⚠️
A80: ⚠️ Seletor da página: R$ 39,90. Descrição: base R$ 28,99 e 'a partir de R$ 20,29' (= 28,99 × 0,70).
A81: ⚠️ Composição 'PA' sem percentual — sublimação, secagem e anti-rugas dependem do %.
A82: ⚠️ 'PA' significa poliamida no mercado têxtil; poliéster/algodão não é PA.
A83: ⚠️ Cor 'Marinho' na lista; a foto mostra azul royal.
A84: ⚠️ Comparativo cita 'Estonada 175g R$ 37,26' (regular); a P02 cita 'Estonada Oversized Bolso 175g R$ 39,78' — ambas 'Esse acabou' nas relacionadas.
A85: ⚠️ 'Primeiro lote com private label abaixo de R$ 600': 20 × R$ 26,09 = R$ 521,80 só em peças; etiqueta é sob orçamento.
A87: 9. Comunicação HMZT
A88: ✅ Pode usar | D88: 📣 / ⛔ Não usar
A89: Gola desagulhada em ribana de 2 cm, sem pesponto. | D89: Qualidade que o cliente final reconhece / não parece promocional.
A90: Algodão com poliéster: amassa menos e aguenta lavagem frequente. | D90: 90% da percepção por 50% do custo / a peça mais inteligente.
A91: Pré-encolhida, reforço ombro a ombro. | D91: Menos devolução, recompra e indicação.
A92: 6 cores, pronta entrega. | D92: Seca 2–3× mais rápido / custo por uso inferior.
A93: Fabricada em Santa Catarina. | D93: MVP mais acessível da indústria.
D94: 'Malha PA' em etiqueta ou site.
D95: Sublimação sem % de poliéster e teste.
D96: Marca HMZT como peça premium.
A98: 10. Pendências com o fornecedor
A99: Pendência | B99: Status | C99: Responsável | D99: Resposta
A100: Preço real (R$ 39,90 × R$ 28,99) | B100: Aberta
A101: Composição em % | B101: Aberta
A102: Marinho × azul royal das fotos | B102: Aberta
A103: Foto do Azul Bebê | B103: Aberta
A104: Sublimação: % e cores | B104: Aberta
A105: Bloqueador de migração no plastisol | B105: Aberta
A106: Orçamento silk 1 cor peito, bordado, etiqueta | B106: Aberta
A108: 11. Fluxo de prompts de lookbook (docs/shop-confeccao/prompts/P11-prompts.md)
A109: Foto | B109: Origem no print | C109: Formato | D109: Status
A110: F1 — Frontal olhar lateral | B110: Origem: fotos #1 (cinza claro), #11 (bege) e #15 (branco) da galeria (frontal com leve giro, braços soltos, olhar para fora) | C110: 4:5 | D110: A gerar
A111: F2 — Mão na nuca | B111: Origem: fotos #2 (cinza claro), #5 (preto) e #10 (azul) da galeria | C111: 4:5 | D111: A gerar
...

Sheet P12
A1: P12 — Camiseta Malhão Compact Algodão BCI 280g
A3: 1. Identificação
A4: Código HMZT | B4: HMZT-P12-REG-BCI280
A5: Fornecedor | B5: Lunfe Malhas — fabricação própria, Itajaí-SC
A6: Referência | B6: 7908365100783
A7: URL | B7: lunfemalhas.com.br/camiseta-malhao-compact-atacado-algodao-bci-lunfe
A8: Categoria no site | B8: Camisetas › Masculino › Regular Fit
A9: Linha HMZT recomendada | B9: Heavy — regular 100% algodão
A10: Estoque | B10: Disponibilidade imediata; 8 cores; despacho em 24h úteis
A11: Descritor canônico (IA) | B11: Camiseta masculina regular fit heavyweight, manga curta reta até o meio do bíceps com barra dupla, gola careca de ribana 2/1 firme e rente, malha 100% algodão de 280 g/m² densa e fosca com trama compacta levemente granulada, caimento estruturado que se sustenta sem colar, barra reta no quadril. Peça lisa, sem logos. Fundo cinza claro de estúdio.
A13: 2. Especificação técnica
A14: Item | B14: Valor | C14: Fonte
A15: Composição | B15: 100% algodão BCI
A16: Fio | B16: 26/1 penteado 'compact' (texto chama de 'fio fino' — é mais grosso que 30/1)
A17: Gramatura | B17: 280 g/m²
A18: Modelagem | B18: Regular fit unissex (tabela masculina)
A19: Gola | B19: Ribana 2/1
A20: Costuras | B20: Reforçadas, ponto conjugado
A21: Tratamentos | B21: Pré-encolhida
A22: BCI | B22: Declarado; sem comprovante; BCI não garante rastreabilidade física
A23: OEKO-TEX | B23: Declarado; sem nº de certificado
A24: Sustentável | B24: 'Premium sustentável', 'consciência ambiental'
A25: Produção | B25: Fabricação própria — Itajaí, SC
A27: 3. Tabela de medidas (cm)
A28: Tamanho | B28: Comprimento | C28: Largura | D28: Ombros | E28: Mangas
A29: P | B29: 70 | C29: 52 | D29: 44 | E29: 16
A30: M | B30: 72 | C30: 54 | D30: 46 | E30: 18
A31: G | B31: 74 | C31: 56 | D31: 48 | E31: 20
A32: GG | B32: 76 | C32: 58 | D32: 50 | E32: 22
A33: EG | B33: 78 | C33: 60 | D33: 52 | E33: 24
A34: Molde regular único Lunfe, em cm, variação 1–2 cm. Modelo 1,84 m / 84 kg veste M. ⚠️ Vendido como unissex com a tabela masculina — pedir grade feminina/PP.
A35: Modelo das fotos: 1,84 m · 84 kg · veste M
A37: 4. Cores disponíveis
A38: Cor | B38: Código HMZT | C38: Ref. fornecedor | D38: Observação
A39: Grafite | B39: GRF | C39: — | D39: Seletor 'Grafitte'; cinza escuro arroxeado nas fotos
A40: Off White | B40: OFF | C40: —
A41: Terracota | B41: TER | C41: — | D41: Sem foto
A42: Marrom | B42: MRR | C42: — | D42: Sem foto
A43: Caramelo | B43: CAR | C43: —
A44: Bege | B44: BGE | C44: — | D44: Sem foto
A45: Verde Militar | B45: VML | C45: —
A46: Azul Marinho | B46: MAR | C46: — | D46: Sem foto
A47: 8 cores em paleta terrosa; sem refs. de cor do fornecedor. Fotografadas: grafite, verde militar, off white, caramelo.
A49: 5. Personalização (preço sempre sob orçamento)
A50: Técnica | B50: Detalhe | C50: Mínimo
A51: Bordado | B51: Peito — malha firme não repuxa | C51: 20 pç
A52: Silk base d'água | B52: Frente/costas | C52: 20 pç
A53: DTF | B53: Full color | C53: 20 pç
A54: Etiqueta private label | B54: Interna + tag | C54: 20 pç
A56: 6. Preços do fornecedor (desconto progressivo)
A57: Preço base (R$) | B57: 42.08
A58: Faixa | B58: Peças | C58: Desconto | D58: Preço unitário | E58: Preço + Pix
A59: Faixa 1 | B59: 20–40 | C59: ='Regras Fornecedor'!$D$4 | D59: =ROUND($B$57*(1-C59),2) | E59: =ROUND(D59*(1-'Regras Fornecedor'!$B$10),2)
A60: Faixa 2 | B60: 40–80 | C60: ='Regras Fornecedor'!$D$5 | D60: =ROUND($B$57*(1-C60),2) | E60: =ROUND(D60*(1-'Regras Fornecedor'!$B$10),2)
A61: Faixa 3 | B61: 80–100 | C61: ='Regras Fornecedor'!$D$6 | D61: =ROUND($B$57*(1-C61),2) | E61: =ROUND(D61*(1-'Regras Fornecedor'!$B$10),2)
A62: Faixa 4 | B62: 100–300 | C62: ='Regras Fornecedor'!$D$7 | D62: =ROUND($B$57*(1-C62),2) | E62: =ROUND(D62*(1-'Regras Fornecedor'!$B$10),2)
A63: Faixa 5 | B63: 300–999 | C63: ='Regras Fornecedor'!$D$8 | D63: =ROUND($B$57*(1-C63),2) | E63: =ROUND(D63*(1-'Regras Fornecedor'!$B$10),2)
A65: 7. Custo HMZT e margem (lote de 20 peças, Pix)
A66: Peça (20 pç, Pix) | B66: =E59
A67: Personalização + etiqueta + tag (R$/pç) | B67: 12 | C67: Estimativa HMZT — trocar pelo orçamento real
A68: Frete rateado + embalagem (R$/pç) | B68: 5 | C68: Estimativa HMZT — trocar pelo orçamento real
A69: Custo unitário estimado | B69: =SUM(B66:B68)
A70: Preço de venda HMZT (R$) | B70: 149 | C70: Sugestão do dossiê — ajustar
A71: Impostos + gateway (% do preço) | B71: 0 | C71: A preencher (Simples + taxa Asaas)
A72: Margem bruta (R$) | B72: =B70-B69
A73: Margem bruta (%) | B73: =IF(B70=0,0,(B70-B69)/B70)
A74: Margem após impostos/gateway (%) | B74: =IF(B70=0,0,(B70*(1-B71)-B69)/B70) | C74: Ainda sem frete ao cliente e mídia
A76: 8. Contradições e erros ⚠️
A77: ⚠️ FAQ chama o fio 26/1 de 'fino'; 26/1 é mais grosso que 30/1.
A78: ⚠️ 'BCI garante rastreabilidade': Better Cotton opera por balanço de massa; uso do nome em produto exige licença.
A79: ⚠️ OEKO-TEX citado sem nº de certificado.
A80: ⚠️ Preço base R$ 42,08 nesta página × R$ 42,09 em outro texto Lunfe (mínimo R$ 29,46 nos dois).
A81: ⚠️ Seletor 'Grafitte' × texto 'Grafite'.
A82: ⚠️ 'Unissex' com a mesma tabela do regular masculino.
A83: ⚠️ Aqui 280 g é 'confortável no clima brasileiro'; na página da P02 o fornecedor diz que 280–300 g é quente e sazonal.
A84: ⚠️ 'Malhão' também nomeia a P10 (Malhão Suedine) — malhas diferentes.
A86: 9. Comunicação HMZT
A87: ✅ Pode usar | D87: 📣 / ⛔ Não usar
A88: 100% algodão, malha encorpada de 280 g/m². | D88: Premium sustentável / consciência ambiental / rastreabilidade sustentável.
A89: Estrutura que mantém a forma no corpo. | D89: O cliente percebe qualidade antes de vestir / impõe presença.
A90: Gola em ribana 2/1, costuras reforçadas, pré-encolhida. | D90: Equilíbrio raro no mercado.
A91: 8 cores em paleta terrosa. | D91: Você está vendendo posicionamento.
A92: Fabricada em Santa Catarina. | D92: Fio fino.
A93: 'Better Cotton' e 'OEKO-TEX Standard 100' só com nº de licença/certificado. | D93: Algodão sustentável certificado sem documento.
A95: 10. Pendências com o fornecedor
A96: Pendência | B96: Status | C96: Responsável | D96: Resposta
A97: Nº OEKO-TEX e comprovante Better Cotton | B97: Aberta
A98: Origem nacional do algodão por escrito | B98: Aberta
A99: Significado de 'compact' | B99: Aberta
A100: Preço R$ 42,08 × R$ 42,09; Pix e parcelamento | B100: Aberta
A101: Refs. de cor e fotos de Terracota, Marrom, Bege, Marinho | B101: Aberta
A102: Grade feminina/PP | B102: Aberta
A103: Orçamento bordado peito + etiqueta + tag | B103: Aberta
A104: Frete Itajaí → SP | B104: Aberta
A106: 11. Fluxo de prompts de lookbook (docs/shop-confeccao/prompts/P12-prompts.md)
A107: Foto | B107: Origem no print | C107: Formato | D107: Status
A108: F1 — 3/4 olhar lateral, mão na barra | B108: Origem: fotos #1 (grafite), #6 (verde militar) e #11 (caramelo) da galeria | C108: 4:5 | D108: A gerar
A109: F2 — Detalhe gola e ombro | B109: Origem: fotos #2 (grafite), #7 (verde militar), #9 e #15 (off white) e #12 (caramelo) da galeria | C109: 4:5 | D109: A gerar
A110: F3 — Detalhe barra da manga | B110: Origem: foto #3 da galeria (grafite, dedos pinçando a barra da manga) | C110: 4:5 | D110: A gerar
A111: F4 — Frontal calça preta | B111: Origem: fotos #4 (grafite) e #8 (off white) da galeria (frontal, braços soltos, calça preta) | C111: 4:5 | D111: A gerar
...

Sheet P13
A1: P13 — Camiseta Estonada Regular 175g (Outras Cores)
A3: 1. Identificação
A4: Código HMZT | B4: HMZT-P13-REG-EST175
A5: Fornecedor | B5: Lunfe Malhas — fabricação própria, Itajaí-SC
A6: Referência | B6: 7897564701282
A7: URL | B7: lunfemalhas.com.br/camiseta-estonada-atacado-algodao-penteado-lunfe-oc
A8: Categoria no site | B8: Camisetas › Masculino › Regular Fit
A9: Linha HMZT recomendada | B9: Lavada/Vintage (nova) — base regular
A10: Estoque | B10: Disponibilidade imediata na página (6 cores no seletor); widget de relacionados mostra "Esse acabou" — widget não confiável
A11: Descritor canônico (IA) | B11: Camiseta masculina regular fit, manga curta, algodão penteado 175 g estonado (stone wash): cor lavada irregular em nuvens, mais clara nas costuras, na borda da gola canelada 2/1, nas barras e nos ombros; superfície fosca e macia. Barra reta no quadril. Peça lisa, sem logos. Fundo cinza claro de estúdio.
A13: 2. Especificação técnica
A14: Item | B14: Valor | C14: Fonte
A15: Composição | B15: 100% algodão penteado
A16: Fio | B16: 30/1 penteado
A17: Gramatura | B17: 175 g/m² (texto) × 180 GSM (banner da galeria)
A18: Modelagem | B18: Regular (tabela padrão Lunfe)
A19: Acabamento | B19: Stone wash (lavagem com pedras-pomes) após a confecção + fixação pós-estonagem
A20: Gola | B20: Canelada 2/1, fecho em anel, reforço ombro a ombro
A21: Costuras | B21: Ponto cadeia; barra dupla em mangas e barra
A22: Tratamentos | B22: Pré-encolhimento, anti-torção, amaciamento
A23: Tamanhos | B23: P ao EG (5)
A24: Produção | B24: Fabricação própria Lunfe — Itajaí-SC
A25: Toque | B25: "Ultra macio, como camiseta lavada 50 vezes"
A26: Cor | B26: "Não progride nas lavagens domésticas"
A27: Modelo das fotos | B27: 1,79 m / 82 kg (texto) × 1,84 m / 84 kg (P14, mesmo modelo)
A29: 3. Tabela de medidas (cm)
A30: Tamanho | B30: Comprimento | C30: Largura | D30: Ombros | E30: Mangas
A31: P | B31: 70 | C31: 52 | D31: 44 | E31: 16
A32: M | B32: 72 | C32: 54 | D32: 46 | E32: 18
A33: G | B33: 74 | C33: 56 | D33: 48 | E33: 20
A34: GG | B34: 76 | C34: 58 | D34: 50 | E34: 22
A35: EG | B35: 78 | C35: 60 | D35: 52 | E35: 24
A36: Mesma tabela regular do P14 (± 1–2 cm). ⚠️ Esta página diz que o modelo tem 1,79 m / 82 kg; o P14 diz 1,84 m / 84 kg — é a mesma pessoa, na mesma sessão de fotos.
A37: Modelo das fotos: 1,84 m · 84 kg · veste M
A39: 4. Cores disponíveis
A40: Cor | B40: Código HMZT | C40: Ref. fornecedor | D40: Observação
A41: Verde Floresta | B41: VFL | C41: n/i | D41: Verde garrafa lavado (fotos #1–4)
A42: Índigo | B42: IND | C42: n/i | D42: Sem foto clara — talvez o tom ameixa das fotos #11–13 ⚠️
A43: Cinza | B43: CIN | C43: n/i | D43: Cinza médio lavado (fotos #5–7)
A44: Laranja Claro | B44: LRC | C44: n/i | D44: Pêssego (fotos #8–10) — parece o "Damasco" do P14
A45: Azul Celeste | B45: ACE | C45: n/i | D45: Azul claro lavado (fotos #14–15)
A46: Bordô | B46: BDO | C46: n/i | D46: Provável tom ameixa/berinjela desbotado das fotos #11–13 ⚠️
A47: ⚠️ Seletor (Verde Floresta, Índigo, Cinza, Laranja Claro, Azul Celeste, Bordô) ≠ ficha técnica do próprio texto (Preto, Marinho, Damasco, Laranja, Bege, Cinza Claro — cópia do P14). Sem referência EST-xxx para estas cores. As fotos mostram 5 tons; um deles (ameixa) pode ser Bordô ou Índigo.
A49: 5. Personalização (preço sempre sob orçamento)
A50: Técnica | B50: Detalhe | C50: Mínimo
A51: Silk | B51: Frente/costas — tipo de tinta não detalhado nesta página | C51: 20 pç
A52: DTF | B52: Full color | C52: 20 pç
A53: Bordado | B53: Peito, mangas | C53: 20 pç
A54: Etiqueta private label | B54: Interna + tag | C54: 20 pç
A56: 6. Preços do fornecedor (desconto progressivo)
A57: Preço base (R$) | B57: 37.26
A58: Faixa | B58: Peças | C58: Desconto | D58: Preço unitário | E58: Preço + Pix
A59: Faixa 1 | B59: 20–40 | C59: ='Regras Fornecedor'!$D$4 | D59: =ROUND($B$57*(1-C59),2) | E59: =ROUND(D59*(1-'Regras Fornecedor'!$B$10),2)
A60: Faixa 2 | B60: 40–80 | C60: ='Regras Fornecedor'!$D$5 | D60: =ROUND($B$57*(1-C60),2) | E60: =ROUND(D60*(1-'Regras Fornecedor'!$B$10),2)
A61: Faixa 3 | B61: 80–100 | C61: ='Regras Fornecedor'!$D$6 | D61: =ROUND($B$57*(1-C61),2) | E61: =ROUND(D61*(1-'Regras Fornecedor'!$B$10),2)
A62: Faixa 4 | B62: 100–300 | C62: ='Regras Fornecedor'!$D$7 | D62: =ROUND($B$57*(1-C62),2) | E62: =ROUND(D62*(1-'Regras Fornecedor'!$B$10),2)
A63: Faixa 5 | B63: 300–999 | C63: ='Regras Fornecedor'!$D$8 | D63: =ROUND($B$57*(1-C63),2) | E63: =ROUND(D63*(1-'Regras Fornecedor'!$B$10),2)
A65: 7. Custo HMZT e margem (lote de 20 peças, Pix)
A66: Peça (20 pç, Pix) | B66: =E59
A67: Personalização + etiqueta + tag (R$/pç) | B67: 9 | C67: Estimativa HMZT — trocar pelo orçamento real
A68: Frete rateado + embalagem (R$/pç) | B68: 4 | C68: Estimativa HMZT — trocar pelo orçamento real
A69: Custo unitário estimado | B69: =SUM(B66:B68)
A70: Preço de venda HMZT (R$) | B70: 119 | C70: Sugestão do dossiê — ajustar
A71: Impostos + gateway (% do preço) | B71: 0 | C71: A preencher (Simples + taxa Asaas)
A72: Margem bruta (R$) | B72: =B70-B69
A73: Margem bruta (%) | B73: =IF(B70=0,0,(B70-B69)/B70)
A74: Margem após impostos/gateway (%) | B74: =IF(B70=0,0,(B70*(1-B71)-B69)/B70) | C74: Ainda sem frete ao cliente e mídia
A76: 8. Contradições e erros ⚠️
A77: ⚠️ P13 × P14 são quase duplicados. Mesma composição, gramatura, preço (R$ 37,26), tabela de desconto, tabela de medidas e sessão de fotos. Muda só o EAN (7897564701282 × 7892948548590), o título ("Vintage") e a cartela. O "-oc" do endereço provavelmente é "outras cores" (hipótese).
A78: ⚠️ Cores: o seletor mostra Verde Floresta, Índigo, Cinza, Laranja Claro, Azul Celeste e Bordô. A ficha técnica do próprio texto lista Preto, Marinho, Damasco, Laranja, Bege e Cinza Claro — cópia do P14.
A79: ⚠️ Modelo: esta página diz 1,79 m / 82 kg; o P14 diz 1,84 m / 84 kg. É a mesma pessoa nas fotos.
A80: ⚠️ Cores × fotos: as fotos mostram 5 tons. Um tom ameixa/berinjela pode ser o Bordô ou o Índigo — não dá para saber.
A81: ⚠️ Laranja Claro (P13) × Damasco (P14): nas fotos parecem a mesma cor, com nomes diferentes.
A82: ⚠️ Amaciamento: aqui diz "amaciamento industrial"; no P14, "amaciamento mecânico pelas pedras" e "nenhum amaciamento químico reproduz".
A83: ⚠️ Desbotamento: aqui, "sem desbotamento excessivo" (admite algum); no P14, "não progride nas lavagens".
A84: ⚠️ Gramatura: texto 175 g/m²; banners da família (P15–P17) dizem "malha beneficiada 180GSM". Pode ser antes × depois da lavagem.
A85: ⚠️ Widget "Produtos relacionados": mostra "Esse acabou" até para produtos com "Disponibilidade imediata" na própria página. Não serve para checar estoque.
A87: 9. Comunicação HMZT
A88: ✅ Pode usar | D88: 📣 / ⛔ Não usar
A89: "100% algodão penteado, fio 30/1" | D89: "Ticket médio 25–40% acima do básico liso" / "+35% vs liso"
A90: "Lavada com pedras depois de costurada: cada peça tem tom e desgaste levemente diferentes" (é o processo físico — dizer como característica, não como "defeito" nem "exclusividade") | D90: "Exclusividade real que justifica preço premium" / "a peça se diferencia sozinha"
A91: "Gola canelada 2/1, costura ponto cadeia, reforço ombro a ombro, barra dupla" | D91: "Consistência que estonagens terceirizadas não alcançam"
A92: "Pré-encolhida e com tratamento anti-torção" | D92: "Toque de camiseta lavada 50 vezes" / "nenhum amaciamento químico reproduz"
A93: "Fabricada em Santa Catarina" | D93: "Não desbota" / "visual vintage permanente" (banner diz "Não desbota" numa peça que é desbotada de propósito)
D94: "Sustenta recompra", "converte", "avaliação positiva desde a primeira vestida"
D95: Selos genéricos da galeria ("100% Original")
A97: 10. Pendências com o fornecedor
A98: Pendência | B98: Status | C98: Responsável | D98: Resposta
A99: Confirmar se P13 = P14 (mesma malha/lote) e cartela real do P13 | B99: Aberta
A100: Identificar a cor ameixa das fotos #11–13 | B100: Aberta
A101: Confirmar gramatura (175 g/m² × 180 GSM dos banners) | B101: Aberta
A102: Orçamento de personalização (bordado pequeno, DTF, etiqueta, tag) e frete Itajaí → SP | B102: Aberta
A103: Origem do algodão (não citada nesta página) | B103: Aberta
A104: Tolerância de variação de tom entre lotes | B104: Aberta
A106: 11. Fluxo de prompts de lookbook (docs/shop-confeccao/prompts/P13-prompts.md)
A107: Foto | B107: Origem no print | C107: Formato | D107: Status
A108: F1 — Hero olhar lateral | B108: Origem: fotos #1 (verde) e #14 (azul celeste) — quase frontal, olhar para o lado | C108: 4:5 | D108: A gerar
A109: F2 — Ajustando a manga | B109: Origem: fotos #2 (verde) e #15 (azul celeste) — 3/4 ajeitando a manga | C109: 4:5 | D109: A gerar
A110: F3 — Detalhe mão na manga | B110: Origem: foto #3 (verde) — detalhe gola, ombro e manga | C110: 4:5 | D110: A gerar
A111: F4 — Costas com rosto de perfil | B111: Origem: fotos #4 (verde) e #10 (laranja claro) | C111: 4:5 | D111: A gerar
...

Sheet P14
A1: P14 — Camiseta Estonada Regular 175g
A3: 1. Identificação
A4: Código HMZT | B4: HMZT-P14-REG-EST175
A5: Fornecedor | B5: Lunfe Malhas — fabricação própria, Itajaí-SC
A6: Referência | B6: 7892948548590
A7: URL | B7: lunfemalhas.com.br/camiseta-estonada-atacado-algodao-penteado-30-1-lunfe
A8: Categoria no site | B8: Camisetas › Masculino › Regular Fit
A9: Linha HMZT recomendada | B9: Lavada/Vintage (nova) — base regular
A10: Estoque | B10: Disponibilidade imediata na página (6 cores); o widget de relacionados das outras páginas mostra "Esse acabou" — widget não confiável
A11: Descritor canônico (IA) | B11: Camiseta masculina regular fit, manga curta, algodão penteado 175 g estonado (stone wash): cor lavada irregular em nuvens, mais clara nas costuras, na borda da gola canelada 2/1, nas barras e nos ombros; superfície fosca e macia. Barra reta no quadril. Peça lisa, sem logos. Fundo cinza claro de estúdio.
A13: 2. Especificação técnica
A14: Item | B14: Valor | C14: Fonte
A15: Composição | B15: 100% algodão penteado
A16: Fio | B16: 30/1 penteado
A17: Gramatura | B17: 175 g/m² (texto) × 180 GSM (banner da galeria)
A18: Modelagem | B18: Regular (tabela padrão Lunfe)
A19: Acabamento | B19: Stone wash (lavagem com pedras-pomes) após a confecção + fixação pós-estonagem
A20: Gola | B20: Canelada 2/1, fecho em anel, reforço ombro a ombro
A21: Costuras | B21: Ponto cadeia; barra dupla em mangas e barra
A22: Tratamentos | B22: Pré-encolhimento, anti-torção, amaciamento
A23: Tamanhos | B23: P ao EG (5)
A24: Produção | B24: Fabricação própria Lunfe — Itajaí-SC
A25: Toque | B25: "Ultra macio, como camiseta lavada 50 vezes"
A26: Cor | B26: "Não progride nas lavagens domésticas"
A28: 3. Tabela de medidas (cm)
A29: Tamanho | B29: Comprimento | C29: Largura | D29: Ombros | E29: Mangas
A30: P | B30: 70 | C30: 52 | D30: 44 | E30: 16
A31: M | B31: 72 | C31: 54 | D31: 46 | E31: 18
A32: G | B32: 74 | C32: 56 | D32: 48 | E32: 20
A33: GG | B33: 76 | C33: 58 | D33: 50 | E33: 22
A34: EG | B34: 78 | C34: 60 | D34: 52 | E34: 24
A35: Tabela regular padrão Lunfe (± 2 cm, + até 1 cm pela estonagem). Modelo 1,84 m / 84 kg veste M.
A36: Modelo das fotos: 1,84 m · 84 kg · veste M
A38: 4. Cores disponíveis
A39: Cor | B39: Código HMZT | C39: Ref. fornecedor | D39: Observação
A40: Preto estonado | B40: PRT | C40: EST-PRT | D40: Desgaste sutil — vira grafite lavado (foto #1)
A41: Marinho estonado | B41: MAR | C41: EST-MRN | D41: Desgaste médio (fotos #11–14)
A42: Damasco estonado | B42: DMS | C42: EST-DMS | D42: Pêssego claro (foto #15) — parece igual ao "Laranja Claro" do P13
A43: Laranja estonado | B43: LRJ | C43: EST-LRJ | D43: Coral forte nas fotos #4–7
A44: Bege estonado | B44: BGE | C44: EST-BGE | D44: Areia clara (fotos #8–10)
A45: Cinza Claro estonado | B45: CZC | C45: EST-CZC | D45: Sem foto na galeria
A46: Seletor da página = lista do texto (6 cores). Única página da família com referência de cor do fornecedor (EST-xxx). Cinza Claro não aparece nas fotos.
A48: 5. Personalização (preço sempre sob orçamento)
A49: Técnica | B49: Detalhe | C49: Mínimo
A50: Silk base d'água | B50: Toque zero; combina com o visual lavado | C50: 20 pç
A51: Silk plastisol | B51: Cobertura total | C51: 20 pç
A52: Gel alto relevo / Puff 3D / Foil | B52: Efeitos sobre a base lavada — testar | C52: 20 pç
A53: DTF | B53: Full color | C53: 20 pç
A54: Bordado | B54: Peito, mangas | C54: 20 pç
A55: Etiqueta private label | B55: Interna costurada + tag externa | C55: 20 pç
A56: Embalagem customizada | B56: Saco, caixa, tag | C56: 50 pç
A57: Cor Pantone + stone wash | B57: Exige aprovação de amostra; 20–30 dias úteis | C57: 100 pç/cor
A59: 6. Preços do fornecedor (desconto progressivo)
A60: Preço base (R$) | B60: 37.26
A61: Faixa | B61: Peças | C61: Desconto | D61: Preço unitário | E61: Preço + Pix
A62: Faixa 1 | B62: 20–40 | C62: ='Regras Fornecedor'!$D$4 | D62: =ROUND($B$60*(1-C62),2) | E62: =ROUND(D62*(1-'Regras Fornecedor'!$B$10),2)
A63: Faixa 2 | B63: 40–80 | C63: ='Regras Fornecedor'!$D$5 | D63: =ROUND($B$60*(1-C63),2) | E63: =ROUND(D63*(1-'Regras Fornecedor'!$B$10),2)
A64: Faixa 3 | B64: 80–100 | C64: ='Regras Fornecedor'!$D$6 | D64: =ROUND($B$60*(1-C64),2) | E64: =ROUND(D64*(1-'Regras Fornecedor'!$B$10),2)
A65: Faixa 4 | B65: 100–300 | C65: ='Regras Fornecedor'!$D$7 | D65: =ROUND($B$60*(1-C65),2) | E65: =ROUND(D65*(1-'Regras Fornecedor'!$B$10),2)
A66: Faixa 5 | B66: 300–999 | C66: ='Regras Fornecedor'!$D$8 | D66: =ROUND($B$60*(1-C66),2) | E66: =ROUND(D66*(1-'Regras Fornecedor'!$B$10),2)
A68: 7. Custo HMZT e margem (lote de 20 peças, Pix)
A69: Peça (20 pç, Pix) | B69: =E62
A70: Personalização + etiqueta + tag (R$/pç) | B70: 9 | C70: Estimativa HMZT — trocar pelo orçamento real
A71: Frete rateado + embalagem (R$/pç) | B71: 4 | C71: Estimativa HMZT — trocar pelo orçamento real
A72: Custo unitário estimado | B72: =SUM(B69:B71)
A73: Preço de venda HMZT (R$) | B73: 119 | C73: Sugestão do dossiê — ajustar
A74: Impostos + gateway (% do preço) | B74: 0 | C74: A preencher (Simples + taxa Asaas)
A75: Margem bruta (R$) | B75: =B73-B72
A76: Margem bruta (%) | B76: =IF(B73=0,0,(B73-B72)/B73)
A77: Margem após impostos/gateway (%) | B77: =IF(B73=0,0,(B73*(1-B74)-B72)/B73) | C77: Ainda sem frete ao cliente e mídia
A79: 8. Contradições e erros ⚠️
A80: ⚠️ P14 × P13: o P13 é a mesma peça (mesma ficha, preço, medidas e fotos) com outro EAN e outra cartela — o texto do P13 até copia as cores do P14.
A81: ⚠️ "Processo artesanal" × "industrial calibrado": o mesmo texto chama a estonagem das duas coisas.
A82: ⚠️ Estonagem interna × lavanderia: aqui "sem lavanderia terceirizada"; no P17, "estonagem em lavanderia industrial". Pode ser lavanderia própria — confirmar.
A83: ⚠️ Gramatura: 175 g/m² no texto × "180GSM" nos banners da família. Provavelmente antes × depois da lavagem.
A84: ⚠️ Cor "permanente": aqui "não progride nas lavagens"; P13/P15 dizem "sem desbotamento excessivo" e recomendam lavar do avesso em água fria para prolongar a cor. Algum desbote vai acontecer.
A85: ⚠️ Prazo Pantone: aqui 20–30 dias úteis; regra geral Lunfe (outros dossiês) 15–25. Faz sentido (tem amostra de lavagem), mas confirmar.
A86: ⚠️ Personalização: oferece plastisol, gel, puff e foil sobre a base lavada. Funciona se aplicado depois da lavagem (peça pronta). Se a estampa for aplicada antes da estonagem, as pedras destroem foil, puff e plastisol ⚠️. Foil sobre superfície desgastada precisa de teste de aderência.
A87: ⚠️ Bordado em 175 g: malha leve franze com bordado grande. Manter logo pequeno (≤ 8–9 cm) com entretela.
A88: ⚠️ Comparativo do próprio texto: coloca a Chinese Cotton 160g (P06) como "premium versátil" — base com algodão de origem sensível; a HMZT não usa essa comparação.
A89: ⚠️ Widget "Produtos relacionados": mostra este produto como "Esse acabou" em outras páginas, mas a própria página diz "Disponibilidade: Imediata".
A91: 9. Comunicação HMZT
A92: ✅ Pode usar | D92: 📣 / ⛔ Não usar
A93: "100% algodão penteado, fio 30/1" | D93: "Ticket médio 25–40% acima do básico liso" / "+35% vs liso"
A94: "Lavada com pedras depois de costurada: cada peça tem tom e desgaste levemente diferentes" (é o processo físico — dizer como característica, não como "defeito" nem "exclusividade") | D94: "Exclusividade real que justifica preço premium" / "a peça se diferencia sozinha"
A95: "Gola canelada 2/1, costura ponto cadeia, reforço ombro a ombro, barra dupla" | D95: "Consistência que estonagens terceirizadas não alcançam"
A96: "Pré-encolhida e com tratamento anti-torção" | D96: "Toque de camiseta lavada 50 vezes" / "nenhum amaciamento químico reproduz"
A97: "Fabricada em Santa Catarina" | D97: "Não desbota" / "visual vintage permanente" (banner diz "Não desbota" numa peça que é desbotada de propósito)
D98: "Sustenta recompra", "converte", "avaliação positiva desde a primeira vestida"
D99: Selos genéricos da galeria ("100% Original")
D100: "A fábrica está produzindo agora — vai ser para a sua marca ou para o concorrente?"
A102: 10. Pendências com o fornecedor
A103: Pendência | B103: Status | C103: Responsável | D103: Resposta
A104: Estonagem própria × lavanderia terceirizada | B104: Aberta
A105: Confirmar gramatura (175 g/m² × 180 GSM dos banners) | B105: Aberta
A106: Orçamento de personalização (bordado pequeno, DTF, etiqueta, tag) e frete Itajaí → SP | B106: Aberta
A107: Origem do algodão (não citada nesta página) | B107: Aberta
A108: Tolerância de variação de tom entre lotes | B108: Aberta
A110: 11. Fluxo de prompts de lookbook (docs/shop-confeccao/prompts/P14-prompts.md)
A111: Foto | B111: Origem no print | C111: Formato | D111: Status
...

Sheet P15
A1: P15 — Camiseta Estonada Neon Regular 175g
A3: 1. Identificação
A4: Código HMZT | B4: HMZT-P15-REG-ESN175
A5: Fornecedor | B5: Lunfe Malhas — fabricação própria, Itajaí-SC
A6: Referência | B6: código interno ESTON#NEON/24
A7: URL | B7: lunfemalhas.com.br/camiseta-estonada-neon-atacado-algodao-penteado-lunfe
A8: Categoria no site | B8: Camisetas › Masculino › Regular Fit
A9: Linha HMZT recomendada | B9: Lavada/Vintage — cápsula de verão (drop)
A10: Estoque | B10: Disponibilidade imediata (6 cores neon)
A11: Descritor canônico (IA) | B11: Camiseta masculina regular fit, manga curta, algodão penteado 175 g em cor neon fluorescente, fosca, com lavagem leve e irregular (levemente mesclada, mais clara nas costuras e na borda da gola canelada 2/1). Barra reta no quadril. Peça lisa, sem logos. Fundo cinza claro de estúdio.
A13: 2. Especificação técnica
A14: Item | B14: Valor | C14: Fonte
A15: Composição | B15: 100% algodão penteado
A16: Fio | B16: 30/1 penteado
A17: Gramatura | B17: 175 g/m² (texto) × 180 GSM (banner da galeria)
A18: Modelagem | B18: Regular (tabela padrão Lunfe)
A19: Cores | B19: 6 neon — solidez à luz não informada
A20: Acabamento | B20: Stone wash (lavagem com pedras-pomes) após a confecção + fixação pós-estonagem
A21: Gola | B21: Canelada 2/1, fecho em anel, reforço ombro a ombro
A22: Costuras | B22: Ponto cadeia; barra dupla em mangas e barra
A23: Tratamentos | B23: Pré-encolhimento, anti-torção, amaciamento
A24: Tamanhos | B24: P ao EG (5)
A25: Produção | B25: Fabricação própria Lunfe — Itajaí-SC
A26: Toque | B26: "Ultra macio, como camiseta lavada 50 vezes"
A27: Cor | B27: "Não progride nas lavagens domésticas"
A29: 3. Tabela de medidas (cm)
A30: Tamanho | B30: Comprimento | C30: Largura | D30: Ombros | E30: Mangas
A31: P | B31: 70 | C31: 52 | D31: 44 | E31: 16
A32: M | B32: 72 | C32: 54 | D32: 46 | E32: 18
A33: G | B33: 74 | C33: 56 | D33: 48 | E33: 20
A34: GG | B34: 76 | C34: 58 | D34: 50 | E34: 22
A35: EG | B35: 78 | C35: 60 | D35: 52 | E35: 24
A36: Mesma tabela regular do P14 (± 1–2 cm). ⚠️ Texto diz modelo 1,79 m / 82 kg — é o mesmo modelo das fotos do P13/P14 (que o P14 diz ter 1,84 m / 84 kg).
A37: Modelo das fotos: 1,84 m · 84 kg · veste M
A39: 4. Cores disponíveis
A40: Cor | B40: Código HMZT | C40: Ref. fornecedor | D40: Observação
A41: Verde Neon | B41: VNN | C41: n/i | D41: Fotos #6–8
A42: Laranja Neon | B42: LRN | C42: n/i | D42: Fotos #1, #2, #5
A43: Amarelo Neon | B43: AMN | C43: n/i | D43: Amarelo-limão (fotos #14–16)
A44: Azul Neon | B44: AZN | C44: n/i | D44: Azul-turquesa (fotos #18–21)
A45: Rosa Neon | B45: RSN | C45: n/i | D45: Rosa-salmão (foto #17)
A46: Roxo Neon | B46: RXN | C46: n/i | D46: Magenta-violeta (fotos #9, #11, #12)
A47: Seletor = texto (6 cores). ⚠️ O banner #13 ("Camisetas Estonadas") mostra uma pilha em tons pastel (lilás, rosa, lima, azul, pêssego, menta, rosa claro) — não são as 6 neon.
A49: 5. Personalização (preço sempre sob orçamento)
A50: Técnica | B50: Detalhe | C50: Mínimo
A51: Silk | B51: Frente/costas — tipo de tinta não detalhado nesta página | C51: 20 pç
A52: DTF | B52: Full color | C52: 20 pç
A53: Bordado | B53: Peito, mangas | C53: 20 pç
A54: Etiqueta private label | B54: Interna + tag | C54: 20 pç
A56: 6. Preços do fornecedor (desconto progressivo)
A57: Preço base (R$) | B57: 37.26
A58: Faixa | B58: Peças | C58: Desconto | D58: Preço unitário | E58: Preço + Pix
A59: Faixa 1 | B59: 20–40 | C59: ='Regras Fornecedor'!$D$4 | D59: =ROUND($B$57*(1-C59),2) | E59: =ROUND(D59*(1-'Regras Fornecedor'!$B$10),2)
A60: Faixa 2 | B60: 40–80 | C60: ='Regras Fornecedor'!$D$5 | D60: =ROUND($B$57*(1-C60),2) | E60: =ROUND(D60*(1-'Regras Fornecedor'!$B$10),2)
A61: Faixa 3 | B61: 80–100 | C61: ='Regras Fornecedor'!$D$6 | D61: =ROUND($B$57*(1-C61),2) | E61: =ROUND(D61*(1-'Regras Fornecedor'!$B$10),2)
A62: Faixa 4 | B62: 100–300 | C62: ='Regras Fornecedor'!$D$7 | D62: =ROUND($B$57*(1-C62),2) | E62: =ROUND(D62*(1-'Regras Fornecedor'!$B$10),2)
A63: Faixa 5 | B63: 300–999 | C63: ='Regras Fornecedor'!$D$8 | D63: =ROUND($B$57*(1-C63),2) | E63: =ROUND(D63*(1-'Regras Fornecedor'!$B$10),2)
A65: 7. Custo HMZT e margem (lote de 20 peças, Pix)
A66: Peça (20 pç, Pix) | B66: =E59
A67: Personalização + etiqueta + tag (R$/pç) | B67: 9 | C67: Estimativa HMZT — trocar pelo orçamento real
A68: Frete rateado + embalagem (R$/pç) | B68: 4 | C68: Estimativa HMZT — trocar pelo orçamento real
A69: Custo unitário estimado | B69: =SUM(B66:B68)
A70: Preço de venda HMZT (R$) | B70: 109 | C70: Sugestão do dossiê — ajustar
A71: Impostos + gateway (% do preço) | B71: 0 | C71: A preencher (Simples + taxa Asaas)
A72: Margem bruta (R$) | B72: =B70-B69
A73: Margem bruta (%) | B73: =IF(B70=0,0,(B70-B69)/B70)
A74: Margem após impostos/gateway (%) | B74: =IF(B70=0,0,(B70*(1-B71)-B69)/B70) | C74: Ainda sem frete ao cliente e mídia
A76: 8. Contradições e erros ⚠️
A77: ⚠️ Neon + algodão: corante fluorescente em algodão tem solidez à luz baixa — desbota com sol e lavagem mais rápido que cor comum. O próprio FAQ recomenda "lavar do avesso em água fria para prolongar a intensidade", o que contradiz "vibração estável".
A78: ⚠️ Efeito estonado quase invisível: nas fotos o neon parece liso/mesclado; o desgaste nas costuras quase não aparece. O argumento "visual vintage" fica fraco nestas cores.
A79: ⚠️ Banner #13 ("Camisetas Estonadas"): mostra pilha de camisetas em tons pastel (lilás, rosa, lima, azul, pêssego, menta, rosa claro), não as 6 neon.
A80: ⚠️ Banner #10: "Malha beneficiada 180GSM" × 175 g/m² no texto; "Não desbota" numa peça estonada.
A81: ⚠️ Modelo: texto diz 1,79 m / 82 kg; é o mesmo modelo das fotos do P14 (1,84 m / 84 kg).
A82: ⚠️ Referência: "ESTON#NEON/24" é código interno, não EAN.
A83: ⚠️ "Estonada clássica": o FAQ diz que a clássica tem preto, marinho, bege e cinza — ignora a cartela do P13 (verde, índigo, azul celeste…).
A85: 9. Comunicação HMZT
A86: ✅ Pode usar | D86: 📣 / ⛔ Não usar
A87: "100% algodão penteado, fio 30/1" | D87: "Ticket médio 25–40% acima do básico liso" / "+35% vs liso"
A88: "Lavada com pedras depois de costurada: cada peça tem tom e desgaste levemente diferentes" (é o processo físico — dizer como característica, não como "defeito" nem "exclusividade") | D88: "Exclusividade real que justifica preço premium" / "a peça se diferencia sozinha"
A89: "Gola canelada 2/1, costura ponto cadeia, reforço ombro a ombro, barra dupla" | D89: "Consistência que estonagens terceirizadas não alcançam"
A90: "Pré-encolhida e com tratamento anti-torção" | D90: "Toque de camiseta lavada 50 vezes" / "nenhum amaciamento químico reproduz"
A91: "Fabricada em Santa Catarina" | D91: "Não desbota" / "visual vintage permanente" (banner diz "Não desbota" numa peça que é desbotada de propósito)
A92: "Cores neon" — sem prometer que não desbota | D92: "Sustenta recompra", "converte", "avaliação positiva desde a primeira vestida"
D93: Selos genéricos da galeria ("100% Original")
D94: "Vibração neon estável lavagem após lavagem"
D95: "Gera mídia espontânea", "desejo instantâneo"
A97: 10. Pendências com o fornecedor
A98: Pendência | B98: Status | C98: Responsável | D98: Resposta
A99: Solidez à luz/lavagem do neon | B99: Aberta
A100: Existência das cores pastel do banner #13 | B100: Aberta
A101: Confirmar gramatura (175 g/m² × 180 GSM dos banners) | B101: Aberta
A102: Orçamento de personalização (bordado pequeno, DTF, etiqueta, tag) e frete Itajaí → SP | B102: Aberta
A103: Origem do algodão (não citada nesta página) | B103: Aberta
A104: Tolerância de variação de tom entre lotes | B104: Aberta
A106: 11. Fluxo de prompts de lookbook (docs/shop-confeccao/prompts/P15-prompts.md)
A107: Foto | B107: Origem no print | C107: Formato | D107: Status
A108: F1 — Frontal olhando a câmera | B108: Origem: foto #21 (azul neon) | C108: 4:5 | D108: A gerar
A109: F2 — 3/4 mão no bolso | B109: Origem: fotos #1 (laranja neon) e #16 (amarelo neon) | C109: 4:5 | D109: A gerar
A110: F3 — Frontal olhar lateral | B110: Origem: fotos #5 (laranja neon), #18 e #19 (azul neon) | C110: 4:5 | D110: A gerar
A111: F4 — Mãos juntas à frente | B111: Origem: fotos #6 (verde neon), #14 (amarelo neon) e #20 (azul neon) | C111: 4:5 | D111: A gerar
...

Sheet P16
A1: P16 — Camiseta Estonada Oversized 175g
A3: 1. Identificação
A4: Código HMZT | B4: HMZT-P16-OVS-EST175
A5: Fornecedor | B5: Lunfe Malhas — fabricação própria, Itajaí-SC
A6: Referência | B6: código interno 30/1OVR/LF
A7: URL | B7: lunfemalhas.com.br/camiseta-estonada-oversized-atacado-algodao-penteado-lunfe
A8: Categoria no site | B8: Camisetas › Masculino › Oversized
A9: Linha HMZT recomendada | B9: Lavada/Vintage (nova) — base oversized
A10: Estoque | B10: Disponibilidade imediata (15 cores); widget de relacionados mostra "Esse acabou" — não confiável
A11: Descritor canônico (IA) | B11: Camiseta masculina oversized, ombro caído, corpo amplo e alongado abaixo do quadril, mangas largas até acima do cotovelo, algodão penteado 175 g estonado: cor lavada irregular, mais clara nas costuras, gola canelada e barras; caimento mole com dobras verticais. Peça lisa, sem logos. Fundo cinza claro de estúdio.
A13: 2. Especificação técnica
A14: Item | B14: Valor | C14: Fonte
A15: Composição | B15: 100% algodão penteado
A16: Fio | B16: 30/1 penteado
A17: Gramatura | B17: 175 g/m² (texto) × 180 GSM (banner da galeria)
A18: Modelagem | B18: Oversized (ombro caído, corpo amplo e alongado)
A19: Acabamento | B19: Stone wash (lavagem com pedras-pomes) após a confecção + fixação pós-estonagem
A20: Gola | B20: Canelada 2/1, fecho em anel, reforço ombro a ombro
A21: Costuras | B21: Ponto cadeia; barra dupla em mangas e barra
A22: Tratamentos | B22: Pré-encolhimento, anti-torção, amaciamento
A23: Tamanhos | B23: P ao EG (5)
A24: Produção | B24: Fabricação própria Lunfe — Itajaí-SC
A25: Toque | B25: "Ultra macio, como camiseta lavada 50 vezes"
A26: Cor | B26: "Não progride nas lavagens domésticas"
A28: 3. Tabela de medidas (cm)
A29: Tamanho | B29: Comprimento | C29: Largura | D29: Ombros | E29: Mangas
A30: P | B30: 73 | C30: 57 | D30: 52 | E30: 24
A31: M | B31: 75 | C31: 59 | D31: 54 | E31: 25
A32: G | B32: 77 | C32: 61 | D32: 56 | E32: 26
A33: GG | B33: 79 | C33: 63 | D33: 58 | E33: 27
A34: EG | B34: 81 | C34: 65 | D34: 60 | E34: 28
A35: Tabela oversized própria (± 1–2 cm). Modelo 1,84 m / 84 kg veste M. ⚠️ Mangas crescem 1 cm por tamanho aqui e 2 cm no P17, embora o texto diga que a modelagem é a mesma.
A36: Modelo das fotos: 1,84 m · 84 kg · veste M
A38: 4. Cores disponíveis
A39: Cor | B39: Código HMZT | C39: Ref. fornecedor | D39: Observação
A40: Verde Musgo | B40: VMG | C40: n/i | D40: Foto #13
A41: Chumbo | B41: CHU | C41: n/i | D41: Marrom-grafite (foto #14)
A42: Azul Jeans | B42: AJN | C42: n/i | D42: Azul acinzentado (foto #17)
A43: Cereja | B43: CRJ | C43: n/i | D43: Vermelho-framboesa (foto #16)
A44: Castanho | B44: CST | C44: n/i | D44: Caramelo (foto #6)
A45: Verde Neon | B45: VNN | C45: n/i | D45: Fotos #21–22
A46: Rosa Neon | B46: RSN | C46: n/i | D46: Fotos #9, #11, #12
A47: Rosa Claro | B47: RSC | C47: n/i | D47: Fotos #25–27
A48: Cereja Escuro | B48: CRE | C48: n/i | D48: Vinho desbotado (fotos #8, #19)
A49: Off White | B49: OFF | C49: n/i | D49: Foto #10 — quase sem efeito lavado
A50: Laranja Neon | B50: LRN | C50: n/i | D50: Fotos #15, #18, #20
... A54: Preto | B54: PRT | C54: n/i | D54: Sem foto (só no mockup #3, sem lavagem)
A55: Seletor = texto (15 cores). Só "Verde Musgo" vem com o prefixo "Estonada -" no seletor. Preto e Azul Marinho não têm foto.
A57: 5. Personalização (preço sempre sob orçamento)
A58: Técnica | B58: Detalhe | C58: Mínimo
A59: Silk | B59: Frente/costas — tipo de tinta não detalhado nesta página | C59: 20 pç
A60: DTF | B60: Full color | C60: 20 pç
A61: Bordado | B61: Peito, mangas | C61: 20 pç
A62: Etiqueta private label | B62: Interna + tag | C62: 20 pç
A64: 6. Preços do fornecedor (desconto progressivo)
A65: Preço base (R$) | B65: 39.78
A66: Faixa | B66: Peças | C66: Desconto | D66: Preço unitário | E66: Preço + Pix
A67: Faixa 1 | B67: 20–40 | C67: ='Regras Fornecedor'!$D$4 | D67: =ROUND($B$65*(1-C67),2) | E67: =ROUND(D67*(1-'Regras Fornecedor'!$B$10),2)
A68: Faixa 2 | B68: 40–80 | C68: ='Regras Fornecedor'!$D$5 | D68: =ROUND($B$65*(1-C68),2) | E68: =ROUND(D68*(1-'Regras Fornecedor'!$B$10),2)
A69: Faixa 3 | B69: 80–100 | C69: ='Regras Fornecedor'!$D$6 | D69: =ROUND($B$65*(1-C69),2) | E69: =ROUND(D69*(1-'Regras Fornecedor'!$B$10),2)
A70: Faixa 4 | B70: 100–300 | C70: ='Regras Fornecedor'!$D$7 | D70: =ROUND($B$65*(1-C70),2) | E70: =ROUND(D70*(1-'Regras Fornecedor'!$B$10),2)
A71: Faixa 5 | B71: 300–999 | C71: ='Regras Fornecedor'!$D$8 | D71: =ROUND($B$65*(1-C71),2) | E71: =ROUND(D71*(1-'Regras Fornecedor'!$B$10),2)
A73: 7. Custo HMZT e margem (lote de 20 peças, Pix)
A74: Peça (20 pç, Pix) | B74: =E67
A75: Personalização + etiqueta + tag (R$/pç) | B75: 10 | C75: Estimativa HMZT — trocar pelo orçamento real
A76: Frete rateado + embalagem (R$/pç) | B76: 4 | C76: Estimativa HMZT — trocar pelo orçamento real
A77: Custo unitário estimado | B77: =SUM(B74:B76)
A78: Preço de venda HMZT (R$) | B78: 139 | C78: Sugestão do dossiê — ajustar
A79: Impostos + gateway (% do preço) | B79: 0 | C79: A preencher (Simples + taxa Asaas)
A80: Margem bruta (R$) | B80: =B78-B77
A81: Margem bruta (%) | B81: =IF(B78=0,0,(B78-B77)/B78)
A82: Margem após impostos/gateway (%) | B82: =IF(B78=0,0,(B78*(1-B79)-B77)/B78) | C82: Ainda sem frete ao cliente e mídia
A84: 8. Contradições e erros ⚠️
A85: ⚠️ Mangas × P17: o texto do P17 diz que a modelagem é idêntica, mas as mangas diferem (P16: 24–28 cm, +1 por tamanho; P17: 22–30 cm, +2 por tamanho).
A86: ⚠️ Gramatura: 175 g/m² no texto × "180GSM" no banner #23.
A87: ⚠️ Banners que não são deste produto: #3 (mockup em camiseta preta sem lavagem), #23 (camiseta branca sem lavagem, outro modelo, "Não desbota"). Iguais aos do P17.
A88: ⚠️ Preto e Azul Marinho estão na cartela mas não têm foto do produto real.
A89: ⚠️ "Estonada Regular tem corte justo ao corpo" (FAQ) — a tabela regular (M 54 cm de largura) é regular, não justa.
A90: ⚠️ Neon oversized: mesmo risco do P15 — cor fluorescente em algodão desbota com sol/lavagem.
A91: ⚠️ "Naturalmente unissex, reduz trocas por tamanho" 📣 — sem dado; a tabela é masculina.
A92: ⚠️ Relacionados: aparece um "Camiseta Oversized Estonada Lunfe" a R$ 90,00 e um "…pret" — cadastros antigos ou errados no site.
A93: ⚠️ Off white (foto #10) quase não mostra efeito lavado — é a cor com menos "vintage".
A95: 9. Comunicação HMZT
A96: ✅ Pode usar | D96: 📣 / ⛔ Não usar
A97: "100% algodão penteado, fio 30/1" | D97: "Ticket médio 25–40% acima do básico liso" / "+35% vs liso"
A98: "Lavada com pedras depois de costurada: cada peça tem tom e desgaste levemente diferentes" (é o processo físico — dizer como característica, não como "defeito" nem "exclusividade") | D98: "Exclusividade real que justifica preço premium" / "a peça se diferencia sozinha"
A99: "Gola canelada 2/1, costura ponto cadeia, reforço ombro a ombro, barra dupla" | D99: "Consistência que estonagens terceirizadas não alcançam"
A100: "Pré-encolhida e com tratamento anti-torção" | D100: "Toque de camiseta lavada 50 vezes" / "nenhum amaciamento químico reproduz"
A101: "Fabricada em Santa Catarina" | D101: "Não desbota" / "visual vintage permanente" (banner diz "Não desbota" numa peça que é desbotada de propósito)
A102: "Modelagem oversized com ombro caído" + tabela de medidas | D102: "Sustenta recompra", "converte", "avaliação positiva desde a primeira vestida"
A103: "15 cores" (conferir antes de publicar) | D103: Selos genéricos da galeria ("100% Original")
D104: "Carro-chefe do streetwear", "a maior paleta" como argumento de venda
D105: "Unissex que reduz trocas"
A107: 10. Pendências com o fornecedor
A108: Pendência | B108: Status | C108: Responsável | D108: Resposta
A109: Tabela de mangas × P17 | B109: Aberta
A110: Fotos de Preto e Azul Marinho | B110: Aberta
A111: Confirmar gramatura (175 g/m² × 180 GSM dos banners) | B111: Aberta
A112: Orçamento de personalização (bordado pequeno, DTF, etiqueta, tag) e frete Itajaí → SP | B112: Aberta
A113: Origem do algodão (não citada nesta página) | B113: Aberta
...

Sheet P17
A1: P17 — Camiseta Estonada Oversized com Bolso 175g
A3: 1. Identificação
A4: Código HMZT | B4: HMZT-P17-OVS-ESB175
A5: Fornecedor | B5: Lunfe Malhas — fabricação própria, Itajaí-SC
A6: Referência | B6: 7896976920472
A7: URL | B7: lunfemalhas.com.br/camiseta-estonada-oversized-bolso-atacado-algodao-penteado-lunfe
A8: Categoria no site | B8: Camisetas › Masculino › Oversized
A9: Linha HMZT recomendada | B9: Lavada/Vintage — destaque oversized com bolso (após reposição)
A10: Estoque | B10: 🔴 "Esse acabou" na própria página (sem seletor, sem preço no topo, sem "Disponibilidade")
A11: Descritor canônico (IA) | B11: Camiseta masculina oversized com bolso quadrado no peito esquerdo, ombro caído, corpo amplo abaixo do quadril, algodão penteado 175 g estonado: cor lavada irregular, mais clara nas costuras, na borda do bolso, na gola canelada e nas barras. Peça lisa, sem logos. Fundo cinza claro de estúdio.
A13: 2. Especificação técnica
A14: Item | B14: Valor | C14: Fonte
A15: Composição | B15: 100% algodão penteado
A16: Fio | B16: 30/1 penteado
A17: Gramatura | B17: 175 g/m² (texto) × 180 GSM (banner da galeria)
A18: Modelagem | B18: Oversized com bolso no peito
A19: Detalhe | B19: Bolso frontal no peito, aplicado antes da lavagem
A20: Acabamento | B20: Stone wash (lavagem com pedras-pomes) após a confecção + fixação pós-estonagem
A21: Gola | B21: Canelada 2/1, fecho em anel, reforço ombro a ombro
A22: Costuras | B22: Ponto cadeia; barra dupla em mangas e barra
A23: Tratamentos | B23: Pré-encolhimento, anti-torção, amaciamento
A24: Tamanhos | B24: P ao EG (5)
A25: Produção | B25: Fabricação própria Lunfe — Itajaí-SC
A26: Toque | B26: "Ultra macio, como camiseta lavada 50 vezes"
A27: Cor | B27: "Não progride nas lavagens domésticas"
A29: 3. Tabela de medidas (cm)
A30: Tamanho | B30: Comprimento | C30: Largura | D30: Ombros | E30: Mangas
A31: P | B31: 73 | C31: 57 | D31: 52 | E31: 22
A32: M | B32: 75 | C32: 59 | D32: 54 | E32: 24
A33: G | B33: 77 | C33: 61 | D33: 56 | E33: 26
A34: GG | B34: 79 | C34: 63 | D34: 58 | E34: 28
A35: EG | B35: 81 | C35: 65 | D35: 60 | E35: 30
A36: Tabela própria (± 1–2 cm), pré-encolhida. Modelo 1,84 m / 84 kg veste M. ⚠️ Mangas diferem do P16 (M 24 × 25; EG 30 × 28), embora o texto diga "mesma modelagem".
A37: Modelo das fotos: 1,84 m · 84 kg · veste M
A39: 4. Cores disponíveis
A40: Cor | B40: Código HMZT | C40: Ref. fornecedor | D40: Observação
A41: Verde Musgo | B41: VMG | C41: n/i | D41: Fotos #1, #2, #4
A42: Azul | B42: AZU | C42: n/i | D42: Azul índigo lavado (fotos #5, #7) — tom exato não definido
A43: Preto | B43: PRT | C43: n/i | D43: Sai grafite-oliva depois da lavagem (fotos #8, #9)
A44: Seletor não aparece (esgotado). Texto: 3 cores. "Azul" não diz qual azul.
A46: 5. Personalização (preço sempre sob orçamento)
A47: Técnica | B47: Detalhe | C47: Mínimo
A48: Bordado no bolso | B48: Até 8 × 8 cm | C48: 20 pç
A49: Silk localizado no bolso | B49: — | C49: 20 pç
A50: Etiqueta aplicada no bolso | B50: Costurada | C50: 20 pç
A51: DTF | B51: Full color | C51: 20 pç
A52: Etiqueta private label | B52: Interna + tag | C52: 20 pç
A54: 6. Preços do fornecedor (desconto progressivo)
A55: Preço base (R$) | B55: 39.78
A56: Faixa | B56: Peças | C56: Desconto | D56: Preço unitário | E56: Preço + Pix
A57: Faixa 1 | B57: 20–40 | C57: ='Regras Fornecedor'!$D$4 | D57: =ROUND($B$55*(1-C57),2) | E57: =ROUND(D57*(1-'Regras Fornecedor'!$B$10),2)
A58: Faixa 2 | B58: 40–80 | C58: ='Regras Fornecedor'!$D$5 | D58: =ROUND($B$55*(1-C58),2) | E58: =ROUND(D58*(1-'Regras Fornecedor'!$B$10),2)
A59: Faixa 3 | B59: 80–100 | C59: ='Regras Fornecedor'!$D$6 | D59: =ROUND($B$55*(1-C59),2) | E59: =ROUND(D59*(1-'Regras Fornecedor'!$B$10),2)
A60: Faixa 4 | B60: 100–300 | C60: ='Regras Fornecedor'!$D$7 | D60: =ROUND($B$55*(1-C60),2) | E60: =ROUND(D60*(1-'Regras Fornecedor'!$B$10),2)
A61: Faixa 5 | B61: 300–999 | C61: ='Regras Fornecedor'!$D$8 | D61: =ROUND($B$55*(1-C61),2) | E61: =ROUND(D61*(1-'Regras Fornecedor'!$B$10),2)
A63: 7. Custo HMZT e margem (lote de 20 peças, Pix)
A64: Peça (20 pç, Pix) | B64: =E57
A65: Personalização + etiqueta + tag (R$/pç) | B65: 10 | C65: Estimativa HMZT — trocar pelo orçamento real
A66: Frete rateado + embalagem (R$/pç) | B66: 4 | C66: Estimativa HMZT — trocar pelo orçamento real
A67: Custo unitário estimado | B67: =SUM(B64:B66)
A68: Preço de venda HMZT (R$) | B68: 149 | C68: Sugestão do dossiê — ajustar
A69: Impostos + gateway (% do preço) | B69: 0 | C69: A preencher (Simples + taxa Asaas)
A70: Margem bruta (R$) | B70: =B68-B67
A71: Margem bruta (%) | B71: =IF(B68=0,0,(B68-B67)/B68)
A72: Margem após impostos/gateway (%) | B72: =IF(B68=0,0,(B68*(1-B69)-B67)/B68) | C72: Ainda sem frete ao cliente e mídia
A74: 8. Contradições e erros ⚠️
A75: ⚠️ Conferência com a página do P02: o comparativo do P02 diz "Estonada Oversized Bolso 175g, 100% algodão penteado 30/1, 3 cores, R$ 39,78" — bate com esta página ✅ (175 g, 30/1, Verde Musgo/Azul/Preto, base R$ 39,78, mínimo R$ 27,85). E o "Esse acabou" do P02 também bate: a própria página do P17 está esgotada (sem seletor, sem preço no topo). O P02 ainda diz "peso ao vestir: leve" e "volume de vendas alto" 📣.
A76: ⚠️ Mangas × P16: texto diz "mesma modelagem oversized", mas as mangas diferem (M 24 × 25; EG 30 × 28; salto de 2 cm × 1 cm).
A77: ⚠️ "Toque peletizado/aveludado": peletizado é acabamento escovado (tipo suedine). Stone wash amacia, mas não cria pelo. Termo errado — não usar.
A78: ⚠️ Lavanderia: aqui "estonagem em lavanderia industrial"; no P14, "sem lavanderia terceirizada".
A79: ⚠️ Gramatura: 175 g/m² × "180GSM" no banner #10.
A80: ⚠️ Mockup #3: camiseta sem bolso e sem lavagem — não representa o produto. Banners #3, #6, #10 e #11 são os mesmos do P16.
A81: ⚠️ "Azul" sem especificar o tom (nas fotos é um índigo lavado).
A82: ⚠️ Reposição: o próprio FAQ avisa que "a estonagem é demorada — lotes podem levar mais tempo para reposição".
A84: 9. Comunicação HMZT
A85: ✅ Pode usar | D85: 📣 / ⛔ Não usar
A86: "100% algodão penteado, fio 30/1" | D86: "Ticket médio 25–40% acima do básico liso" / "+35% vs liso"
A87: "Lavada com pedras depois de costurada: cada peça tem tom e desgaste levemente diferentes" (é o processo físico — dizer como característica, não como "defeito" nem "exclusividade") | D87: "Exclusividade real que justifica preço premium" / "a peça se diferencia sozinha"
A88: "Gola canelada 2/1, costura ponto cadeia, reforço ombro a ombro, barra dupla" | D88: "Consistência que estonagens terceirizadas não alcançam"
A89: "Pré-encolhida e com tratamento anti-torção" | D89: "Toque de camiseta lavada 50 vezes" / "nenhum amaciamento químico reproduz"
A90: "Fabricada em Santa Catarina" | D90: "Não desbota" / "visual vintage permanente" (banner diz "Não desbota" numa peça que é desbotada de propósito)
A91: "Bolso no peito" — área para bordado discreto | D91: "Sustenta recompra", "converte", "avaliação positiva desde a primeira vestida"
A92: "Modelagem oversized com ombro caído" | D92: Selos genéricos da galeria ("100% Original")
D93: "Toque peletizado/aveludado"
D94: "Você vende como assinatura de marca"
D95: "Volume de vendas alto" (P02)
A97: 10. Pendências com o fornecedor
A98: Pendência | B98: Status | C98: Responsável | D98: Resposta
A99: Previsão de reposição | B99: Aberta
A100: Tabela de mangas × P16 | B100: Aberta
A101: Tom do "Azul" | B101: Aberta
A102: Medida e posição do bolso | B102: Aberta
A103: Confirmar gramatura (175 g/m² × 180 GSM dos banners) | B103: Aberta
A104: Orçamento de personalização (bordado pequeno, DTF, etiqueta, tag) e frete Itajaí → SP | B104: Aberta
A105: Origem do algodão (não citada nesta página) | B105: Aberta
A106: Tolerância de variação de tom entre lotes | B106: Aberta
A108: 11. Fluxo de prompts de lookbook (docs/shop-confeccao/prompts/P17-prompts.md)
A109: Foto | B109: Origem no print | C109: Formato | D109: Status
A110: F1 — 3/4 olhar lateral | B110: Origem: foto #1 (verde musgo) | C110: 4:5 | D110: A gerar
A111: F2 — 3/4 sorrindo | B111: Origem: foto #2 (verde musgo) | C111: 4:5 | D111: A gerar
...

Sheet P18
A1: P18 — Camiseta Rib Wide Texture 240g — canelado largo vertical
A3: 1. Identificação
A4: Código HMZT | B4: HMZT-P18-REG-RIB240
A5: Fornecedor | B5: Lunfe Malhas — fabricação própria, Itajaí-SC
A6: Referência | B6: 7898132575007 (EAN-13)
A7: URL | B7: lunfemalhas.com.br/camiseta-rib-wide-texture-240g-atacado-lunfe
A8: Categoria no site | B8: Camisetas › Malhas Texturizadas
A9: Linha HMZT recomendada | B9: Textura (nova) — alternativa vertical; esgotada
A10: Estoque | B10: 🔴 "Esse acabou" na página (sem seletor de cor) × FAQ: "5 cores em estoque, despacho em 24h" ⚠️
A11: Descritor canônico (IA) | B11: Camiseta masculina regular fit, manga curta, malha texturizada 240 g/m² com canelado largo vertical: colunas em relevo de 4–6 mm separadas por vales estreitos, do ombro à barra e ao longo das mangas; superfície fosca; gola careca em faixa lisa; barra dupla reta no quadril. Peça lisa, sem logos. Fundo cinza claro de estúdio.
A13: 2. Especificação técnica
A14: Item | B14: Valor | C14: Fonte
A15: Composição | B15: 52% algodão + 48% poliéster
A16: Origem do algodão | B16: "Algodão premium importado" — origem não informada
A17: Gramatura | B17: 240 g/m²
A18: Textura | B18: Rib Wide — canelado largo vertical: nervuras de 4–6 mm, vales de 2–3 mm, do ombro à barra; superfície fosca
A19: Construção | B19: Malha (tricô) texturizada — o texto chama de "tecelagem", termo errado para malha
A20: Modelagem | B20: Regular fit
A21: Gola | B21: Ribana lisa, acabamento clean (faixa lisa, sem canelado aparente)
A22: Acabamentos | B22: Costura reforçada em todas as emendas; barra dupla
A23: Tratamentos | B23: Pré-encolhimento, anti-torção, fixação de cor de alta solidez
A24: Tamanhos | B24: P, M, G, GG, EG (5)
A25: Cuidados | B25: Lavar do avesso, ciclo delicado, 30 °C
A26: Produção | B26: Fabricação própria Lunfe — Itajaí, SC
... A32: "Linhas verticais afinam e alongam — ilusão comprovada" | B32: Sem fonte
A34: 3. Tabela de medidas (cm)
A35: Tamanho | B35: Comprimento | C35: Largura | D35: Ombros | E35: Mangas
A36: P | B36: 70 | C36: 52 | D36: 44 | E36: 16
A37: M | B37: 72 | C37: 54 | D37: 46 | E37: 18
A38: G | B38: 74 | C38: 56 | D38: 48 | E38: 20
A39: GG | B39: 76 | C39: 58 | D39: 50 | E39: 22
A40: EG | B40: 78 | C40: 60 | D40: 52 | E40: 24
A41: Tabela do fornecedor em cm, medida em repouso, tolerância ± 2 cm. É a mesma tabela única dos produtos regulares Lunfe (M = 72 × 54, ombro 46, manga 18). Modelo das fotos: 1,84 m · 84 kg · veste M.
A42: Modelo das fotos: 1,84 m · 84 kg · veste M
A44: 4. Cores disponíveis
A45: Cor | B45: Código HMZT | C45: Ref. fornecedor | D45: Observação
A46: Preto | B46: PRT | C46: RBW-PRT | D46: Fotos #7–#9 (preto levemente azulado — confirmar se não é o Marinho)
A47: Off White | B47: OFF | C47: RBW-OFW | D47: Fotos #1–#3; a textura aparece mais
A48: Bege | B48: BGE | C48: RBW-BGE | D48: Só no texto; não aparece nas fotos
A49: Marrom | B49: MRR | C49: RBW-MRR | D49: Fotos #4–#6 (marrom-chocolate escuro)
A50: Marinho | B50: MAR | C50: RBW-MRN | D50: Só no texto
A51: Texto: 5 cores. Página: produto esgotado, sem seletor. Fotos: off-white, marrom e preto. Pantone a partir de 100 pç/cor.
A53: 5. Personalização (preço sempre sob orçamento)
A54: Técnica | B54: Detalhe | C54: Mínimo
A55: Silk screen | B55: Até 4 cores; a textura aparece sob a estampa (cobertura irregular nos vales) ⚠️ testar | C55: 20 pç
A56: DTF | B56: Full color; a prensa térmica pode achatar as nervuras ⚠️ testar pressão | C56: 20 pç
A57: Bordado | B57: Peito e mangas; usar entretela — o canelado pode franzir sob bordado denso | C57: 20 pç
A58: Etiqueta private label | B58: Etiqueta interna costurada + tag externa | C58: 20 pç
A59: Embalagem customizada | B59: Saco com logo, caixa premium, tag especial | C59: 50 pç
A60: Cor Pantone | B60: Tingimento exclusivo, 15–25 dias úteis | C60: 100 pç/cor
A62: 6. Preços do fornecedor (desconto progressivo)
A63: Preço base (R$) | B63: 59
A64: Faixa | B64: Peças | C64: Desconto | D64: Preço unitário | E64: Preço + Pix
A65: Faixa 1 | B65: 20–40 | C65: ='Regras Fornecedor'!$D$4 | D65: =ROUND($B$63*(1-C65),2) | E65: =ROUND(D65*(1-'Regras Fornecedor'!$B$10),2)
A66: Faixa 2 | B66: 40–80 | C66: ='Regras Fornecedor'!$D$5 | D66: =ROUND($B$63*(1-C66),2) | E66: =ROUND(D66*(1-'Regras Fornecedor'!$B$10),2)
A67: Faixa 3 | B67: 80–100 | C67: ='Regras Fornecedor'!$D$6 | D67: =ROUND($B$63*(1-C67),2) | E67: =ROUND(D67*(1-'Regras Fornecedor'!$B$10),2)
A68: Faixa 4 | B68: 100–300 | C68: ='Regras Fornecedor'!$D$7 | D68: =ROUND($B$63*(1-C68),2) | E68: =ROUND(D68*(1-'Regras Fornecedor'!$B$10),2)
A69: Faixa 5 | B69: 300–999 | C69: ='Regras Fornecedor'!$D$8 | D69: =ROUND($B$63*(1-C69),2) | E69: =ROUND(D69*(1-'Regras Fornecedor'!$B$10),2)
A71: 7. Custo HMZT e margem (lote de 20 peças, Pix)
A72: Peça (20 pç, Pix) | B72: =E65
A73: Personalização + etiqueta + tag (R$/pç) | B73: 10 | C73: Estimativa HMZT — trocar pelo orçamento real
A74: Frete rateado + embalagem (R$/pç) | B74: 4 | C74: Estimativa HMZT — trocar pelo orçamento real
A75: Custo unitário estimado | B75: =SUM(B72:B74)
A76: Preço de venda HMZT (R$) | B76: 149 | C76: Sugestão do dossiê — ajustar
A77: Impostos + gateway (% do preço) | B77: 0 | C77: A preencher (Simples + taxa Asaas)
A78: Margem bruta (R$) | B78: =B76-B75
A79: Margem bruta (%) | B79: =IF(B76=0,0,(B76-B75)/B76)
A80: Margem após impostos/gateway (%) | B80: =IF(B76=0,0,(B76*(1-B77)-B75)/B76) | C80: Ainda sem frete ao cliente e mídia
A82: 8. Contradições e erros ⚠️
A83: ⚠️ Estoque: página diz "Esse acabou"; FAQ diz 5 cores em estoque com despacho em 24h.
A84: ⚠️ Composição confirmada 52% algodão / 48% poliéster, base R$ 59,00 — bate com o texto do P04 e com a Plissé/Ripple/Waffle; a Piqué é outra composição (51% poliéster / 49% algodão).
A85: ⚠️ "Produzida por tecelagem": malha é tricô (knit), não tecelagem (tecido plano). Erro técnico repetido em toda a linha.
A86: ⚠️ Fotos × texto: o texto descreve nervuras regulares de 4–6 mm; as fotos mostram colunas de larguras variadas com grão horizontal (visual de tricô). Pedir amostra.
A87: ⚠️ O comparativo cita uma "Ottoman Texture 240g" (51% poliéster / 49% algodão, R$ 59,00) que não foi catalogada.
A88: ⚠️ "Algodão premium importado" sem origem — o algodão importado da Lunfe nos P05/P06 é de Xinjiang.
A89: ⚠️ Visualmente muito parecida com a Plissé (P19): as duas são verticais e largas; risco de canibalização se lançar as duas.
A91: 9. Comunicação HMZT
A92: ✅ Pode usar | D92: 📣 / ⛔ Não usar
A93: "Malha canelada larga vertical, 240 g/m²." | D93: "Algodão premium importado" — origem não informada; o algodão importado da Lunfe é de Xinjiang nos P05/P06 (risco de marca)
A94: "52% algodão, 48% poliéster" — sempre por extenso. | D94: "Ticket 40–60% acima da lisa", "margem real", "sustenta preço premium"
A95: "Textura no próprio tecido: a peça se diferencia sem estampa." | D95: "Categoria que está redefinindo o mercado", "dominando o mercado premium"
A96: "Caimento estruturado, não cola no corpo." | D96: "O cliente toca, não solta, compra" e demais afirmações de conversão sem fonte
A97: "Pré-encolhida, com tratamento anti-torção." | D97: "Textura permanente por toda a vida útil" (sem laudo)
A98: "Fabricada em Santa Catarina." | D98: "Coleção texturizada mais completa do mercado atacadista brasileiro"
D99: "Linhas verticais afinam e alongam — ilusão óptica comprovada"
D100: "Peça de alfaiataria casual", "polo de luxo", "peça de grife"
D101: "Sem concorrência na arara"
A103: 10. Pendências com o fornecedor
A104: Pendência | B104: Status | C104: Responsável | D104: Resposta
A105: Reposição e cartela real (página esgotada × FAQ em estoque) | B105: Aberta
A106: Origem do "algodão premium importado" (Xinjiang?) | B106: Aberta
A107: Amostra física: largura real das nervuras e aspecto (as fotos parecem jacquard irregular) | B107: Aberta
A108: Preto das fotos #7–#9 é Preto ou Marinho? | B108: Aberta
A109: Orçamento: bordado peito, etiqueta, tag; teste de DTF sobre o canelado | B109: Aberta
A110: Existe a Ottoman Texture 240g? Página e fotos | B110: Aberta
A112: 11. Fluxo de prompts de lookbook (docs/shop-confeccao/prompts/P18-prompts.md)
A113: Foto | B113: Origem no print | C113: Formato | D113: Status
A114: F1 — Frontal recortado (off-white) | B114: Origem: foto #1 da galeria (off-white, frontal, cabeça cortada na altura do nariz, braços soltos, jeans claro rasgado) | C114: 4:5 | D114: A gerar
A115: F2 — Detalhe gola, ombro e manga (off-white) | B115: Origem: foto #2 da galeria (off-white, recorte dos lábios ao peito, gola e manga à direita) | C115: 4:5 | D115: A gerar
A116: F3 — 3/4 ajustando o bracelete (off-white) | B116: Origem: foto #3 da galeria (off-white, leve 3/4, rosto cortado no nariz, mão direita segurando o pulso esquerdo) | C116: 4:5 | D116: A gerar
...

Sheet P19
A1: P19 — Camiseta Plissé Texture 240g — canelado vertical largo acetinado
A3: 1. Identificação
A4: Código HMZT | B4: HMZT-P19-REG-PLS240
A5: Fornecedor | B5: Lunfe Malhas — fabricação própria, Itajaí-SC
A6: Referência | B6: 7899881942508 (EAN-13)
A7: URL | B7: lunfemalhas.com.br/camiseta-plisse-texture-240g-atacado-lunfe
A8: Categoria no site | B8: Camisetas › Malhas Texturizadas
A9: Linha HMZT recomendada | B9: Textura (nova) — cápsula noturna / drop
A10: Estoque | B10: ✅ Em estoque — seletor mostra só Cinza e Preto; preço exibido R$ 53,10 (já com −10%)
A11: Descritor canônico (IA) | B11: Camiseta masculina regular fit, manga curta, malha texturizada 240 g/m² com canais verticais largos (5–8 mm) e regulares, faces planas com brilho acetinado suave e sulcos finos escuros, do ombro à barra e nas mangas; gola careca em faixa lisa fosca; barra dupla reta no quadril. Peça lisa, sem logos. Fundo cinza claro de estúdio.
A13: 2. Especificação técnica
A14: Item | B14: Valor | C14: Fonte
A15: Composição | B15: 52% algodão + 48% poliéster
A16: Origem do algodão | B16: "Algodão premium importado" — origem não informada
A17: Gramatura | B17: 240 g/m²
A18: Textura | B18: Plissé — canais verticais largos de 5–8 mm, regulares, com brilho acetinado
A19: Construção | B19: Malha (tricô) texturizada — o texto chama de "tecelagem", termo errado para malha
A20: Modelagem | B20: Regular fit
A21: Gola | B21: Ribana lisa, acabamento clean (faixa lisa, sem canelado aparente)
A22: Acabamentos | B22: Costura reforçada em todas as emendas; barra dupla
A23: Tratamentos | B23: Pré-encolhimento, anti-torção, fixação de cor de alta solidez
A24: Tamanhos | B24: P, M, G, GG, EG (5)
A25: Cuidados | B25: Lavar do avesso, ciclo delicado, 30 °C
A26: Produção | B26: Fabricação própria Lunfe — Itajaí, SC
... A32: Nome "plissé" | B32: Não é plissado termofixado; é um canelado largo regular (as fotos confirmam)
A34: 3. Tabela de medidas (cm)
A35: Tamanho | B35: Comprimento | C35: Largura | D35: Ombros | E35: Mangas
A36: P | B36: 70 | C36: 52 | D36: 44 | E36: 16
A37: M | B37: 72 | C37: 54 | D37: 46 | E37: 18
A38: G | B38: 74 | C38: 56 | D38: 48 | E38: 20
A39: GG | B39: 76 | C39: 58 | D39: 50 | E39: 22
A40: EG | B40: 78 | C40: 60 | D40: 52 | E40: 24
A41: Tabela do fornecedor em cm, medida em repouso, tolerância ± 2 cm. É a mesma tabela única dos produtos regulares Lunfe (M = 72 × 54, ombro 46, manga 18). Modelo das fotos: 1,84 m · 84 kg · veste M.
A42: Modelo das fotos: 1,84 m · 84 kg · veste M
A44: 4. Cores disponíveis
A45: Cor | B45: Código HMZT | C45: Ref. fornecedor | D45: Observação
A46: Preto | B46: PRT | C46: PLS-PRT | D46: Fotos #4–#7; onde o brilho mais aparece
A47: Cinza | B47: CZA | C47: — | D47: Fotos #1–#3 e seletor da página; ausente da lista do texto ⚠️
A48: Off White | B48: OFF | C48: PLS-OFW | D48: Só no texto; fora do seletor
A49: Bege | B49: BGE | C49: PLS-BGE | D49: Só no texto; fora do seletor
A50: Marrom | B50: MRR | C50: PLS-MRR | D50: Só no texto; fora do seletor
A51: Marinho | B51: MAR | C51: PLS-MRN | D51: Só no texto; fora do seletor
A52: Texto: 5 cores (Preto, Off White, Bege, Marrom, Marinho). Seletor: Cinza e Preto. Fotos: cinza claro e preto. Só PRT é confirmado nas três fontes.
A54: 5. Personalização (preço sempre sob orçamento)
A55: Técnica | B55: Detalhe | C55: Mínimo
A56: Silk screen | B56: Até 4 cores; estampa fosca sobre base brilhante. ⚠️ Poliéster tingido pode migrar para tinta clara (usar tinta anti-migração/baixa cura em cores escuras) | C56: 20 pç
A57: DTF | B57: Full color; ⚠️ a prensa pode marcar brilho ("lustro") e achatar os canais — testar com papel de proteção | C57: 20 pç
A58: Bordado | B58: Peito e mangas; bordado pequeno com entretela | C58: 20 pç
A59: Etiqueta private label | B59: Etiqueta interna costurada + tag externa | C59: 20 pç
A60: Embalagem customizada | B60: Saco com logo, caixa premium, tag especial | C60: 50 pç
A61: Cor Pantone | B61: Tingimento exclusivo, 15–25 dias úteis | C61: 100 pç/cor
A63: 6. Preços do fornecedor (desconto progressivo)
A64: Preço base (R$) | B64: 59
A65: Faixa | B65: Peças | C65: Desconto | D65: Preço unitário | E65: Preço + Pix
A66: Faixa 1 | B66: 20–40 | C66: ='Regras Fornecedor'!$D$4 | D66: =ROUND($B$64*(1-C66),2) | E66: =ROUND(D66*(1-'Regras Fornecedor'!$B$10),2)
A67: Faixa 2 | B67: 40–80 | C67: ='Regras Fornecedor'!$D$5 | D67: =ROUND($B$64*(1-C67),2) | E67: =ROUND(D67*(1-'Regras Fornecedor'!$B$10),2)
A68: Faixa 3 | B68: 80–100 | C68: ='Regras Fornecedor'!$D$6 | D68: =ROUND($B$64*(1-C68),2) | E68: =ROUND(D68*(1-'Regras Fornecedor'!$B$10),2)
A69: Faixa 4 | B69: 100–300 | C69: ='Regras Fornecedor'!$D$7 | D69: =ROUND($B$64*(1-C69),2) | E69: =ROUND(D69*(1-'Regras Fornecedor'!$B$10),2)
A70: Faixa 5 | B70: 300–999 | C70: ='Regras Fornecedor'!$D$8 | D70: =ROUND($B$64*(1-C70),2) | E70: =ROUND(D70*(1-'Regras Fornecedor'!$B$10),2)
A72: 7. Custo HMZT e margem (lote de 20 peças, Pix)
A73: Peça (20 pç, Pix) | B73: =E66
A74: Personalização + etiqueta + tag (R$/pç) | B74: 10 | C74: Estimativa HMZT — trocar pelo orçamento real
A75: Frete rateado + embalagem (R$/pç) | B75: 4 | C75: Estimativa HMZT — trocar pelo orçamento real
A76: Custo unitário estimado | B76: =SUM(B73:B75)
A77: Preço de venda HMZT (R$) | B77: 159 | C77: Sugestão do dossiê — ajustar
A78: Impostos + gateway (% do preço) | B78: 0 | C78: A preencher (Simples + taxa Asaas)
A79: Margem bruta (R$) | B79: =B77-B76
A80: Margem bruta (%) | B80: =IF(B77=0,0,(B77-B76)/B77)
A81: Margem após impostos/gateway (%) | B81: =IF(B77=0,0,(B77*(1-B78)-B76)/B77) | C81: Ainda sem frete ao cliente e mídia
A83: 8. Contradições e erros ⚠️
A84: ⚠️ Cores: o texto lista 5 cores sem cinza; o seletor da página mostra só Cinza e Preto; as fotos são cinza e preto.
A85: ⚠️ Composição 52% algodão / 48% poliéster, base R$ 59,00 — igual à Rib Wide, Ripple e Waffle; diferente da Piqué (51% poliéster / 49% algodão).
A86: ⚠️ "Tecelagem com canais": é malha (tricô), não tecelagem.
A87: ⚠️ O nome "plissé" sugere plissado termofixado; as fotos mostram um canelado largo e regular. Na prática é a "canelada larga" mais limpa da linha — parece mais Rib Wide que a própria Rib Wide.
A88: ⚠️ Explicação do brilho ("fibras de poliéster orientadas como no cetim") é pseudo-técnica; o brilho provável vem de fio de poliéster filamento ou do acabamento. Pedir ficha do fio.
A89: ⚠️ O resumo fala em "margem de 2–3×" e varejo de R$ 129–179 — alegação sem fonte.
A90: ⚠️ "Algodão premium importado" sem origem.
A92: 9. Comunicação HMZT
A93: ✅ Pode usar | D93: 📣 / ⛔ Não usar
A94: "Canelado vertical largo com brilho acetinado suave." | D94: "Algodão premium importado" — origem não informada; o algodão importado da Lunfe é de Xinjiang nos P05/P06 (risco de marca)
A95: "52% algodão, 48% poliéster" — sempre por extenso. | D95: "Ticket 40–60% acima da lisa", "margem real", "sustenta preço premium"
A96: "Malha 240 g/m², opaca, pré-encolhida, anti-torção." | D96: "Categoria que está redefinindo o mercado", "dominando o mercado premium"
A97: "Uma camiseta para a noite: presença sem precisar de camisa." (posicionamento, não dado) | D97: "O cliente toca, não solta, compra" e demais afirmações de conversão sem fonte
A98: "Fabricada em Santa Catarina." | D98: "Textura permanente por toda a vida útil" (sem laudo)
D99: "Coleção texturizada mais completa do mercado atacadista brasileiro"
D100: "O olho humano é biologicamente atraído por brilho", "atenção involuntária"
D101: "CTR significativamente acima da média", "engajamento acima da média"
D102: "Concorrência mínima", "praticamente inexistente no atacado brasileiro"
D103: "Margem de 2–3×", "consumidor aceita R$ 129–179"
D104: "Brilho estrutural que nunca sai" (sem laudo)
A106: 10. Pendências com o fornecedor
A107: Pendência | B107: Status | C107: Responsável | D107: Resposta
A108: Cartela real: Cinza existe no texto? Off White, Bege, Marrom e Marinho têm estoque? | B108: Aberta
A109: Origem do algodão e tipo do fio de poliéster (filamento?) que gera o brilho | B109: Aberta
A110: Teste de lavagem do brilho (5–10 ciclos) na amostra | B110: Aberta
A111: Teste de DTF/silk: marca de prensa e migração de corante | B111: Aberta
A112: Orçamento: bordado, etiqueta, tag, caixa | B112: Aberta
A114: 11. Fluxo de prompts de lookbook (docs/shop-confeccao/prompts/P19-prompts.md)
A115: Foto | B115: Origem no print | C115: Formato | D115: Status
A116: F1 — Hero 3/4 olhar para o lado (cinza) | B116: Origem: foto #1 da galeria (cinza, 3/4, olhar para baixo e para o lado, mãos ajustando o bracelete, jeans) | C116: 4:5 | D116: A gerar
...

Sheet P20
A1: P20 — Camiseta Ripple Texture 240g — micro-ondulação horizontal
A3: 1. Identificação
A4: Código HMZT | B4: HMZT-P20-REG-RPL240
A5: Fornecedor | B5: Lunfe Malhas — fabricação própria, Itajaí-SC
A6: Referência | B6: 7892896708893 (EAN-13)
A7: URL | B7: lunfemalhas.com.br/camiseta-ripple-texture-240g-atacado-lunfe
A8: Categoria no site | B8: Camisetas › Malhas Texturizadas
A9: Linha HMZT recomendada | B9: Textura (nova) — base principal (quiet luxury, sob blazer)
A10: Estoque | B10: ✅ Em estoque — seletor com 6 cores (Preto, Off White, Azul, Verde, Marrom, Cinza); preço exibido R$ 53,10
A11: Descritor canônico (IA) | B11: Camiseta masculina regular fit, manga curta, malha texturizada 240 g/m² com micro-ondulação horizontal fina (linhas de 1–2 mm) em toda a peça; parece lisa de longe e revela as linhas de perto; superfície fosca; gola careca em faixa lisa com pesponto; barra dupla reta no quadril. Peça lisa, sem logos. Fundo cinza claro de estúdio.
A13: 2. Especificação técnica
A14: Item | B14: Valor | C14: Fonte
A15: Composição | B15: 52% algodão + 48% poliéster
A16: Origem do algodão | B16: "Algodão premium importado" — origem não informada
A17: Gramatura | B17: 240 g/m²
A18: Textura | B18: Ripple — micro-ondulação horizontal: faixas de 1–2 mm alternando relevo e superfície lisa
A19: Construção | B19: Malha (tricô) texturizada — o texto chama de "tecelagem", termo errado para malha
A20: Modelagem | B20: Regular fit
A21: Gola | B21: Ribana lisa, acabamento clean (faixa lisa, sem canelado aparente)
A22: Acabamentos | B22: Costura reforçada em todas as emendas; barra dupla
A23: Tratamentos | B23: Pré-encolhimento, anti-torção, fixação de cor de alta solidez
A24: Tamanhos | B24: P, M, G, GG, EG (5)
A25: Cuidados | B25: Lavar do avesso, ciclo delicado, 30 °C
A26: Produção | B26: Fabricação própria Lunfe — Itajaí, SC
... A31: Visibilidade | B31: Sutil — aparece de perto e com luz lateral
A33: 3. Tabela de medidas (cm)
A34: Tamanho | B34: Comprimento | C34: Largura | D34: Ombros | E34: Mangas
A35: P | B35: 70 | C35: 52 | D35: 44 | E35: 16
A36: M | B36: 72 | C36: 54 | D36: 46 | E36: 18
A37: G | B37: 74 | C37: 56 | D37: 48 | E37: 20
A38: GG | B38: 76 | C38: 58 | D38: 50 | E38: 22
A39: EG | B39: 78 | C39: 60 | D39: 52 | E39: 24
A40: Tabela do fornecedor em cm, medida em repouso, tolerância ± 2 cm. É a mesma tabela única dos produtos regulares Lunfe (M = 72 × 54, ombro 46, manga 18). Modelo das fotos: 1,84 m · 84 kg · veste M.
A41: Modelo das fotos: 1,84 m · 84 kg · veste M
A43: 4. Cores disponíveis
A44: Cor | B44: Código HMZT | C44: Ref. fornecedor | D44: Observação
A45: Preto | B45: PRT | C45: RPL-PRT | D45: Fotos #1–#3 (preto azulado — pode ser o Marinho; confirmar)
A46: Off White | B46: OFF | C46: RPL-OFW | D46: Fotos #8–#10; a cor que mais revela a textura
A47: Marrom | B47: MRR | C47: RPL-MRR | D47: Fotos #4–#7 (chocolate escuro)
A48: Azul | B48: AZL | C48: — | D48: Fotos #11–#13 (azul lavanda/periwinkle); só no seletor ⚠️
A49: Verde | B49: VRD | C49: — | D49: Fotos #14–#15 (verde-oliva acinzentado); só no seletor ⚠️
A50: Cinza | B50: CZA | C50: — | D50: Só no seletor; não aparece nas fotos ⚠️
A51: Bege | B51: BGE | C51: RPL-BGE | D51: Só no texto ⚠️
A52: Marinho | B52: MAR | C52: RPL-MRN | D52: Só no texto ⚠️ (ou é o "preto" das fotos)
A53: Texto: 5 cores (Preto, Off White, Bege, Marrom, Marinho). Seletor: 6 (Preto, Off White, Azul, Verde, Marrom, Cinza). Fotos: 5 (preto/marinho, marrom, off-white, azul, verde). Confirmadas nas três fontes: Preto, Off White, Marrom.
A55: 5. Personalização (preço sempre sob orçamento)
A56: Técnica | B56: Detalhe | C56: Mínimo
A57: Silk screen | B57: Até 4 cores; a micro-textura interfere pouco. ⚠️ Cores escuras: tinta anti-migração (poliéster) | C57: 20 pç
A58: DTF | B58: Full color; boa aderência — testar prensa para não achatar a micro-ondulação | C58: 20 pç
A59: Bordado | B59: Peito e mangas; melhor combinação da linha (bordado pequeno no peito) | C59: 20 pç
A60: Etiqueta private label | B60: Etiqueta interna costurada + tag externa | C60: 20 pç
A61: Embalagem customizada | B61: Saco com logo, caixa premium, tag especial | C61: 50 pç
A62: Cor Pantone | B62: Tingimento exclusivo, 15–25 dias úteis | C62: 100 pç/cor
A64: 6. Preços do fornecedor (desconto progressivo)
A65: Preço base (R$) | B65: 59
A66: Faixa | B66: Peças | C66: Desconto | D66: Preço unitário | E66: Preço + Pix
A67: Faixa 1 | B67: 20–40 | C67: ='Regras Fornecedor'!$D$4 | D67: =ROUND($B$65*(1-C67),2) | E67: =ROUND(D67*(1-'Regras Fornecedor'!$B$10),2)
A68: Faixa 2 | B68: 40–80 | C68: ='Regras Fornecedor'!$D$5 | D68: =ROUND($B$65*(1-C68),2) | E68: =ROUND(D68*(1-'Regras Fornecedor'!$B$10),2)
A69: Faixa 3 | B69: 80–100 | C69: ='Regras Fornecedor'!$D$6 | D69: =ROUND($B$65*(1-C69),2) | E69: =ROUND(D69*(1-'Regras Fornecedor'!$B$10),2)
A70: Faixa 4 | B70: 100–300 | C70: ='Regras Fornecedor'!$D$7 | D70: =ROUND($B$65*(1-C70),2) | E70: =ROUND(D70*(1-'Regras Fornecedor'!$B$10),2)
A71: Faixa 5 | B71: 300–999 | C71: ='Regras Fornecedor'!$D$8 | D71: =ROUND($B$65*(1-C71),2) | E71: =ROUND(D71*(1-'Regras Fornecedor'!$B$10),2)
A73: 7. Custo HMZT e margem (lote de 20 peças, Pix)
A74: Peça (20 pç, Pix) | B74: =E67
A75: Personalização + etiqueta + tag (R$/pç) | B75: 10 | C75: Estimativa HMZT — trocar pelo orçamento real
A76: Frete rateado + embalagem (R$/pç) | B76: 4 | C76: Estimativa HMZT — trocar pelo orçamento real
A77: Custo unitário estimado | B77: =SUM(B74:B76)
A78: Preço de venda HMZT (R$) | B78: 149 | C78: Sugestão do dossiê — ajustar
A79: Impostos + gateway (% do preço) | B79: 0 | C79: A preencher (Simples + taxa Asaas)
A80: Margem bruta (R$) | B80: =B78-B77
A81: Margem bruta (%) | B81: =IF(B78=0,0,(B78-B77)/B78)
A82: Margem após impostos/gateway (%) | B82: =IF(B78=0,0,(B78*(1-B79)-B77)/B78) | C82: Ainda sem frete ao cliente e mídia
A84: 8. Contradições e erros ⚠️
A85: ⚠️ Cores: texto (5) × seletor (6) × fotos (5) não batem; Azul, Verde e Cinza não existem no texto; Bege e Marinho não existem no seletor.
A86: ⚠️ Composição 52% algodão / 48% poliéster, base R$ 59,00 — confirma o texto do P04 para a linha texturizada.
A87: ⚠️ "Tecelagem com variação de tensão": é malha, não tecelagem; a descrição do processo é vaga.
A88: ⚠️ O texto diz que a Ripple é "a única textura da linha que funciona sob blazer", mas o comparativo da própria página dá a Waffle como "aceitável" sob blazer.
A89: ⚠️ Compara com "ottoman" — há uma Ottoman Texture 240g citada na página da Rib Wide, não catalogada.
A90: ⚠️ "Algodão premium importado" sem origem.
A92: 9. Comunicação HMZT
A93: ✅ Pode usar | D93: 📣 / ⛔ Não usar
A94: "Micro-textura horizontal que aparece de perto e ao toque." | D94: "Algodão premium importado" — origem não informada; o algodão importado da Lunfe é de Xinjiang nos P05/P06 (risco de marca)
A95: "52% algodão, 48% poliéster" — sempre por extenso. | D95: "Ticket 40–60% acima da lisa", "margem real", "sustenta preço premium"
A96: "Parece lisa de longe; de perto, a textura aparece." | D96: "Categoria que está redefinindo o mercado", "dominando o mercado premium"
A97: "Funciona sozinha ou por baixo de blazer." (uso, não dado) | D97: "O cliente toca, não solta, compra" e demais afirmações de conversão sem fonte
A98: "Malha 240 g/m², pré-encolhida, anti-torção." | D98: "Textura permanente por toda a vida útil" (sem laudo)
A99: "Fabricada em Santa Catarina." | D99: "Coleção texturizada mais completa do mercado atacadista brasileiro"
D100: "O movimento quiet luxury domina a moda masculina 2024–2026"
D101: "Sustenta preço 30–50% acima do básico"
D102: "É a textura para quem entende de roupa" (tom ok como inspiração, não como fato)
A104: 10. Pendências com o fornecedor
A105: Pendência | B105: Status | C105: Responsável | D105: Resposta
A106: Cartela real e referência (RPL-xxx) de Azul, Verde e Cinza | B106: Aberta
A107: O "preto" das fotos #1–#3 é Preto ou Marinho? | B107: Aberta
A108: Origem do "algodão premium importado" | B108: Aberta
A109: Amostra: escala real da ondulação (1–2 mm) e opacidade no off-white | B109: Aberta
A110: Orçamento: bordado peito (até 8 cm), etiqueta, tag | B110: Aberta
A112: 11. Fluxo de prompts de lookbook (docs/shop-confeccao/prompts/P20-prompts.md)
A113: Foto | B113: Origem no print | C113: Formato | D113: Status
A114: F1 — Hero 3/4 mãos juntas (preto) | B114: Origem: foto #1 da galeria (preto-azulado, leve 3/4, cabeça inclinada, mãos juntas na cintura, calça off-white) | C114: 4:5 | D114: A gerar
A115: F2 — Detalhe gola e manga (preto) | B115: Origem: foto #2 da galeria (preto, recorte dos lábios ao peito) | C115: 4:5 | D115: A gerar
...

Sheet P21
A1: P21 — Camiseta Waffle Knit Texture 240g — faixas trançadas horizontais
A3: 1. Identificação
A4: Código HMZT | B4: HMZT-P21-REG-WFK240
A5: Fornecedor | B5: Lunfe Malhas — fabricação própria, Itajaí-SC
A6: Referência | B6: 7896698542020 (EAN-13)
A7: URL | B7: lunfemalhas.com.br/camiseta-waffle-knit-texture-240g-atacado-lunfe
A8: Categoria no site | B8: Camisetas › Malhas Texturizadas
A9: Linha HMZT recomendada | B9: Textura (nova) — casual de fim de semana e presente
A10: Estoque | B10: ✅ Em estoque — seletor com Marrom, Preto, Off White; "a partir de R$ 53,10"
A11: Descritor canônico (IA) | B11: Camiseta masculina regular fit, manga curta, malha texturizada 240 g/m² com listras horizontais tom sobre tom: faixas lisas alternadas com faixas em relevo de micro-células (3–5 mm), visual de tricô artesanal; superfície fosca; gola careca em faixa lisa; barra dupla reta no quadril. Peça lisa, sem logos. Fundo cinza claro de estúdio.
A13: 2. Especificação técnica
A14: Item | B14: Valor | C14: Fonte
A15: Composição | B15: 52% algodão + 48% poliéster
A16: Origem do algodão | B16: "Algodão premium importado" — origem não informada
A17: Gramatura | B17: 240 g/m²
A18: Textura | B18: Waffle Knit — faixas horizontais: faixas lisas alternadas com faixas em relevo de micro-células (3–5 mm)
A19: Construção | B19: Malha (tricô) texturizada — o texto chama de "tecelagem", termo errado para malha
A20: Modelagem | B20: Regular fit
A21: Gola | B21: Ribana lisa, acabamento clean (faixa lisa, sem canelado aparente)
A22: Acabamentos | B22: Costura reforçada em todas as emendas; barra dupla
A23: Tratamentos | B23: Pré-encolhimento, anti-torção, fixação de cor de alta solidez
A24: Tamanhos | B24: P, M, G, GG, EG (5)
A25: Cuidados | B25: Lavar do avesso, ciclo delicado, 30 °C
A26: Produção | B26: Fabricação própria Lunfe — Itajaí, SC
... A31: Nome "waffle" | B31: As fotos mostram listras horizontais de micro-bolinhas (tipo pipoca/arroz), não a grade quadriculada de um waffle
A33: 3. Tabela de medidas (cm)
A34: Tamanho | B34: Comprimento | C34: Largura | D34: Ombros | E34: Mangas
A35: P | B35: 70 | C35: 52 | D35: 44 | E35: 16
A36: M | B36: 72 | C36: 54 | D36: 46 | E36: 18
A37: G | B37: 74 | C37: 56 | D37: 48 | E37: 20
A38: GG | B38: 76 | C38: 58 | D38: 50 | E38: 22
A39: EG | B39: 78 | C39: 60 | D39: 52 | E39: 24
A40: Tabela do fornecedor em cm, medida em repouso, tolerância ± 2 cm. É a mesma tabela única dos produtos regulares Lunfe (M = 72 × 54, ombro 46, manga 18). Modelo das fotos: 1,84 m · 84 kg · veste M.
A41: Modelo das fotos: 1,84 m · 84 kg · veste M
A43: 4. Cores disponíveis
A44: Cor | B44: Código HMZT | C44: Ref. fornecedor | D44: Observação
A45: Preto | B45: PRT | C45: WFK-PRT | D45: Fotos #4–#6
A46: Off White | B46: OFF | C46: WFK-OFW | D46: Fotos #7–#9
A47: Bege | B47: BGE | C47: WFK-BGE | D47: Fotos #1–#3 (areia claro); no seletor não há bege — aparece "Marrom" ⚠️
A48: Marrom | B48: MRR | C48: WFK-MRR | D48: No seletor e no texto; não aparece nas fotos (ou é o bege das fotos?)
A49: Marinho | B49: MAR | C49: WFK-MRN | D49: Só no texto
A50: Texto: 5 cores. Seletor: Marrom, Preto, Off White. Fotos: bege/areia, preto, off-white. Confirmar se o "Marrom" do seletor é o bege das fotos.
A52: 5. Personalização (preço sempre sob orçamento)
A53: Técnica | B53: Detalhe | C53: Mínimo
A54: Silk screen | B54: Até 4 cores; a textura cria fundo irregular — preferir arte pequena. ⚠️ Anti-migração em cores escuras | C54: 20 pç
A55: DTF | B55: Full color; ⚠️ a prensa achata as micro-células — testar | C55: 20 pç
A56: Bordado | B56: Peito e mangas; contraste fio liso × textura — melhor opção | C56: 20 pç
A57: Etiqueta private label | B57: Etiqueta interna costurada + tag externa | C57: 20 pç
A58: Embalagem customizada | B58: Saco com logo, caixa premium, tag especial | C58: 50 pç
A59: Cor Pantone | B59: Tingimento exclusivo, 15–25 dias úteis | C59: 100 pç/cor
A61: 6. Preços do fornecedor (desconto progressivo)
A62: Preço base (R$) | B62: 59
A63: Faixa | B63: Peças | C63: Desconto | D63: Preço unitário | E63: Preço + Pix
A64: Faixa 1 | B64: 20–40 | C64: ='Regras Fornecedor'!$D$4 | D64: =ROUND($B$62*(1-C64),2) | E64: =ROUND(D64*(1-'Regras Fornecedor'!$B$10),2)
A65: Faixa 2 | B65: 40–80 | C65: ='Regras Fornecedor'!$D$5 | D65: =ROUND($B$62*(1-C65),2) | E65: =ROUND(D65*(1-'Regras Fornecedor'!$B$10),2)
A66: Faixa 3 | B66: 80–100 | C66: ='Regras Fornecedor'!$D$6 | D66: =ROUND($B$62*(1-C66),2) | E66: =ROUND(D66*(1-'Regras Fornecedor'!$B$10),2)
A67: Faixa 4 | B67: 100–300 | C67: ='Regras Fornecedor'!$D$7 | D67: =ROUND($B$62*(1-C67),2) | E67: =ROUND(D67*(1-'Regras Fornecedor'!$B$10),2)
A68: Faixa 5 | B68: 300–999 | C68: ='Regras Fornecedor'!$D$8 | D68: =ROUND($B$62*(1-C68),2) | E68: =ROUND(D68*(1-'Regras Fornecedor'!$B$10),2)
A70: 7. Custo HMZT e margem (lote de 20 peças, Pix)
A71: Peça (20 pç, Pix) | B71: =E64
A72: Personalização + etiqueta + tag (R$/pç) | B72: 10 | C72: Estimativa HMZT — trocar pelo orçamento real
A73: Frete rateado + embalagem (R$/pç) | B73: 4 | C73: Estimativa HMZT — trocar pelo orçamento real
A74: Custo unitário estimado | B74: =SUM(B71:B73)
A75: Preço de venda HMZT (R$) | B75: 149 | C75: Sugestão do dossiê — ajustar
A76: Impostos + gateway (% do preço) | B76: 0 | C76: A preencher (Simples + taxa Asaas)
A77: Margem bruta (R$) | B77: =B75-B74
A78: Margem bruta (%) | B78: =IF(B75=0,0,(B75-B74)/B75)
A79: Margem após impostos/gateway (%) | B79: =IF(B75=0,0,(B75*(1-B76)-B74)/B75) | C79: Ainda sem frete ao cliente e mídia
A81: 8. Contradições e erros ⚠️
A82: ⚠️ Cores: seletor mostra Marrom, Preto, Off White; fotos mostram bege, preto, off-white; texto lista 5 cores.
A83: ⚠️ Composição 52% algodão / 48% poliéster, base R$ 59,00 — igual às outras três texturas verticais/horizontais.
A84: ⚠️ "Waffle" no nome, mas o visual é de listras horizontais com micro-bolinhas, não de grade de waffle.
A85: ⚠️ "Tecelagem com pontos alternados": é malha, não tecelagem.
A86: ⚠️ "Escala de 3–5 mm é a que os dedos mais percebem" — pseudo-ciência sem fonte.
A87: ⚠️ "Algodão premium importado" sem origem.
A89: 9. Comunicação HMZT
A90: ✅ Pode usar | D90: 📣 / ⛔ Não usar
A91: "Textura de faixas horizontais com relevo, com visual de tricô artesanal." | D91: "Algodão premium importado" — origem não informada; o algodão importado da Lunfe é de Xinjiang nos P05/P06 (risco de marca)
A92: "52% algodão, 48% poliéster" — sempre por extenso. | D92: "Ticket 40–60% acima da lisa", "margem real", "sustenta preço premium"
A93: "Malha 240 g/m², pré-encolhida, anti-torção." | D93: "Categoria que está redefinindo o mercado", "dominando o mercado premium"
A94: "Boa para presente com embalagem." (uso) | D94: "O cliente toca, não solta, compra" e demais afirmações de conversão sem fonte
A95: "Fabricada em Santa Catarina." | D95: "Textura permanente por toda a vida útil" (sem laudo)
D96: "Coleção texturizada mais completa do mercado atacadista brasileiro"
D97: "Feita à mão", "artesanal" como fato — é industrial (pode dizer "visual artesanal")
D98: "Compra por toque", "tempo de contato maior = mais conversão"
D99: "Faixa que os dedos humanos mais respondem"
D100: "Handmade look domina 2025–2026"
A102: 10. Pendências com o fornecedor
A103: Pendência | B103: Status | C103: Responsável | D103: Resposta
A104: Cor "Marrom" do seletor = bege das fotos? Cartela e referências reais | B104: Aberta
A105: Origem do "algodão premium importado" | B105: Aberta
A106: Amostra: estrutura real (células em faixa × grade waffle) | B106: Aberta
A107: Teste de DTF/silk sobre as células | B107: Aberta
A108: Orçamento: bordado peito, etiqueta, tag, caixa de presente | B108: Aberta
A110: 11. Fluxo de prompts de lookbook (docs/shop-confeccao/prompts/P21-prompts.md)
A111: Foto | B111: Origem no print | C111: Formato | D111: Status
A112: F1 — Frontal olhar para o lado (bege) | B112: Origem: foto #1 da galeria (bege, frontal, cabeça virada para a direita da câmera, jeans) | C112: 4:5 | D112: A gerar
A113: F2 — 3/4 ajustando o bracelete (bege) | B113: Origem: foto #2 da galeria (bege, 3/4, cabeça inclinada, mãos na cintura) | C113: 4:5 | D113: A gerar
A114: F3 — Detalhe gola e manga (bege) | B114: Origem: foto #3 da galeria (bege, recorte dos lábios ao peito, colar fino) | C114: 4:5 | D114: A gerar
A115: F4 — Detalhe gola e manga (preto) | B115: Origem: foto #4 da galeria (preto, recorte dos lábios ao peito) — cor original 'black', calça 'off-white cream straight trousers' | C115: 4:5 | D115: A gerar
...

Sheet P22
A1: P22 — Camiseta Piqué Texture 240g — micro-mesh
A3: 1. Identificação
A4: Código HMZT | B4: HMZT-P22-REG-PIQ240
A5: Fornecedor | B5: Lunfe Malhas — fabricação própria, Itajaí-SC
A6: Referência | B6: 7892446890252 (EAN-13)
A7: URL | B7: lunfemalhas.com.br/camiseta-pique-texture-240g-atacado-private-label-lunfe
A8: Categoria no site | B8: Camisetas › Malhas Texturizadas
A9: Linha HMZT recomendada | B9: Textura (nova) — piquê "old money" e uniforme B2B bordado
A10: Estoque | B10: ✅ Pronta entrega: Branco, Azul Celeste, Verde Sage ("estoque permanente"); "a partir de R$ 53,10"; despacho em até 3 dias úteis
A11: Descritor canônico (IA) | B11: Camiseta masculina regular fit, manga curta, malha piquê 240 g/m² (51% poliéster, 49% algodão) com micro-losangos em grade regular, textura de camisa polo, superfície fosca e seca; gola careca em faixa lisa com pesponto; barra dupla reta no quadril. Peça lisa, sem logos. Fundo cinza claro de estúdio.
A13: 2. Especificação técnica
A14: Item | B14: Valor | C14: Fonte
A15: Composição | B15: 51% poliéster + 49% algodão (poliéster majoritário)
A16: Gramatura | B16: 240 g/m² (± 5%)
A17: Textura | B17: Piquê micro-mesh: micro-losangos 3D em grade regular, pontos altos e baixos alternados
A18: Construção | B18: "Tecelagem piquê (interlock com relevo micro-mesh)" — piquê é malha de ponto carregado, não interlock nem tecelagem
A19: Largura do rolo | B19: 1,80 m (tubular aberta)
A20: Rendimento | B20: 3,5 a 4,0 camisetas por metro linear (M)
A21: Tingimento | B21: "Reativo com fixação" — corante reativo não tinge poliéster (51% da peça)
A22: Tratamentos | B22: Pré-encolhimento térmico; controle dimensional peça a peça
A23: Gola | B23: "Ribana reforçada, acabamento clean, sem canelado" (faixa lisa com pesponto nas fotos)
A24: Costuras | B24: Ponto cadeia em todas as emendas; reforço ombro a ombro
A25: Barras | B25: Dupla em mangas e barra
A26: Modelagem | B26: Regular fit (oversized "em estudo")
... A33: Preço | B33: Tabela "sob consulta" × resumo "a partir de R$ 41,30" e página R$ 53,10
A35: 3. Tabela de medidas (cm)
A36: Tamanho | B36: Comprimento | C36: Largura | D36: Ombros | E36: Mangas
A37: P | B37: 70 | C37: 52 | D37: 44 | E37: 16
A38: M | B38: 72 | C38: 54 | D38: 46 | E38: 18
A39: G | B39: 74 | C39: 56 | D39: 48 | E39: 20
A40: GG | B40: 76 | C40: 58 | D40: 50 | E40: 22
A41: EG | B41: 78 | C41: 60 | D41: 52 | E41: 24
A42: Tabela do fornecedor em cm, em repouso, ± 2 cm — mesma base de modelagem das linhas 100% algodão. Grade customizada acima de 200 pç. Modelo: 1,84 m · 84 kg · veste M.
A43: Modelo das fotos: 1,84 m · 84 kg · veste M
A45: 4. Cores disponíveis
A46: Cor | B46: Código HMZT | C46: Ref. fornecedor | D46: Observação
A47: Branco | B47: BCO | C47: PIQ-BRA | D47: Fotos #4–#5; pronta entrega
A48: Azul Celeste | B48: AZC | C48: PIQ-AZC | D48: Fotos #1–#3; nas fotos é um azul-médio vivo (cornflower), mais forte que "celeste" ⚠️
A49: Verde Sage | B49: VSG | C49: PIQ-VSG | D49: Fotos #6–#8; verde-sálvia acinzentado
A50: Só 3 cores em pronta entrega (bate texto × seletor × fotos). Outras cores: Pantone a partir de 100 pç/cor, 15–25 dias úteis. Não há preto nem off-white.
A52: 5. Personalização (preço sempre sob orçamento)
A53: Técnica | B53: Detalhe | C53: Mínimo
A54: Silk screen | B54: Até 4 cores. ⚠️ Poliéster majoritário: usar tinta anti-migração/baixa cura; a textura aparece sob a tinta | C54: 20 pç
A55: DTF | B55: Full color; ⚠️ temperatura baixa (poliéster marca/brilha) e testar achatamento da textura | C55: 20 pç
A56: Bordado | B56: Até 15.000 pontos — melhor opção (logo peito, estilo polo) | C56: 20 pç
A57: Etiqueta private label | B57: Etiqueta interna + tag externa | C57: 20 pç
A58: Embalagem customizada | B58: Saco com logo, caixa personalizada, tag | C58: 50 pç
A59: Cor Pantone | B59: Tingimento exclusivo, 15–25 dias úteis | C59: 100 pç/cor
A61: 6. Preços do fornecedor (desconto progressivo)
A62: Preço base (R$) | B62: 59
A63: Faixa | B63: Peças | C63: Desconto | D63: Preço unitário | E63: Preço + Pix
A64: Faixa 1 | B64: 20–40 | C64: ='Regras Fornecedor'!$D$4 | D64: =ROUND($B$62*(1-C64),2) | E64: =ROUND(D64*(1-'Regras Fornecedor'!$B$10),2)
A65: Faixa 2 | B65: 40–80 | C65: ='Regras Fornecedor'!$D$5 | D65: =ROUND($B$62*(1-C65),2) | E65: =ROUND(D65*(1-'Regras Fornecedor'!$B$10),2)
A66: Faixa 3 | B66: 80–100 | C66: ='Regras Fornecedor'!$D$6 | D66: =ROUND($B$62*(1-C66),2) | E66: =ROUND(D66*(1-'Regras Fornecedor'!$B$10),2)
A67: Faixa 4 | B67: 100–300 | C67: ='Regras Fornecedor'!$D$7 | D67: =ROUND($B$62*(1-C67),2) | E67: =ROUND(D67*(1-'Regras Fornecedor'!$B$10),2)
A68: Faixa 5 | B68: 300–999 | C68: ='Regras Fornecedor'!$D$8 | D68: =ROUND($B$62*(1-C68),2) | E68: =ROUND(D68*(1-'Regras Fornecedor'!$B$10),2)
A70: 7. Custo HMZT e margem (lote de 20 peças, Pix)
A71: Peça (20 pç, Pix) | B71: =E64
A72: Personalização + etiqueta + tag (R$/pç) | B72: 10 | C72: Estimativa HMZT — trocar pelo orçamento real
A73: Frete rateado + embalagem (R$/pç) | B73: 4 | C73: Estimativa HMZT — trocar pelo orçamento real
A74: Custo unitário estimado | B74: =SUM(B71:B73)
A75: Preço de venda HMZT (R$) | B75: 139 | C75: Sugestão do dossiê — ajustar
A76: Impostos + gateway (% do preço) | B76: 0 | C76: A preencher (Simples + taxa Asaas)
A77: Margem bruta (R$) | B77: =B75-B74
A78: Margem bruta (%) | B78: =IF(B75=0,0,(B75-B74)/B75)
A79: Margem após impostos/gateway (%) | B79: =IF(B75=0,0,(B75*(1-B76)-B74)/B75) | C79: Ainda sem frete ao cliente e mídia
A81: 8. Contradições e erros ⚠️
A82: ⚠️ Composição: 51% poliéster / 49% algodão — confirma o texto do P05; o texto do P04 (52% algodão / 48% poliéster) vale para Rib Wide, Plissé, Ripple e Waffle, não para a Piqué. São duas composições na mesma "linha texturizada".
A83: ⚠️ Preço: a tabela diz "sob consulta" em todas as faixas, mas o resumo diz "a partir de R$ 41,30" e a página mostra "a partir de R$ 53,10" — equivale à base R$ 59,00 das outras texturas (inferido; confirmar).
A84: ⚠️ "Tingimento reativo": corante reativo só tinge a parte de algodão; poliéster exige corante disperso (tingimento em dois banhos). Pedir o processo real — risco de cor desigual ou mescla não intencional.
A85: ⚠️ "Interlock com relevo" / "tecelagem": piquê é malha de ponto carregado; não é interlock nem tecido plano.
A86: ⚠️ "Ribana... sem canelado": ribana é, por definição, canelada; nas fotos a gola é uma faixa lisa com pesponto.
A87: ⚠️ Prazo: aqui "despacho em até 3 dias úteis"; nas outras texturas, 24 h úteis.
A88: ⚠️ Comparativo diz "Chinese Cotton 180g"; a ficha P06 é 160 g.
A89: ⚠️ A página da Rib Wide descreve a Piqué como "micro-mesh (furinhos)" e cita uma Ottoman Texture 240g não catalogada.
A90: ⚠️ Cor "Azul Celeste" nas fotos é um azul-médio vivo, não celeste.
A92: 9. Comunicação HMZT
A93: ✅ Pode usar | D93: 📣 / ⛔ Não usar
A94: "Malha piquê 240 g/m², textura de polo em formato de camiseta." | D94: "A mesma engenharia de Zara, COS, H&M Studio" — nunca citar marcas de terceiros
A95: "51% poliéster, 49% algodão" — sempre por extenso, poliéster primeiro. | D95: "Marcas com textura registraram ticket 40–60% maior", "os dados são claros"
A96: "Amassa pouco e seca rápido" (propriedade geral do poliéster; sem número). | D96: "Uma das poucas fábricas nacionais", "produto de catálogo internacional"
A97: "Aceita bordado de logo, no estilo polo." | D97: "Anti-rugas = menos devoluções", "cliente que volta"
A98: "Fabricada em Santa Catarina, com malharia própria." | D98: "95% das marcas vendem lisa"
D99: "Secagem 2–3× mais rápida" (sem laudo)
D100: "Algodão" como argumento principal — a peça é majoritariamente poliéster
A102: 10. Pendências com o fornecedor
A103: Pendência | B103: Status | C103: Responsável | D103: Resposta
A104: Preço base oficial (tabela "sob consulta") | B104: Aberta
A105: Processo de tingimento (reativo + disperso?) e solidez de cor | B105: Aberta
A106: Cor real do "Azul Celeste"; existe preto, marinho ou off-white em pronta entrega? | B106: Aberta
A107: Prazo real: 24 h ou 3 dias úteis | B107: Aberta
A108: Orçamento: bordado peito até 15.000 pontos, etiqueta, tag | B108: Aberta
A109: Previsão da versão oversized | B109: Aberta
A111: 11. Fluxo de prompts de lookbook (docs/shop-confeccao/prompts/P22-prompts.md)
A112: Foto | B112: Origem no print | C112: Formato | D112: Status
A113: F1 — Frontal braços soltos (azul) | B113: Origem: foto #1 da galeria (azul, frontal, olhar para a câmera, jeans claro) | C113: 4:5 | D113: A gerar
A114: F2 — Detalhe gola com pesponto (azul) | B114: Origem: foto #2 da galeria (azul, recorte dos lábios ao peito, gola lisa com pesponto) | C114: 4:5 | D114: A gerar
A115: F3 — Olhar baixo pinçando a manga (azul) | B115: Origem: foto #3 da galeria (azul, cabeça baixa, mão pinçando a manga esquerda) | C115: 4:5 | D115: A gerar
A116: F4 — Frontal mão no bolso (branco) | B116: Origem: foto #4 da galeria (branco, leve 3/4, mão esquerda no bolso) — cor original 'bright white' | C116: 4:5 | D116: A gerar
A117: F5 — Detalhe mão pinçando a manga (branco) | B117: Origem: foto #5 da galeria (branco, recorte dos lábios ao peito, mão pinçando a barra da manga, anel de sinete) | C117: 4:5 | D117: A gerar
...

Sheet P23
A1: P23 — Regata Masculina Canelada 2/1 Slim Fit (American Style)
A3: 1. Identificação
A4: Código HMZT | B4: HMZT-P23-SLM-CAN21
A5: Fornecedor | B5: Lunfe Malhas — fabricação própria, Itajaí-SC
A6: Referência | B6: 7891024178355 (EAN-13)
A7: URL | B7: lunfemalhas.com.br/regata-masculina-canelada-atacado-slim-fit-lunfe
A8: Categoria no site | B8: Camisetas › Masculino › Regatas
A9: Linha HMZT recomendada | B9: Regatas / Verão — Essencial (entrada, kit e cross-sell)
A10: Estoque | B10: 🔴 'Esse acabou' na página (sem seletor de cor); resumo promete envio em 24h ⚠️
A11: Descritor canônico (IA) | B11: Regata masculina slim fit estilo americano em malha canelada 2/1 de algodão, nervuras verticais finas, gola careca alta com viés de ribana, cavas moderadas com viés, alças de 6–7 cm, barra reta no quadril. Justa ao corpo, fosca. Peça lisa.
A13: 2. Especificação técnica
A14: Item | B14: Valor | C14: Fonte
A15: Tipo | B15: Regata masculina (sem manga)
A16: Malha | B16: Canelada rib knit 2/1, 'alta densidade de fios'
A17: Composição | B17: 100% algodão (sem elastano — elasticidade é mecânica, da nervura)
A18: Gramatura | B18: Não informada
A19: Modelagem | B19: Slim fit / American style (ajustada)
A20: Gola | B20: Careca alta, acabamento reforçado (viés de ribana fina nas fotos)
A21: Cavas | B21: Acabamento limpo com viés de ribana; cava moderada (não 'cavadona')
A22: Reforços | B22: Travetes nos pontos de tensão
A23: Tratamentos | B23: Amaciamento industrial; estabilização de encolhimento
A24: Opacidade | B24: Não transparece 'em condições normais de uso' (inclusive branco)
A25: Tingimento | B25: 'Alta fixação — vermelho que não desbota'
A26: Tamanhos | B26: P ao EG (5)
... A28: Modelo das fotos | B28: 1,84 m · 84 kg · veste M
A30: 3. Tabela de medidas (cm)
A31: Tamanho | B31: Comprimento | C31: Largura | D31: Cavas
A32: P | B32: 68 | C32: 46 | D32: 22
A33: M | B33: 70 | C33: 48 | D33: 23
A34: G | B34: 72 | C34: 50 | D34: 24
A35: GG | B35: 74 | C35: 52 | D35: 25
A36: EG | B36: 76 | C36: 54 | D36: 26
A37: Em cm, ± 1–2 cm. Largura = meia-circunferência do peito (M = 48 cm ≈ 96 cm de volta, menor que o tórax do modelo — a nervura estica). 'Cavas' = altura da cava. ⚠️ Faltam largura da alça/ombro e medida da barra.
A38: Modelo das fotos: 1,84 m · 84 kg · veste M
A40: 4. Cores disponíveis
A41: Cor | B41: Código HMZT | C41: Ref. fornecedor | D41: Observação
A42: Preto | B42: PRT | C42: — (sem ref.) | D42: Fotos #1–#3
A43: Branco | B43: BRA | C43: — (sem ref.) | D43: Fotos #6–#8 (lê como branco óptico / off leve)
A44: Azul | B44: AZU | C44: — (sem ref.) | D44: Fotos #9–#10 — azul médio 'cornflower', não royal
A45: Vermelho | B45: VRM | C45: — (sem ref.) | D45: Fotos #4–#5
A46: Marinho | B46: MAR | C46: — (sem ref.) | D46: Fotos #11–#12
A47: 5 cores na ficha técnica, todas fotografadas. A página não publica código de referência por cor (diferente dos moletons) — pedir. Página sem seletor de variação ('Esse acabou').
A49: 5. Personalização (preço sempre sob orçamento)
A50: Técnica | B50: Detalhe | C50: Mínimo
A51: Bordado | B51: Peito esquerdo pequeno (≤ 6 cm) — 🟢 melhor opção; usar entretela removível para a nervura não repuxar | C51: 20 pç
A52: Silk base d'água | B52: Frente/costas — ⚠️ nervura 2/1 dá impressão 'listrada'; só tinta com elasticidade, nunca plastisol rígido | C52: 20 pç
A53: DTF | B53: Full color — ⚠️ filme rígido sobre malha elástica tende a trincar; só peça-teste | C53: 20 pç
A54: Etiqueta private label | B54: Etiqueta interna + tag | C54: 20 pç
A55: Preço | B55: Toda personalização sob orçamento (não informado) | C55: —
A57: 6. Preços do fornecedor (desconto progressivo)
A58: Preço base (R$) | B58: 24.99
A59: Faixa | B59: Peças | C59: Desconto | D59: Preço unitário | E59: Preço + Pix
A60: Faixa 1 | B60: 20–40 | C60: ='Regras Fornecedor'!$D$4 | D60: =ROUND($B$58*(1-C60),2) | E60: =ROUND(D60*(1-'Regras Fornecedor'!$B$10),2)
A61: Faixa 2 | B61: 40–80 | C61: ='Regras Fornecedor'!$D$5 | D61: =ROUND($B$58*(1-C61),2) | E61: =ROUND(D61*(1-'Regras Fornecedor'!$B$10),2)
A62: Faixa 3 | B62: 80–100 | C62: ='Regras Fornecedor'!$D$6 | D62: =ROUND($B$58*(1-C62),2) | E62: =ROUND(D62*(1-'Regras Fornecedor'!$B$10),2)
A63: Faixa 4 | B63: 100–300 | C63: ='Regras Fornecedor'!$D$7 | D63: =ROUND($B$58*(1-C63),2) | E63: =ROUND(D63*(1-'Regras Fornecedor'!$B$10),2)
A64: Faixa 5 | B64: 300–999 | C64: ='Regras Fornecedor'!$D$8 | D64: =ROUND($B$58*(1-C64),2) | E64: =ROUND(D64*(1-'Regras Fornecedor'!$B$10),2)
A66: 7. Custo HMZT e margem (lote de 20 peças, Pix)
A67: Peça (20 pç, Pix) | B67: =E60
A68: Personalização + etiqueta + tag (R$/pç) | B68: 8 | C68: Estimativa HMZT — trocar pelo orçamento real
A69: Frete rateado + embalagem (R$/pç) | B69: 4 | C69: Estimativa HMZT — trocar pelo orçamento real
A70: Custo unitário estimado | B70: =SUM(B67:B69)
A71: Preço de venda HMZT (R$) | B71: 89 | C71: Sugestão do dossiê — ajustar
A72: Impostos + gateway (% do preço) | B72: 0 | C72: A preencher (Simples + taxa Asaas)
A73: Margem bruta (R$) | B73: =B71-B70
A74: Margem bruta (%) | B74: =IF(B71=0,0,(B71-B70)/B71)
A75: Margem após impostos/gateway (%) | B75: =IF(B71=0,0,(B71*(1-B72)-B70)/B71) | C75: Ainda sem frete ao cliente e mídia
A77: 8. Contradições e erros ⚠️
A78: ⚠️ Estoque: página diz 'Esse acabou' (nenhuma variação selecionável); resumo diz 'Envio em até 24h'.
A79: ⚠️ Gramatura não informada — impossível comparar com regatas do mercado ou escrever '200 g' etc.
A80: ⚠️ FAQ define 2/1 como 'duas carreiras de frente para uma de verso' — em malharia são COLUNAS (nervuras verticais), não carreiras. Erro técnico do redator.
A81: ⚠️ A lisa (R$ 24,99) é MAIS CARA que a estonada (P24, R$ 23,99), que passa por um processo a mais (lavanderia). Preço invertido — confirmar.
A82: ⚠️ Nome da página alterna 'Slim Fit' e 'American Style' e o arquivo das fotos chama 'camiseta_regata_basica' — mesmo produto, nomenclatura solta.
A83: ⚠️ Opacidade 'mesmo em cores claras' é alegação: na foto #6 o branco deixa perceber o relevo do peito (a peça é justa) — não é transparência, mas marca o corpo.
A85: 9. Comunicação HMZT
A86: ✅ Pode usar | D86: 📣 / ⛔ Não usar
A87: "Malha canelada 2/1, 100% algodão." | D87: 📣 "A peça que o cliente prova e leva na hora" / "a venda se faz sozinha".
A88: "Elasticidade da própria nervura — ajusta ao corpo sem elastano." | D88: 📣 "Menos devolução, mais recompra", "zero reclamação por desbotamento".
A89: "Modelagem slim, estilo americano." | D89: 📣 "Domina o feed / as redes sociais", "demanda pronta".
A90: "Gola e cavas com acabamento em ribana; travetes nos pontos de tensão." | D90: 📣 "Aumenta ticket médio em qualquer venda", "faturamento recorrente".
A91: "Fabricada em Santa Catarina." | D91: 📣 "Vermelho que não desbota" (sem laudo de solidez).
D92: ⚠️ Qualquer gramatura (não informada).
A94: 10. Pendências com o fornecedor
A95: Pendência | B95: Status | C95: Responsável | D95: Resposta
A96: Gramatura (g/m²) e título do fio | B96: Aberta
A97: Reposição / estoque real por cor (página esgotada) | B97: Aberta
A98: Códigos de referência por cor | B98: Aberta
A99: Por que a lisa custa mais que a estonada (P24)? | B99: Aberta
A100: Largura da alça e cava em cm; tabela de ombro | B100: Aberta
A101: Orçamento: bordado peito pequeno + etiqueta; peça-teste de silk/DTF sobre canelado | B101: Aberta
A103: 11. Fluxo de prompts de lookbook (docs/shop-confeccao/prompts/P23-prompts.md)
A104: Foto | B104: Origem no print | C104: Formato | D104: Status
A105: F1 — Frontal com colar | B105: Origem: foto #1 da galeria (preto, frontal, corrente prata, mão esquerda no bolso) | C105: 4:5 | D105: A gerar
A106: F2 — Olhar baixo, leve 3/4 | B106: Origem: foto #2 (preto, cabeça baixa olhando para o ombro) | C106: 4:5 | D106: A gerar
A107: F3 — Detalhe gola e cava | B107: Origem: foto #3 (preto, recorte do nariz ao peito) | C107: 4:5 | D107: A gerar
A108: F4 — Olhar para o lado | B108: Origem: foto #4 (vermelho, rosto virado, mão no bolso) | C108: 4:5 | D108: A gerar
A109: F5 — Frontal, polegares nos bolsos | B109: Origem: foto #5 (vermelho, frontal, olhar na câmera) | C109: 4:5 | D109: A gerar
A110: F6 — Frontal simétrico | B110: Origem: foto #6 (branco, frontal, mãos nos bolsos) | C110: 4:5 | D110: A gerar
A111: F7 — 3/4 segurando a barra | B111: Origem: foto #7 (branco, 3/4, cabeça inclinada, mãos na barra) | C111: 4:5 | D111: A gerar
A112: F8 — Detalhe gola e ombro (centralizado) | B112: Origem: foto #8 (branco, recorte dos lábios ao peito) | C112: 4:5 | D112: A gerar
...

Sheet P24
A1: P24 — Regata Estonada Canelada 2/1 Slim Fit (Stone Wash)
A3: 1. Identificação
A4: Código HMZT | B4: HMZT-P24-SLM-CAN21SW
A5: Fornecedor | B5: Lunfe Malhas — fabricação própria, Itajaí-SC
A6: Referência | B6: 7896139148606 (EAN-13)
A7: URL | B7: lunfemalhas.com.br/regata-estonada-canelada-atacado-stone-wash-lunfe
A8: Categoria no site | B8: Camisetas › Masculino › Regatas
A9: Linha HMZT recomendada | B9: Regatas / Verão — Vintage (drop streetwear, lavada)
A10: Estoque | B10: 🔴 'Esse acabou' na página; FAQ avisa que a reposição da estonada é lenta (lavanderia)
A11: Descritor canônico (IA) | B11: Regata masculina slim fit em malha canelada 2/1 de algodão lavada com pedras (stone wash): cor desbotada irregular, nervuras com claros e escuros, viés da gola e das cavas com borda mais clara e gasta. Gola careca alta, cavas moderadas, barra reta no quadril. Fosca, toque macio. Peça lisa.
A13: 2. Especificação técnica
A14: Item | B14: Valor | C14: Fonte
A15: Tipo | B15: Regata masculina (sem manga)
A16: Malha | B16: Canelada rib knit 2/1 (mesma base da P23)
A17: Composição | B17: 100% algodão
A18: Gramatura | B18: Não informada
A19: Processo | B19: Estonagem em lavanderia industrial (stone wash)
A20: Toque | B20: 'Peletizado', 'ultra macio', 'aveludado'
A21: Modelagem | B21: Slim fit atlético
A22: Gola | B22: Careca, reforçada, com efeito desgastado
A23: Cavas | B23: Acabamento limpo com viés de ribana
A24: Reforços | B24: Travetes nos pontos de tensão
A25: Tratamentos | B25: Amaciamento por estonagem; pré-encolhida pelo processo
A26: Encolhimento | B26: 'Zero pós-compra'
... A30: Modelo das fotos | B30: 1,84 m · 84 kg · veste M
A32: 3. Tabela de medidas (cm)
A33: Tamanho | B33: Comprimento | C33: Largura | D33: Cavas
A34: P | B34: 68 | C34: 46 | D34: 22
A35: M | B35: 70 | C35: 48 | D35: 23
A36: G | B36: 72 | C36: 50 | D36: 24
A37: GG | B37: 74 | C37: 52 | D37: 25
A38: EG | B38: 76 | C38: 54 | D38: 26
A39: Em cm, ± 1–2 cm, peça pré-encolhida. Tabela idêntica à P23 (M = 70 × 48, cava 23). ⚠️ Faltam largura de alça e barra; gramatura não informada.
A40: Modelo das fotos: 1,84 m · 84 kg · veste M
A42: 4. Cores disponíveis
A43: Cor | B43: Código HMZT | C43: Ref. fornecedor | D43: Observação
A44: Azul | B44: AZU | C44: — (sem ref.) | D44: Fotos #1–#2 — azul cobalto desbotado
A45: Cinza | B45: CIN | C45: — (sem ref.) | D45: Fotos #3–#5 — grafite lavado
A46: Bordô | B46: BDO | C46: — (sem ref.) | D46: Fotos #6–#7 — lê como malva/ameixa desbotado, bem mais claro que um bordô
A47: Verde | B47: VRD | C47: — (sem ref.) | D47: Fotos #8–#9 — verde oliva/militar lavado
A48: 4 cores, todas fotografadas. Cor e desgaste variam peça a peça (efeito da lavagem) — o cliente final pode receber tom diferente da foto. Sem código de referência por cor.
A50: 5. Personalização (preço sempre sob orçamento)
A51: Técnica | B51: Detalhe | C51: Mínimo
A52: Bordado | B52: Peito pequeno — 🟢 melhor opção; bordar DEPOIS da lavagem (peça pronta) | C52: 20 pç
A53: Silk base d'água | B53: ⚠️ nervura + superfície lavada = impressão irregular; testar | C53: 20 pç
A54: DTF | B54: ⚠️ filme sobre malha elástica e lavada tende a trincar/descolar; só peça-teste | C54: 20 pç
A55: Estampa ANTES da estonagem | B55: ⚠️ Não fazer: pedras e lavagem desgastam e soltam a tinta (salvo efeito 'vintage' intencional, com teste) | C55: —
A56: Etiqueta private label | B56: Interna + tag | C56: 20 pç
A57: Preço | B57: Sob orçamento | C57: —
A59: 6. Preços do fornecedor (desconto progressivo)
A60: Preço base (R$) | B60: 23.99
A61: Faixa | B61: Peças | C61: Desconto | D61: Preço unitário | E61: Preço + Pix
A62: Faixa 1 | B62: 20–40 | C62: ='Regras Fornecedor'!$D$4 | D62: =ROUND($B$60*(1-C62),2) | E62: =ROUND(D62*(1-'Regras Fornecedor'!$B$10),2)
A63: Faixa 2 | B63: 40–80 | C63: ='Regras Fornecedor'!$D$5 | D63: =ROUND($B$60*(1-C63),2) | E63: =ROUND(D63*(1-'Regras Fornecedor'!$B$10),2)
A64: Faixa 3 | B64: 80–100 | C64: ='Regras Fornecedor'!$D$6 | D64: =ROUND($B$60*(1-C64),2) | E64: =ROUND(D64*(1-'Regras Fornecedor'!$B$10),2)
A65: Faixa 4 | B65: 100–300 | C65: ='Regras Fornecedor'!$D$7 | D65: =ROUND($B$60*(1-C65),2) | E65: =ROUND(D65*(1-'Regras Fornecedor'!$B$10),2)
A66: Faixa 5 | B66: 300–999 | C66: ='Regras Fornecedor'!$D$8 | D66: =ROUND($B$60*(1-C66),2) | E66: =ROUND(D66*(1-'Regras Fornecedor'!$B$10),2)
A68: 7. Custo HMZT e margem (lote de 20 peças, Pix)
A69: Peça (20 pç, Pix) | B69: =E62
A70: Personalização + etiqueta + tag (R$/pç) | B70: 8 | C70: Estimativa HMZT — trocar pelo orçamento real
A71: Frete rateado + embalagem (R$/pç) | B71: 4 | C71: Estimativa HMZT — trocar pelo orçamento real
A72: Custo unitário estimado | B72: =SUM(B69:B71)
A73: Preço de venda HMZT (R$) | B73: 99 | C73: Sugestão do dossiê — ajustar
A74: Impostos + gateway (% do preço) | B74: 0 | C74: A preencher (Simples + taxa Asaas)
A75: Margem bruta (R$) | B75: =B73-B72
A76: Margem bruta (%) | B76: =IF(B73=0,0,(B73-B72)/B73)
A77: Margem após impostos/gateway (%) | B77: =IF(B73=0,0,(B73*(1-B74)-B72)/B73) | C77: Ainda sem frete ao cliente e mídia
A79: 8. Contradições e erros ⚠️
A80: ⚠️ Preço invertido: a estonada (R$ 23,99) custa MENOS que a lisa P23 (R$ 24,99), apesar de ter uma etapa extra de lavanderia.
A81: ⚠️ 'Toque peletizado' não é termo técnico claro — 'peletizado' costuma remeter a bolinhas (pilling). Pedir explicação; não usar.
A82: ⚠️ 'Nenhuma unidade é igual à outra' (📣 como charme) = ⚠️ risco no e-commerce: a foto não garante o tom recebido.
A83: ⚠️ Estoque: 'Esse acabou' na página + resumo 'envio em até 24h' + FAQ diz que reposição demora.
A84: ⚠️ Nome da cor 'Bordô' não bate com a foto (malva/ameixa claro desbotado).
A85: ⚠️ Mesmo erro técnico da P23 sobre 'carreiras' na definição de 2/1.
A86: ⚠️ 'A concorrência não tem esse acabamento' — alegação sem prova; regata canelada estonada é comum no mercado.
A88: 9. Comunicação HMZT
A89: ✅ Pode usar | D89: 📣 / ⛔ Não usar
A90: "Malha canelada 2/1, 100% algodão, lavada com pedras (stone wash)." | D90: 📣 "Toque peletizado ultra macio".
A91: "Efeito vintage — cada peça tem um desgaste único." (com aviso de variação de tom) | D91: 📣 "Aparência de marca de boutique", "a concorrência não tem".
A92: "Pré-encolhida no processo de lavanderia." | D92: 📣 "Recompra garantida", "fideliza", "quem compra uma cor volta pelas outras".
A93: "Modelagem slim, ajustada ao corpo." | D93: 📣 "Encolhimento zero" (usar 'pré-encolhida').
A94: "Fabricada em Santa Catarina." | D94: 📣 "Blinda a margem", "margem de moda premium".
A96: 10. Pendências com o fornecedor
A97: Pendência | B97: Status | C97: Responsável | D97: Resposta
A98: Gramatura e fio (é a mesma malha da P23?) | B98: Aberta
A99: Reposição e prazo de lavanderia | B99: Aberta
A100: Faixa de variação de tom aceitável por lote (pedir amostra de 2–3 peças da mesma cor) | B100: Aberta
A101: Explicar 'toque peletizado' | B101: Aberta
A102: Por que custa menos que a lisa? | B102: Aberta
A103: Orçamento de bordado pós-lavagem + etiqueta | B103: Aberta
A105: 11. Fluxo de prompts de lookbook (docs/shop-confeccao/prompts/P24-prompts.md)
A106: Foto | B106: Origem no print | C106: Formato | D106: Status
A107: F1 — 3/4 olhar para fora | B107: Origem: foto #1 (azul, corpo levemente 3/4, rosto virado) | C107: 4:5 | D107: A gerar
A108: F2 — Detalhe gola lavada | B108: Origem: foto #2 (azul, recorte dos lábios ao peito) | C108: 4:5 | D108: A gerar
A109: F3 — Frontal, cabeça inclinada | B109: Origem: foto #3 (cinza, frontal, olhar na câmera) | C109: 4:5 | D109: A gerar
A110: F4 — Frontal olhar lateral | B110: Origem: foto #4 (cinza, rosto para a direita da câmera) | C110: 4:5 | D110: A gerar
A111: F5 — Detalhe cava e ombro | B111: Origem: foto #5 (cinza, recorte do nariz ao peito) | C111: 4:5 | D111: A gerar
A112: F6 — Frontal mãos nos bolsos | B112: Origem: foto #6 (bordô/malva, frontal) | C112: 4:5 | D112: A gerar
A113: F7 — Detalhe gola (malva) | B113: Origem: foto #7 (bordô/malva, recorte dos lábios ao peito) | C113: 4:5 | D113: A gerar
A114: F8 — Frontal segurando a barra | B114: Origem: foto #8 (verde, frontal, mão na barra) | C114: 4:5 | D114: A gerar
...

Sheet P25
A1: P25 — Calça Moletom 3 Cabos 320g Felpada Confort Fit
A3: 1. Identificação
A4: Código HMZT | B4: HMZT-P25-CNF-MOL320
A5: Fornecedor | B5: Lunfe Malhas — fabricação própria, Itajaí-SC
A6: Referência | B6: 7893697799578 (EAN-13)
A7: URL | B7: lunfemalhas.com.br/calca-moletom-3-cabos-320g-felpada-atacado-lunfe
A8: Categoria no site | B8: Inverno
A9: Linha HMZT recomendada | B9: Inverno Heavy — conjunto com o moletom P26 (calça avulsa como complemento)
A10: Estoque | B10: ⚠️ 'Disponibilidade: Imediata' e 'Esse acabou' na mesma página; FAQ: '4 cores em estoque, despacho 24h'
A11: Descritor canônico (IA) | B11: Calça de moletom masculina confort/jogger em moletom 3 cabos 320 g, felpado por dentro, cós largo com elástico e cordão cru, falsa braguilha pespontada, bolsos laterais inclinados, recorte frontal até o joelho, perna afunilada terminando em punho de ribana no tornozelo. Fosca, encorpada. Peça lisa.
A13: 2. Especificação técnica
A14: Item | B14: Valor | C14: Fonte
A15: Composição | B15: 50% algodão + 50% poliéster
A16: Construção | B16: Moletom 3 cabos (triple ply) com felpado interno
A17: Gramatura | B17: 320 g/m² (heavyweight)
A18: Modelagem | B18: Confort fit 'levemente solta' — nas fotos: jogger com perna afunilada
A19: Cintura | B19: Elástica embutida em cós largo + cordão cru de ajuste (saída por 2 ilhoses)
A20: Bolsos | B20: Laterais funcionais (profundidade para celular); sem bolso traseiro visível nas fotos
A21: Barra | B21: Punho em ribana canelada
A22: Detalhes vistos nas fotos | B22: Falsa braguilha pespontada; recorte frontal do bolso ao joelho + recorte de joelho
A23: Acabamentos | B23: Costuras reforçadas; overlock nas costuras internas
A24: Tratamentos | B24: Pré-encolhimento industrial; fixação de cor de alta solidez
A25: Opacidade | B25: '100% opaca em qualquer posição e cor'
A26: Joelho | B26: 'Resiste ao embolsamento'
... A30: Modelo das fotos | B30: 1,84 m · 84 kg · veste M (fotos sem rosto)
A32: 3. Tabela de medidas (cm)
A33: Tamanho | B33: Cintura (relaxada) | C33: Quadril | D33: Comprimento | E33: Barra
A34: P | B34: 36 | C34: 50 | D34: 100 | E34: 16
A35: M | B35: 39 | C35: 53 | D35: 103 | E35: 17
A36: G | B36: 42 | C36: 56 | D36: 106 | E36: 18
A37: GG | B37: 45 | C37: 59 | D37: 109 | E37: 19
A38: ⚠️ Em cm, ± 2 cm. Cintura medida com elástico relaxado, em meia-volta (M 39 ≈ 78 cm de volta); cordão dá ± 3 cm. Quadril e barra também em meia-volta (M: quadril ≈ 106 cm, punho ≈ 34 cm). Comprimento = lateral total. FALTAM gancho (dianteiro/traseiro), entreperna, coxa e joelho — sem eles o provador online fica fraco. Sem tamanho EG, enquanto o moletom P26 vai até EG.
A39: Modelo das fotos: 1,84 m · 84 kg · veste M
A41: 4. Cores disponíveis
A42: Cor | B42: Código HMZT | C42: Ref. fornecedor | D42: Observação
A43: Preto | B43: PRT | C43: CML-PRT | D43: Fotos #1–#4
A44: Marinho | B44: MAR | C44: CML-MRN | D44: Fotos #7–#9
A45: Bege | B45: BGE | C45: CML-BGE | D45: Fotos #5–#6 — ⚠️ nas fotos é caramelo/mostarda-camelo, bem mais saturado que 'bege'
A46: Chumbo | B46: CHU | C46: CML-CHM | D46: Sem foto
A47: 4 cores com referência do fornecedor. ⚠️ O texto diz que as cores 'coincidem com a grade do Moletom Gola Careca 3 Cabos' — mas o P26 tem Preto, Branco, Marinho, Vermelho, Terracota e Azul Claro. Só Preto e Marinho formam conjunto de verdade.
A49: 5. Personalização (preço sempre sob orçamento)
A50: Técnica | B50: Detalhe | C50: Mínimo
A51: Bordado | B51: Cintura frontal (logo pequeno) — 🟢 recomendado; lateral da perna | C51: 20 pç
A52: Silk | B52: Lateral da perna — ⚠️ texto cita 'bolso traseiro', que não aparece nas fotos | C52: 20 pç
A53: DTF | B53: Full color, lateral da perna | C53: 20 pç
A54: Etiqueta private label | B54: Interna + tag externa na cintura | C54: 20 pç
A55: Embalagem customizada | B55: Conjunto moletom + calça | C55: 50 pç
